Workbook
Name ListaEquipos: '[1]herramientas mat transp y mano'!$A$2:$A$215
Name ListaMateriales: '[1]herramientas mat transp y mano'!$E$2:$E$149
Name ListaProfesiones: '[1]herramientas mat transp y mano'!$M$2:$M$137
Name ListaTransporte: '[1]herramientas mat transp y mano'!$I$2:$I$26

Sheet herramientas mat transp y mano
A1: EQUIPOS Y HERRAMIENTAS | B1: TARIFA | C1: TARIFA +25% | E1: MATERIALES | F1: PRECIO | G1: PRECIO +25% | I1: TRANSPORTE | J1: TARIFA | K1: Columna1 | M1: PROFESIÓN | N1: NIVEL | O1: VALOR/DÍA
A2: Acarreo por km | B2: 65000 | C2: =B2*1.25 -> 81250 | E2: Abono organico x M2 | F2: 5000 | G2: =F2*1.25 -> 6250 | I2: Acarreo por km | J2: 65000 | K2: =IF(J2="",0,J2*1.25) -> 81250 | M2: ALBAÑIL | N2: 4 | O2: =IFERROR(INDEX('tabla salarial'!$AS$4:$AS$9,MATCH(N2,'tabla salarial'!$AT$4:$AT$9,0)),0) -> 407197.8
A3: Aguja Capotera | B3: 1000 | C3: =B3*1.25 -> 1250 | E3: Abrasivo aprobado | G3: =F3*1.25 -> 0 | I3: Buseta | K3: =IF(J3="",0,J3*1.25) -> 0 | M3: ALINEADOR DE TUBERÍAS | N3: 5 | O3: =IFERROR(INDEX('tabla salarial'!$AS$4:$AS$9,MATCH(N3,'tabla salarial'!$AT$4:$AT$9,0)),0) -> 443956.94
A4: Alicate diablo | B4: 500 | C4: =B4*1.25 -> 625 | E4: Aceite 15w40 | F4: 85000 | G4: =F4*1.25 -> 106250 | I4: Buseta Acpm | J4: 600000 | K4: =IF(J4="",0,J4*1.25) -> 750000 | M4: AMBIENTAL | N4: 5 | O4: =IFERROR(INDEX('tabla salarial'!$AS$4:$AS$9,MATCH(N4,'tabla salarial'!$AT$4:$AT$9,0)),0) -> 443956.94
A5: Alicate machosolo | B5: 3000 | C5: =B5*1.25 -> 3750 | E5: Aceite 4t gal | F5: 85000 | G5: =F5*1.25 -> 106250 | I5: cama baja | K5: =IF(J5="",0,J5*1.25) -> 0 | M5: ANALISTA DE GESTIÓN DE MANTENIMIENTO | N5: 3 | O5: =IFERROR(INDEX('tabla salarial'!$AS$4:$AS$9,MATCH(N5,'tabla salarial'!$AT$4:$AT$9,0)),0) -> 371571.33
A6: Alicate universal | B6: 500 | C6: =B6*1.25 -> 625 | E6: Aceite lubricante | F6: 65000 | G6: =F6*1.25 -> 81250 | I6: camion cinterna | J6: 1500000 | K6: =IF(J6="",0,J6*1.25) -> 1875000 | M6: ANDAMIERO | N6: 4 | O6: =IFERROR(INDEX('tabla salarial'!$AS$4:$AS$9,MATCH(N6,'tabla salarial'!$AT$4:$AT$9,0)),0) -> 407197.8
A7: Almadana 3" Bronce | B7: 3000 | C7: =B7*1.25 -> 3750 | E7: Acero 60000 psi kg | F7: 6350 | G7: =F7*1.25 -> 7937.5 | I7: Camión doble cabina | J7: 550000 | K7: =IF(J7="",0,J7*1.25) -> 687500 | M7: ANDAMIERO 1 | N7: 4 | O7: =IFERROR(INDEX('tabla salarial'!$AS$4:$AS$9,MATCH(N7,'tabla salarial'!$AT$4:$AT$9,0)),0) -> 407197.8
A8: Almadana 6" Bronce | B8: 6000 | C8: =B8*1.25 -> 7500 | E8: Acero de refuerzo G-60 figurado | F8: 4341 | G8: =F8*1.25 -> 5426.25 | I8: Camion Grua | J8: 3650000 | K8: =IF(J8="",0,J8*1.25) -> 4562500 | M8: ANDAMIERO 1A | N8: 5 | O8: =IFERROR(INDEX('tabla salarial'!$AS$4:$AS$9,MATCH(N8,'tabla salarial'!$AT$4:$AT$9,0)),0) -> 443956.94
A9: Almadana en bronce | B9: 450 | C9: =B9*1.25 -> 562.5 | E9: Acpm Galon | F9: 11500 | G9: =F9*1.25 -> 14375 | I9: Camion Sisterna | J9: 1500000 | K9: =IF(J9="",0,J9*1.25) -> 1875000 | M9: APAREJADOR | N9: 3 | O9: =IFERROR(INDEX('tabla salarial'!$AS$4:$AS$9,MATCH(N9,'tabla salarial'!$AT$4:$AT$9,0)),0) -> 371571.33
A10: almadana x6 lb | B10: 20000 | C10: =B10*1.25 -> 25000 | E10: Adoquín de concreto o arcilla | F10: 2750 | G10: =F10*1.25 -> 3437.5 | I10: Concretadora Bulto y Medio Acpm | J10: 600000 | K10: =I1:K10=IF(J10="",0,J10*1.25) -> 0 | M10: APAREJADOR DE GRÚA / APAREJADOR DE CARGAS / APAREJADOR DE EQUIPOS DE IZAJE* | N10: 2 | O10: =IFERROR(INDEX('tabla salarial'!$AS$4:$AS$9,MATCH(N10,'tabla salarial'!$AT$4:$AT$9,0)),0) -> 355821.88
A11: Andamios Layher | B11: 135000 | C11: =B11*1.25 -> 168750 | E11: Adoquín tipo corbatin | F11: 2200 | G11: =F11*1.25 -> 2750 | I11: mini cargador | J11: 840000 | K11: =IF(J11="",0,J11*1.25) -> 1050000 | M11: AUXILIAR ADMINISTRATIVO | N11: 2 | O11: =IFERROR(INDEX('tabla salarial'!$AS$4:$AS$9,MATCH(N11,'tabla salarial'!$AT$4:$AT$9,0)),0) -> 355821.88
A12: Arnés de seguridad y Erlingas | B12: 9000 | C12: =B12*1.25 -> 11250 | E12: Adoquin tolete | F12: 1800 | G12: =F12*1.25 -> 2250 | I12: minicargador | J12: 840000 | K12: =IF(J12="",0,J12*1.25) -> 1050000 | M12: AUXILIAR AMBIENTAL | N12: 3 | O12: =IFERROR(INDEX('tabla salarial'!$AS$4:$AS$9,MATCH(N12,'tabla salarial'!$AT$4:$AT$9,0)),0) -> 371571.33
A13: aspiradora industrial | B13: 60000 | C13: =B13*1.25 -> 75000 | E13: Agua m3 | F13: 6000 | G13: =F13*1.25 -> 7500 | I13: moto nieveladora | J13: 1820000 | K13: =IF(J13="",0,J13*1.25) -> 2275000 | M13: AUXILIAR CIVIL | N13: 1 | O13: =IFERROR(INDEX('tabla salarial'!$AS$4:$AS$9,MATCH(N13,'tabla salarial'!$AT$4:$AT$9,0)),0) -> 382109.06
A14: Avisos de seguridad | B14: 1000 | C14: =B14*1.25 -> 1250 | E14: Alambre Galvanizado 14 - kilo | F14: 14000 | G14: =F14*1.25 -> 17500 | I14: Moto niveladora | J14: 1820000 | K14: =IF(J14="",0,J14*1.25) -> 2275000 | M14: AUXILIAR DE ASEO Y CAFETERIA | N14: 1 | O14: =IFERROR(INDEX('tabla salarial'!$AS$4:$AS$9,MATCH(N14,'tabla salarial'!$AT$4:$AT$9,0)),0) -> 382109.06
A15: Azadon | B15: 700 | C15: =B15*1.25 -> 875 | E15: Alambre HG calibre 14 | F15: 14000 | G15: =F15*1.25 -> 17500 | I15: pavimentadora | J15: 4000000 | K15: =IF(J15="",0,J15*1.25) -> 5000000 | M15: AUXILIAR DE ENFERMERÍA | N15: 3 | O15: =IFERROR(INDEX('tabla salarial'!$AS$4:$AS$9,MATCH(N15,'tabla salarial'!$AT$4:$AT$9,0)),0) -> 371571.33
A16: Balde concretero | B16: 500 | C16: =B16*1.25 -> 625 | E16: Alambre negro para amarre | F16: 7592 | G16: =F16*1.25 -> 9490 | I16: retro excavadora de llanta | J16: 1330000 | K16: =IF(J16="",0,J16*1.25) -> 1662500 | M16: AUXILIAR DE INVENTARIOS | N16: 2 | O16: =IFERROR(INDEX('tabla salarial'!$AS$4:$AS$9,MATCH(N16,'tabla salarial'!$AT$4:$AT$9,0)),0) -> 355821.88
A17: Baldes Asfalto | B17: 12000 | C17: =B17*1.25 -> 15000 | E17: ARENA DE SANDBLASTING TIPO SOGAMOSO | F17: 11934 | G17: =F17*1.25 -> 14917.5 | I17: Retroexcavadora con llantas | J17: 190000 | K17: =IF(J17="",0,J17*1.25) -> 237500 | M17: AUXILIAR DE MATERIALES | N17: 3 | O17: =IFERROR(INDEX('tabla salarial'!$AS$4:$AS$9,MATCH(N17,'tabla salarial'!$AT$4:$AT$9,0)),0) -> 371571.33
A18: Banco figuracion | B18: 3000 | C18: =B18*1.25 -> 3750 | E18: Arena fina seca para sello de juntas | F18: 21000 | G18: =F18*1.25 -> 26250 | I18: Retroexcavadora de llantas | J18: 1330000 | K18: =IF(J18="",0,J18*1.25) -> 1662500 | M18: AYUDANTE CADENERO | N18: 2 | O18: =IFERROR(INDEX('tabla salarial'!$AS$4:$AS$9,MATCH(N18,'tabla salarial'!$AT$4:$AT$9,0)),0) -> 355821.88
A19: Barra | B19: 1500 | C19: =B19*1.25 -> 1875 | E19: Arena para cama/capa de soporte | F19: 31000 | G19: =F19*1.25 -> 38750 | I19: Retroexcavadora de oruga | J19: 322000 | K19: =IF(J19="",0,J19*1.25) -> 402500 | M19: AYUDANTE DE BODEGA O BODEGUERO | N19: 2 | O19: =IFERROR(INDEX('tabla salarial'!$AS$4:$AS$9,MATCH(N19,'tabla salarial'!$AT$4:$AT$9,0)),0) -> 355821.88
A20: bichiroque | B20: 1000 | C20: =B20*1.25 -> 1250 | E20: Aspersores | F20: 34900 | G20: =F20*1.25 -> 43625 | I20: Transporte de equipo oruga | J20: 4500000 | K20: =IF(J20="",0,J20*1.25) -> 5625000 | M20: AYUDANTE DE OBRA CIVIL | N20: 2 | O20: =IFERROR(INDEX('tabla salarial'!$AS$4:$AS$9,MATCH(N20,'tabla salarial'!$AT$4:$AT$9,0)),0) -> 355821.88
A21: Bomba para concreto m3 | B21: 70000 | C21: =B21*1.25 -> 87500 | E21: Avisos de seguridad | F21: 500 | G21: =F21*1.25 -> 625 | I21: traslado de equipos | J21: 1650000 | K21: =IF(J21="",0,J21*1.25) -> 2062500 | M21: AYUDANTE DE PINTURA | N21: 2 | O21: =IFERROR(INDEX('tabla salarial'!$AS$4:$AS$9,MATCH(N21,'tabla salarial'!$AT$4:$AT$9,0)),0) -> 355821.88
A22: Bomba para fumigar | B22: 5000 | C22: =B22*1.25 -> 6250 | E22: base asfáltica o base negra m3 | F22: 390000 | G22: =F22*1.25 -> 487500 | I22: trasporte de equipo | J22: 4500000 | K22: =IF(J22="",0,J22*1.25) -> 5625000 | M22: AYUDANTE ELECTRICISTA | N22: 2 | O22: =IFERROR(INDEX('tabla salarial'!$AS$4:$AS$9,MATCH(N22,'tabla salarial'!$AT$4:$AT$9,0)),0) -> 355821.88
... A25: Buldron | B25: 5000 | C25: =B25*1.25 -> 6250 | E25: Bolsa para Basura | F25: 1500 | G25: =F25*1.25 -> 1875 | I25: volqueta 14 M3 | J25: 1250000 | K25: =IF(J25="",0,J25*1.25) -> 1562500 | M25: AYUDANTE MECANICO | N25: 4 | O25: =IFERROR(INDEX('tabla salarial'!$AS$4:$AS$9,MATCH(N25,'tabla salarial'!$AT$4:$AT$9,0)),0) -> 407197.8
A26: Burro Metalico Hechizo Diferencial | B26: 5000 | C26: =B26*1.25 -> 6250 | E26: Bordillo/sardinel/confinamiento | G26: =F26*1.25 -> 0 | I26: Volqueta de 14 m³ | J26: 1350000 | K26: =IF(J26="",0,J26*1.25) -> 1687500 | M26: AYUDANTE MECÁNICO | N26: 2 | O26: =IFERROR(INDEX('tabla salarial'!$AS$4:$AS$9,MATCH(N26,'tabla salarial'!$AT$4:$AT$9,0)),0) -> 355821.88
A27: Burro Metalico Hechizo Tubería | B27: 3000 | C27: =B27*1.25 -> 3750 | E27: Broca Rotomartillo 1 1/4 x 12" | F27: 455000 | G27: =F27*1.25 -> 568750 | M27: AYUDANTE MECÁNICO OFF SHORE | N27: 2 | O27: =IFERROR(INDEX('tabla salarial'!$AS$4:$AS$9,MATCH(N27,'tabla salarial'!$AT$4:$AT$9,0)),0) -> 355821.88
A28: Buseta acpm | B28: 600000 | C28: =B28*1.25 -> 750000 | E28: Broca tipo pala | F28: 65000 | G28: =F28*1.25 -> 81250 | M28: AYUDANTE MTTO VEHICULOS | N28: 1 | O28: =IFERROR(INDEX('tabla salarial'!$AS$4:$AS$9,MATCH(N28,'tabla salarial'!$AT$4:$AT$9,0)),0) -> 382109.06
A29: Cabo para pala | B29: 20000 | C29: =B29*1.25 -> 25000 | E29: Broca tipo punta | F29: 65000 | G29: =F29*1.25 -> 81250 | M29: AYUDANTE PAILERÍA | N29: 2 | O29: =IFERROR(INDEX('tabla salarial'!$AS$4:$AS$9,MATCH(N29,'tabla salarial'!$AT$4:$AT$9,0)),0) -> 355821.88
A30: Caja De Herramientas | B30: 10000 | C30: =B30*1.25 -> 12500 | E30: brocha 3" | F30: 20000 | G30: =F30*1.25 -> 25000 | M30: AYUDANTE SOLDADURA | N30: 2 | O30: =IFERROR(INDEX('tabla salarial'!$AS$4:$AS$9,MATCH(N30,'tabla salarial'!$AT$4:$AT$9,0)),0) -> 355821.88
A31: Camilla primeros auxilios | B31: 3000 | C31: =B31*1.25 -> 3750 | E31: Cal | F31: 50000 | G31: =F31*1.25 -> 62500 | M31: AYUDANTE SOLDADURA* | N31: 4 | O31: =IFERROR(INDEX('tabla salarial'!$AS$4:$AS$9,MATCH(N31,'tabla salarial'!$AT$4:$AT$9,0)),0) -> 407197.8
A32: Camión doble cabina | B32: 550000 | C32: =B32*1.25 -> 687500 | E32: careta de esmerilar para casco | F32: 42000 | G32: =F32*1.25 -> 52500 | M32: AYUDANTE TUBERÍA | N32: 2 | O32: =IFERROR(INDEX('tabla salarial'!$AS$4:$AS$9,MATCH(N32,'tabla salarial'!$AT$4:$AT$9,0)),0) -> 355821.88
A33: Carpa plastica 10x6 | B33: 40000 | C33: =B33*1.25 -> 50000 | E33: Carpa plastica 4x4 | F33: 27500 | G33: =F33*1.25 -> 34375 | M33: BUZO SEGUNDA | N33: 3 | O33: =IFERROR(INDEX('tabla salarial'!$AS$4:$AS$9,MATCH(N33,'tabla salarial'!$AT$4:$AT$9,0)),0) -> 371571.33
A34: Carpa plastica 4x4 | B34: 27500 | C34: =B34*1.25 -> 34375 | E34: Carpa plastica 6x4 | F34: 30000 | G34: =F34*1.25 -> 37500 | M34: CADENERO 1 | N34: 4 | O34: =IFERROR(INDEX('tabla salarial'!$AS$4:$AS$9,MATCH(N34,'tabla salarial'!$AT$4:$AT$9,0)),0) -> 407197.8
A35: Carpa plastica 6x4 | B35: 30000 | C35: =B35*1.25 -> 37500 | E35: Carpa plastica 6x6 | F35: 32500 | G35: =F35*1.25 -> 40625 | M35: CAMARERA | N35: 1 | O35: =IFERROR(INDEX('tabla salarial'!$AS$4:$AS$9,MATCH(N35,'tabla salarial'!$AT$4:$AT$9,0)),0) -> 382109.06
A36: Carpa plastica 6x6 | B36: 32500 | C36: =B36*1.25 -> 40625 | E36: Catalizador/endurecedor | G36: =F36*1.25 -> 0 | M36: CAMARERO | N36: 2 | O36: =IFERROR(INDEX('tabla salarial'!$AS$4:$AS$9,MATCH(N36,'tabla salarial'!$AT$4:$AT$9,0)),0) -> 355821.88
A37: Carretilla | B37: 1500 | C37: =B37*1.25 -> 1875 | E37: Cemento 50 kl | F37: 38000 | G37: =F37*1.25 -> 47500 | M37: CAPATAZ | N37: 6 | O37: =IFERROR(INDEX('tabla salarial'!$AS$4:$AS$9,MATCH(N37,'tabla salarial'!$AT$4:$AT$9,0)),0) -> 555393.74
A38: cepillo de alambre bronce | B38: 3000 | C38: =B38*1.25 -> 3750 | E38: Cespedon x M2 | F38: 35000 | G38: =F38*1.25 -> 43750 | M38: CAPATAZ DE ZONAS VERDES Y ROCERIA* | N38: 4 | O38: =IFERROR(INDEX('tabla salarial'!$AS$4:$AS$9,MATCH(N38,'tabla salarial'!$AT$4:$AT$9,0)),0) -> 407197.8
A39: Chaleco reflectivo | B39: 625 | C39: =B39*1.25 -> 781.25 | E39: Cespedon x M2 | F39: 43750 | G39: =F39*1.25 -> 54687.5 | M39: CONDUCTOR | N39: 2 | O39: =IFERROR(INDEX('tabla salarial'!$AS$4:$AS$9,MATCH(N39,'tabla salarial'!$AT$4:$AT$9,0)),0) -> 355821.88
A40: cincel 3/4 x 12" | B40: 3000 | C40: =B40*1.25 -> 3750 | E40: Chaleco Reflectivo | F40: 20000 | G40: =F40*1.25 -> 25000 | M40: CONDUCTOR DE VEHÍCULO LIVIANO Y/O PASAJEROS | N40: 1 | O40: =IFERROR(INDEX('tabla salarial'!$AS$4:$AS$9,MATCH(N40,'tabla salarial'!$AT$4:$AT$9,0)),0) -> 382109.06
A41: Codal Aluminio 3 m | B41: 3000 | C41: =B41*1.25 -> 3750 | E41: cinta de enmascarar 2" rollo | F41: 14900 | G41: =F41*1.25 -> 18625 | M41: CONDUCTOR VEHÍCULO PESADO PROPIO DE LA INDUSTRIA DE MÁS DE 3 TON | N41: 3 | O41: =IFERROR(INDEX('tabla salarial'!$AS$4:$AS$9,MATCH(N41,'tabla salarial'!$AT$4:$AT$9,0)),0) -> 371571.33
A42: Codo sanitaria 6" Reutilizar | B42: 10000 | C42: =B42*1.25 -> 12500 | E42: Cinta de seguridad amarilla/negra x 500 | F42: 55000 | G42: =F42*1.25 -> 68750 | M42: CONECTOR OFF SHORE | N42: 2 | O42: =IFERROR(INDEX('tabla salarial'!$AS$4:$AS$9,MATCH(N42,'tabla salarial'!$AT$4:$AT$9,0)),0) -> 355821.88
A43: Colombianas de seguridad | B43: 1000 | C43: =B43*1.25 -> 1250 | E43: Cinta enmascarar | G43: =F43*1.25 -> 0 | M43: CONTRAMAESTRE AB EMBARCACIÓN | N43: 5 | O43: =IFERROR(INDEX('tabla salarial'!$AS$4:$AS$9,MATCH(N43,'tabla salarial'!$AT$4:$AT$9,0)),0) -> 443956.94
A44: Colombina | B44: 1000 | C44: =B44*1.25 -> 1250 | E44: Clavo de acero de 3" | F44: 15000 | G44: =F44*1.25 -> 18750 | M44: DOBLADOR | N44: 4 | O44: =IFERROR(INDEX('tabla salarial'!$AS$4:$AS$9,MATCH(N44,'tabla salarial'!$AT$4:$AT$9,0)),0) -> 407197.8
A45: comprensor de aire | B45: 25000 | C45: =B45*1.25 -> 31250 | E45: Concreto 2500 psi para solado/atraque | F45: 464823 | G45: =F45*1.25 -> 581028.75 | M45: DOCUMENTADOR | N45: 4 | O45: =IFERROR(INDEX('tabla salarial'!$AS$4:$AS$9,MATCH(N45,'tabla salarial'!$AT$4:$AT$9,0)),0) -> 407197.8
A46: Compresor de aire | B46: 25000 | C46: =B46*1.25 -> 31250 | E46: Concreto 3000 psi para estructuras/cabezales/aletas | F46: 620000 | G46: =F46*1.25 -> 775000 | M46: ELECTRICISTA 1 | N46: 4 | O46: =IFERROR(INDEX('tabla salarial'!$AS$4:$AS$9,MATCH(N46,'tabla salarial'!$AT$4:$AT$9,0)),0) -> 407197.8
A47: Concretadora | B47: 60000 | C47: =B47*1.25 -> 75000 | E47: Concreto 4000 psi para estructuras/cabezales/aletas | F47: 670000 | G47: =F47*1.25 -> 837500 | M47: ELECTRICISTA 1A | N47: 5 | O47: =IFERROR(INDEX('tabla salarial'!$AS$4:$AS$9,MATCH(N47,'tabla salarial'!$AT$4:$AT$9,0)),0) -> 443956.94
A48: Cono de seguridad | B48: 500 | C48: =B48*1.25 -> 625 | E48: Concreto con Camion Mixer m3 | F48: 550000 | G48: =F48*1.25 -> 687500 | M48: ELECTROMECÁNICO | N48: 4 | O48: =IFERROR(INDEX('tabla salarial'!$AS$4:$AS$9,MATCH(N48,'tabla salarial'!$AT$4:$AT$9,0)),0) -> 407197.8
A49: Cortatubo de 1/2 a 2" | B49: 50000 | C49: =B49*1.25 -> 62500 | E49: Confinamiento externo | G49: =F49*1.25 -> 0 | M49: ENFERMERA PROFESIONAL | N49: 6 | O49: =IFERROR(INDEX('tabla salarial'!$AS$4:$AS$9,MATCH(N49,'tabla salarial'!$AT$4:$AT$9,0)),0) -> 555393.74
A50: Cortatubo de 2 a 4" | B50: 70000 | C50: =B50*1.25 -> 87500 | E50: Corrector | F50: 2000 | G50: =F50*1.25 -> 2500 | M50: ESMERILADOR | N50: 3 | O50: =IFERROR(INDEX('tabla salarial'!$AS$4:$AS$9,MATCH(N50,'tabla salarial'!$AT$4:$AT$9,0)),0) -> 371571.33
A51: Cortatubo de 4 a 6" | B51: 100000 | C51: =B51*1.25 -> 125000 | E51: Cras | F51: 1185900 | G51: =F51*1.25 -> 1482375 | M51: GUADAÑADOR* | N51: 2 | O51: =IFERROR(INDEX('tabla salarial'!$AS$4:$AS$9,MATCH(N51,'tabla salarial'!$AT$4:$AT$9,0)),0) -> 355821.88
A52: Cúter industrial | B52: 800 | C52: =B52*1.25 -> 1000 | E52: Disco de corte 7" para metarl 1 1/16" | F52: 11500 | G52: =F52*1.25 -> 14375 | M52: HSE | N52: 6 | O52: =IFERROR(INDEX('tabla salarial'!$AS$4:$AS$9,MATCH(N52,'tabla salarial'!$AT$4:$AT$9,0)),0) -> 555393.74
A53: detector de gas | B53: 40000 | C53: =B53*1.25 -> 50000 | E53: Disco de corte para metal 4,5" 1/64 | F53: 5500 | G53: =F53*1.25 -> 6875 | M53: INSPECTOR HSE | N53: 5 | O53: =IFERROR(INDEX('tabla salarial'!$AS$4:$AS$9,MATCH(N53,'tabla salarial'!$AT$4:$AT$9,0)),0) -> 443956.94
A54: Detector de tubería | B54: 150000 | C54: =B54*1.25 -> 187500 | E54: Disco Flat 4,5 | F54: 5000 | G54: =F54*1.25 -> 6250 | M54: INSTRUMENTISTA | N54: 4 | O54: =IFERROR(INDEX('tabla salarial'!$AS$4:$AS$9,MATCH(N54,'tabla salarial'!$AT$4:$AT$9,0)),0) -> 407197.8
A55: Diferencial 2 ton | B55: 25000 | C55: =B55*1.25 -> 31250 | E55: Disco para pulir Metal 4,5" 1 1/4" | F55: 5500 | G55: =F55*1.25 -> 6875 | M55: INSTRUMENTISTA 1 | N55: 4 | O55: =IFERROR(INDEX('tabla salarial'!$AS$4:$AS$9,MATCH(N55,'tabla salarial'!$AT$4:$AT$9,0)),0) -> 407197.8
A56: Dique almacenamiento de combustibles | B56: 700 | C56: =B56*1.25 -> 875 | E56: Disco para pulir Metal 7" | F56: 11500 | G56: =F56*1.25 -> 14375 | M56: INSTRUMENTISTA 1A | N56: 5 | O56: =IFERROR(INDEX('tabla salarial'!$AS$4:$AS$9,MATCH(N56,'tabla salarial'!$AT$4:$AT$9,0)),0) -> 443956.94
A57: Dique en lamina para equipos | B57: 500 | C57: =B57*1.25 -> 625 | E57: DISCOS CLEAN STRIP | F57: 22450 | G57: =F57*1.25 -> 28062.5 | M57: JARDINERO | N57: 1 | O57: =IFERROR(INDEX('tabla salarial'!$AS$4:$AS$9,MATCH(N57,'tabla salarial'!$AT$4:$AT$9,0)),0) -> 382109.06
A58: Dique para Metalico | B58: 1000 | C58: =B58*1.25 -> 1250 | E58: discos de corte de 7" / discos diamantados o abrasivos | F58: 62000 | G58: =F58*1.25 -> 77500 | M58: LABORATORISTA | N58: 5 | O58: =IFERROR(INDEX('tabla salarial'!$AS$4:$AS$9,MATCH(N58,'tabla salarial'!$AT$4:$AT$9,0)),0) -> 443956.94
A59: Dique residuos contaminantes | B59: 500 | C59: =B59*1.25 -> 625 | E59: DISCOS FLAP | F59: 13450 | G59: =F59*1.25 -> 16812.5 | M59: MAESTRO DE OBRA CIVIL* | N59: 5 | O59: =IFERROR(INDEX('tabla salarial'!$AS$4:$AS$9,MATCH(N59,'tabla salarial'!$AT$4:$AT$9,0)),0) -> 443956.94
A60: Dobladora Manual | B60: 3000 | C60: =B60*1.25 -> 3750 | E60: Emulsión asfáltica para imprimación galon | F60: 30000 | G60: =F60*1.25 -> 37500 | M60: MARINERO AB DE EMBARCACIÓN | N60: 2 | O60: =IFERROR(INDEX('tabla salarial'!$AS$4:$AS$9,MATCH(N60,'tabla salarial'!$AT$4:$AT$9,0)),0) -> 355821.88
A61: Electrosoldador | B61: 50000 | C61: =B61*1.25 -> 62500 | E61: Emulsión para riego de liga galon | F61: 25000 | G61: =F61*1.25 -> 31250 | M61: MARINERO AJUSTADOR DE BRIDAS | N61: 2 | O61: =IFERROR(INDEX('tabla salarial'!$AS$4:$AS$9,MATCH(N61,'tabla salarial'!$AT$4:$AT$9,0)),0) -> 355821.88
A62: Entibado metalico 4x4x2 | C62: =B62*1.25 -> 0 | E62: Entibado metalico 2x4x4 | F62: 100000 | G62: =F62*1.25 -> 125000 | M62: MARINERO COCINERO EMBARCACIÓN MAYOR | N62: 3 | O62: =IFERROR(INDEX('tabla salarial'!$AS$4:$AS$9,MATCH(N62,'tabla salarial'!$AT$4:$AT$9,0)),0) -> 371571.33
A63: Equipo de topografía | C63: =B63*1.25 -> 0 | E63: espatula 3" | F63: 8000 | G63: =F63*1.25 -> 10000 | M63: MARINERO COSTANERO DE CUBIERTA | N63: 1 | O63: =IFERROR(INDEX('tabla salarial'!$AS$4:$AS$9,MATCH(N63,'tabla salarial'!$AT$4:$AT$9,0)),0) -> 382109.06
A64: Equipo topografico | B64: 500000 | C64: =B64*1.25 -> 625000 | E64: Estibado metalico 4x4x2 | F64: 100000 | G64: =F64*1.25 -> 125000 | M64: MARINERO DE CUBIERTA | N64: 2 | O64: =IFERROR(INDEX('tabla salarial'!$AS$4:$AS$9,MATCH(N64,'tabla salarial'!$AT$4:$AT$9,0)),0) -> 355821.88
A65: Equipos Oxicorte | B65: 50000 | C65: =B65*1.25 -> 62500 | E65: Excavaciones menor a 1,2 m | F65: 805421 | G65: =F65*1.25 -> 1006776.2 | M65: MARINERO DE MÁQUINAS | N65: 3 | O65: =IFERROR(INDEX('tabla salarial'!$AS$4:$AS$9,MATCH(N65,'tabla salarial'!$AT$4:$AT$9,0)),0) -> 371571.33
A66: Escalera Electrica Dieletica | B66: 25000 | C66: =B66*1.25 -> 31250 | E66: Filtro para motor T85 | F66: 22000 | G66: =F66*1.25 -> 27500 | M66: MARINERO OPERADOR | N66: 2 | O66: =IFERROR(INDEX('tabla salarial'!$AS$4:$AS$9,MATCH(N66,'tabla salarial'!$AT$4:$AT$9,0)),0) -> 355821.88
A67: Escalera tipo tijera | B67: 12500 | C67: =B67*1.25 -> 15625 | E67: Geodren planar | F67: 114000 | G67: =F67*1.25 -> 142500 | M67: MARINERO TIMONEL | N67: 3 | O67: =IFERROR(INDEX('tabla salarial'!$AS$4:$AS$9,MATCH(N67,'tabla salarial'!$AT$4:$AT$9,0)),0) -> 371571.33
A68: Escoba de cerdas duras | B68: 1000 | C68: =B68*1.25 -> 1250 | E68: Geomembra m2 | F68: 160000 | G68: =F68*1.25 -> 200000 | M68: MECÁNICO 1 | N68: 4 | O68: =IFERROR(INDEX('tabla salarial'!$AS$4:$AS$9,MATCH(N68,'tabla salarial'!$AT$4:$AT$9,0)),0) -> 407197.8
A69: Escoba de varita | B69: 20000 | C69: =B69*1.25 -> 25000 | E69: Geotextil m2 | F69: 4300 | G69: =F69*1.25 -> 5375 | M69: MECÁNICO 1A | N69: 5 | O69: =IFERROR(INDEX('tabla salarial'!$AS$4:$AS$9,MATCH(N69,'tabla salarial'!$AT$4:$AT$9,0)),0) -> 443956.94
A70: Escuadra metalica 24" | B70: 1000 | C70: =B70*1.25 -> 1250 | E70: Grapa | F70: 15900 | G70: =F70*1.25 -> 19875 | M70: MECÁNICO OFF SHORE | N70: 3 | O70: =IFERROR(INDEX('tabla salarial'!$AS$4:$AS$9,MATCH(N70,'tabla salarial'!$AT$4:$AT$9,0)),0) -> 371571.33
A71: Eslinga de 3x3 sintetica | B71: 5000 | C71: =B71*1.25 -> 6250 | E71: Grata metalica de 1/4" 7" | F71: 40000 | G71: =F71*1.25 -> 50000 | M71: MENSAJERO* | N71: 1 | O71: =IFERROR(INDEX('tabla salarial'!$AS$4:$AS$9,MATCH(N71,'tabla salarial'!$AT$4:$AT$9,0)),0) -> 382109.06
A72: Eslinga de 3x6 sintetica | B72: 5000 | C72: =B72*1.25 -> 6250 | E72: Grata metalica de 1/8" 7" | F72: 35000 | G72: =F72*1.25 -> 43750 | M72: MESERO | N72: 1 | O72: =IFERROR(INDEX('tabla salarial'!$AS$4:$AS$9,MATCH(N72,'tabla salarial'!$AT$4:$AT$9,0)),0) -> 382109.06
A73: Eslingas/aparejos certificados | B73: 40000 | C73: =B73*1.25 -> 50000 | E73: GRATA TRENZADA CIRCULAR | F73: 10750 | G73: =F73*1.25 -> 13437.5 | M73: MONTADOR 1 | N73: 4 | O73: =IFERROR(INDEX('tabla salarial'!$AS$4:$AS$9,MATCH(N73,'tabla salarial'!$AT$4:$AT$9,0)),0) -> 407197.8
A74: Eslingas/aparejos certificados 3" x 4" | C74: =B74*1.25 -> 0 | E74: GRATA TRENZADA CIRCULAR | G74: =F74*1.25 -> 0 | M74: MONTADOR 1A | N74: 5 | O74: =IFERROR(INDEX('tabla salarial'!$AS$4:$AS$9,MATCH(N74,'tabla salarial'!$AT$4:$AT$9,0)),0) -> 443956.94
A75: Estibas plasticas | B75: 1108 | C75: =B75*1.25 -> 1385 | E75: Gravilla triturada Clasificada TM 3/4 | F75: 64000 | G75: =F75*1.25 -> 80000 | M75: OBRERO | N75: 1 | O75: =IFERROR(INDEX('tabla salarial'!$AS$4:$AS$9,MATCH(N75,'tabla salarial'!$AT$4:$AT$9,0)),0) -> 382109.06
A76: Extencion electrica 100mts | B76: 15000 | C76: =B76*1.25 -> 18750 | E76: guantes antivibración | F76: 33200 | G76: =F76*1.25 -> 41500 | M76: OBRERO | N76: 1 | O76: =IFERROR(INDEX('tabla salarial'!$AS$4:$AS$9,MATCH(N76,'tabla salarial'!$AT$4:$AT$9,0)),0) -> 382109.06
A77: Extintor Co2 | B77: 1500 | C77: =B77*1.25 -> 1875 | E77: guantes de nitrilo largo | F77: 15000 | G77: =F77*1.25 -> 18750 | M77: OBRERO APICULTOR Y FUMIGADOR* | N77: 1 | O77: =IFERROR(INDEX('tabla salarial'!$AS$4:$AS$9,MATCH(N77,'tabla salarial'!$AT$4:$AT$9,0)),0) -> 382109.06
A78: Extractor de aire | B78: 15000 | C78: =B78*1.25 -> 18750 | E78: guantes quirulgico | F78: 1000 | G78: =F78*1.25 -> 1250 | M78: OBRERO CON EXPERIENCIA | N78: 2 | O78: =IFERROR(INDEX('tabla salarial'!$AS$4:$AS$9,MATCH(N78,'tabla salarial'!$AT$4:$AT$9,0)),0) -> 355821.88
A79: Flexómetro | B79: 500 | C79: =B79*1.25 -> 625 | E79: Hoga | F79: 450000 | G79: =F79*1.25 -> 562500 | M79: OBRERO DESCONTAMINACION | N79: 1 | O79: =IFERROR(INDEX('tabla salarial'!$AS$4:$AS$9,MATCH(N79,'tabla salarial'!$AT$4:$AT$9,0)),0) -> 382109.06
A80: Gato Hidraulico | B80: 2500 | C80: =B80*1.25 -> 3125 | E80: Hoja Segueta | F80: 6500 | G80: =F80*1.25 -> 8125 | M80: OFICIAL CONSTRUCCION | N80: 3 | O80: =IFERROR(INDEX('tabla salarial'!$AS$4:$AS$9,MATCH(N80,'tabla salarial'!$AT$4:$AT$9,0)),0) -> 371571.33
A81: Gps | B81: 100000 | C81: =B81*1.25 -> 125000 | E81: Ladrillo Tolete | F81: 1500 | G81: =F81*1.25 -> 1875 | M81: OFICIAL DE CONSTRUCCION | N81: 4 | O81: =IFERROR(INDEX('tabla salarial'!$AS$4:$AS$9,MATCH(N81,'tabla salarial'!$AT$4:$AT$9,0)),0) -> 407197.8
A82: Grapa Hechiza 2" | B82: 2000 | C82: =B82*1.25 -> 2500 | E82: Lapicero negro | F82: 1000 | G82: =F82*1.25 -> 1250 | M82: OFICIAL DE MÁQUINAS HASTA 3000 KW | N82: 5 | O82: =IFERROR(INDEX('tabla salarial'!$AS$4:$AS$9,MATCH(N82,'tabla salarial'!$AT$4:$AT$9,0)),0) -> 443956.94
A83: Grapa Hechiza 3" | B83: 3000 | C83: =B83*1.25 -> 3750 | E83: Lapiz Rojo | F83: 1000 | G83: =F83*1.25 -> 1250 | M83: OFICIAL DE OBRA CIVIL* | N83: 4 | O83: =IFERROR(INDEX('tabla salarial'!$AS$4:$AS$9,MATCH(N83,'tabla salarial'!$AT$4:$AT$9,0)),0) -> 407197.8
A84: Grapa Hechiza 4" | B84: 4000 | C84: =B84*1.25 -> 5000 | E84: Lija Industrial | F84: 18000 | G84: =F84*1.25 -> 22500 | M84: OFICIAL DE PUENTE | N84: 6 | O84: =IFERROR(INDEX('tabla salarial'!$AS$4:$AS$9,MATCH(N84,'tabla salarial'!$AT$4:$AT$9,0)),0) -> 555393.74
A85: Grapa Hechiza 6" | B85: 6000 | C85: =B85*1.25 -> 7500 | E85: Limpiador PVC | F85: 40000 | G85: =F85*1.25 -> 50000 | M85: OFICIAL I | N85: 3 | O85: =IFERROR(INDEX('tabla salarial'!$AS$4:$AS$9,MATCH(N85,'tabla salarial'!$AT$4:$AT$9,0)),0) -> 371571.33
A86: Grillete 7/8 | B86: 5000 | C86: =B86*1.25 -> 6250 | E86: Listón de madera 2 x 1 x 3 | F86: 20000 | G86: =F86*1.25 -> 25000 | M86: OFICIAL PUENTE HASTA 3000 TRB | N86: 5 | O86: =IFERROR(INDEX('tabla salarial'!$AS$4:$AS$9,MATCH(N86,'tabla salarial'!$AT$4:$AT$9,0)),0) -> 443956.94
... A104: Llave expansiva de 48" | B104: 6000 | C104: =B104*1.25 -> 7500 | E104: Pintura en aerosol | F104: 20000 | G104: =F104*1.25 -> 25000 | M104: OPERADOR MONTACARGAS | N104: 4 | O104: =IFERROR(INDEX('tabla salarial'!$AS$4:$AS$9,MATCH(N104,'tabla salarial'!$AT$4:$AT$9,0)),0) -> 407197.8
A105: Llave para tubo 14" | B105: 2000 | C105: =B105*1.25 -> 2500 | E105: Placas testigo 0,10 × 0,10 m | G105: =F105*1.25 -> 0 | M105: OPERADOR PLANTA DE CONCRETO | N105: 4 | O105: =IFERROR(INDEX('tabla salarial'!$AS$4:$AS$9,MATCH(N105,'tabla salarial'!$AT$4:$AT$9,0)),0) -> 407197.8
A106: Llave para tubo 18" | B106: 2000 | C106: =B106*1.25 -> 2500 | E106: Plastico negro | F106: 9500 | G106: =F106*1.25 -> 11875 | M106: OPERADOR PLANTA ELÉCTRICA | N106: 1 | O106: =IFERROR(INDEX('tabla salarial'!$AS$4:$AS$9,MATCH(N106,'tabla salarial'!$AT$4:$AT$9,0)),0) -> 382109.06
A107: Llave para tubo 24" | B107: 4000 | C107: =B107*1.25 -> 5000 | E107: Plástico negro | F107: 9500 | G107: =F107*1.25 -> 11875 | M107: OPERADOR RETROLLANTAS | N107: 4 | O107: =IFERROR(INDEX('tabla salarial'!$AS$4:$AS$9,MATCH(N107,'tabla salarial'!$AT$4:$AT$9,0)),0) -> 407197.8
A108: Llave para tubo 8" | B108: 1000 | C108: =B108*1.25 -> 1250 | E108: Plástico/lona de protección | G108: =F108*1.25 -> 0 | M108: OPERADOR VEHICULO PESADO | N108: 4 | O108: =IFERROR(INDEX('tabla salarial'!$AS$4:$AS$9,MATCH(N108,'tabla salarial'!$AT$4:$AT$9,0)),0) -> 407197.8
A109: Llave para tubo Tipo Cremallera 36" | B109: 7000 | C109: =B109*1.25 -> 8750 | E109: Polisombra 100m | F109: 12000 | G109: =F109*1.25 -> 15000 | M109: PAILERO 1 | N109: 4 | O109: =IFERROR(INDEX('tabla salarial'!$AS$4:$AS$9,MATCH(N109,'tabla salarial'!$AT$4:$AT$9,0)),0) -> 407197.8
A110: Machete | B110: 1500 | C110: =B110*1.25 -> 1875 | E110: Prueba de Concreto | F110: 60000 | G110: =F110*1.25 -> 75000 | M110: PAILERO 1A | N110: 5 | O110: =IFERROR(INDEX('tabla salarial'!$AS$4:$AS$9,MATCH(N110,'tabla salarial'!$AT$4:$AT$9,0)),0) -> 443956.94
A111: Machete con funda | B111: 1500 | C111: =B111*1.25 -> 1875 | E111: Puntilla de 2,5" | F111: 9500 | G111: =F111*1.25 -> 11875 | M111: PINTOR | N111: 3 | O111: =IFERROR(INDEX('tabla salarial'!$AS$4:$AS$9,MATCH(N111,'tabla salarial'!$AT$4:$AT$9,0)),0) -> 371571.33
A112: Mampara en aluminio | B112: 3000 | C112: =B112*1.25 -> 3750 | E112: Puntilla de 3,5" | F112: 9500 | G112: =F112*1.25 -> 11875 | M112: RECEPCIONISTA* | N112: 1 | O112: =IFERROR(INDEX('tabla salarial'!$AS$4:$AS$9,MATCH(N112,'tabla salarial'!$AT$4:$AT$9,0)),0) -> 382109.06
A113: Marco Segueta | B113: 700 | C113: =B113*1.25 -> 875 | E113: RECUBRIMIENTO SIGMALINE 2500 BASE + CATALIZADOR m2 | F113: 196721 | G113: =F113*1.25 -> 245901.25 | M113: RESCATISTA DE ALTURAS | N113: 5 | O113: =IFERROR(INDEX('tabla salarial'!$AS$4:$AS$9,MATCH(N113,'tabla salarial'!$AT$4:$AT$9,0)),0) -> 443956.94
A114: Martillo | B114: 700 | C114: =B114*1.25 -> 875 | E114: Recubrimiento TPT-STD-013 | G114: =F114*1.25 -> 0 | M114: RESCATISTA DE ALTURAS | N114: 2 | O114: =IFERROR(INDEX('tabla salarial'!$AS$4:$AS$9,MATCH(N114,'tabla salarial'!$AT$4:$AT$9,0)),0) -> 355821.88
A115: Martillo demoledor neumático/eléctrico | B115: 80000 | C115: =B115*1.25 -> 100000 | E115: rodilleras | F115: 40000 | G115: =F115*1.25 -> 50000 | M115: RETROCARGADOR | N115: 3 | O115: =IFERROR(INDEX('tabla salarial'!$AS$4:$AS$9,MATCH(N115,'tabla salarial'!$AT$4:$AT$9,0)),0) -> 371571.33
A116: Mazo de caucho | B116: 500 | C116: =B116*1.25 -> 625 | E116: Rollo Pita polipropileno | F116: 35000 | G116: =F116*1.25 -> 43750 | M116: SAND BLASTERO, SAND BLASTER O PINTOR | N116: 3 | O116: =IFERROR(INDEX('tabla salarial'!$AS$4:$AS$9,MATCH(N116,'tabla salarial'!$AT$4:$AT$9,0)),0) -> 371571.33
A117: media caneca plastica 55 g | B117: 2000 | E117: Sacos de polipropileno | F117: 1200 | G117: =F117*1.25 -> 1500 | M117: SEÑALIZADOR VIAL* | N117: 1 | O117: =IFERROR(INDEX('tabla salarial'!$AS$4:$AS$9,MATCH(N117,'tabla salarial'!$AT$4:$AT$9,0)),0) -> 382109.06
A118: Mesa de madera | B118: 5000 | C118: =B118*1.25 -> 6250 | E118: Sellante para juntas SIKAfle 1a | F118: 56000 | G118: =F118*1.25 -> 70000 | M118: SOCORRISTA, CONDUCTOR DE AMBULANCIA | N118: 2 | O118: =IFERROR(INDEX('tabla salarial'!$AS$4:$AS$9,MATCH(N118,'tabla salarial'!$AT$4:$AT$9,0)),0) -> 355821.88
A119: Motobomba diesel | B119: 40000 | C119: =B119*1.25 -> 50000 | E119: Sika 1 impermeabilizante kl | F119: 45000 | G119: =F119*1.25 -> 56250 | M119: SOLDADOR 1 | N119: 4 | O119: =IFERROR(INDEX('tabla salarial'!$AS$4:$AS$9,MATCH(N119,'tabla salarial'!$AT$4:$AT$9,0)),0) -> 407197.8
...

Sheet trazado,locali y replanteo
A1: TRAZADO, LOCALIZACIÓN Y REPLANTEO
A2: EQUIPOS | B2: CANT | C2: REND/DIA | D2: TARIFA/DIA | E2: VR.PARCIAL | F2: M2
F3: 781
A4: Machete | B4: 1 | C4: 6 | D4: =IFERROR(VLOOKUP(A4,[1]!TablaEquipos[#Data],2,FALSE),0) -> 1500 | E4: =B4*C4*D4 -> 9000
A5: Martillo | B5: 1 | C5: 6 | D5: =IFERROR(VLOOKUP(A5,[1]!TablaEquipos[#Data],2,FALSE),0) -> 700 | E5: =B5*C5*D5 -> 4200
A6: Pala | B6: 1 | C6: 6 | D6: =IFERROR(VLOOKUP(A6,[1]!TablaEquipos[#Data],2,FALSE),0) -> 700 | E6: =B6*C6*D6 -> 4200
A7: Barra | B7: 1 | C7: 6 | D7: =IFERROR(VLOOKUP(A7,[1]!TablaEquipos[#Data],2,FALSE),0) -> 1500 | E7: =B7*C7*D7 -> 9000
A8: Carretilla | B8: 1 | C8: 6 | D8: =IFERROR(VLOOKUP(A8,[1]!TablaEquipos[#Data],2,FALSE),0) -> 1500 | E8: =B8*C8*D8 -> 9000
A9: Sombrilla para sol | B9: 1 | C9: 6 | D9: =IFERROR(VLOOKUP(A9,[1]!TablaEquipos[#Data],2,FALSE),0) -> 2000 | E9: =B9*C9*D9 -> 12000
A10: Detector de tubería | B10: 1 | C10: 6 | D10: =IFERROR(VLOOKUP(A10,[1]!TablaEquipos[#Data],2,FALSE),0) -> 150000 | E10: =B10*C10*D10 -> 900000
A11: Gps | B11: 1 | C11: 6 | D11: =IFERROR(VLOOKUP(A11,[1]!TablaEquipos[#Data],2,FALSE),0) -> 100000 | E11: =B11*C11*D11 -> 600000
A12: Plomada | B12: 1 | C12: 6 | D12: =IFERROR(VLOOKUP(A12,[1]!TablaEquipos[#Data],2,FALSE),0) -> 1500 | E12: =B12*C12*D12 -> 9000
A13: Nivel 18" | B13: 1 | C13: 6 | D13: =IFERROR(VLOOKUP(A13,[1]!TablaEquipos[#Data],2,FALSE),0) -> 2000 | E13: =B13*C13*D13 -> 12000
A14: Escuadra metalica 24" | B14: 1 | C14: 6 | D14: =IFERROR(VLOOKUP(A14,[1]!TablaEquipos[#Data],2,FALSE),0) -> 1000 | E14: =B14*C14*D14 -> 6000
A15: thermo agua
F17: =SUM(E4:E16) -> 1574400
A18: MATERIALES | B18: CANT | C18: REND/DIA | D18: TARIFA | E18: VR.PARCIAL
A19: Listón de madera 2 x 4 x 3 | D19: =IFERROR(VLOOKUP(A19,[1]!TablaMateriales[#Data],2,FALSE),0) -> 35000 | E19: =B19*D19 -> 0
A20: Listón de madera 2 x 1 x 3 | B20: 50 | D20: =IFERROR(VLOOKUP(A20,[1]!TablaMateriales[#Data],2,FALSE),0) -> 20000 | E20: =B20*D20 -> 1000000
A21: Cal | D21: =IFERROR(VLOOKUP(A21,[1]!TablaMateriales[#Data],2,FALSE),0) -> 50000 | E21: =B21*D21 -> 0
A22: Nailon/hilo de alineación | B22: 2 | D22: =IFERROR(VLOOKUP(A22,[1]!TablaMateriales[#Data],2,FALSE),0) -> 25000 | E22: =B22*D22 -> 50000
A23: Puntilla de 2,5" | B23: 5 | D23: =IFERROR(VLOOKUP(A23,[1]!TablaMateriales[#Data],2,FALSE),0) -> 9500 | E23: =B23*D23 -> 47500
A24: Puntilla de 3,5" | D24: =IFERROR(VLOOKUP(A24,[1]!TablaMateriales[#Data],2,FALSE),0) -> 9500 | E24: =B24*D24 -> 0
A25: Clavo de acero de 3" | B25: 3 | D25: =IFERROR(VLOOKUP(A25,[1]!TablaMateriales[#Data],2,FALSE),0) -> 15000 | E25: =B25*D25 -> 45000
A26: Pintura en aerosol | B26: 20 | D26: =IFERROR(VLOOKUP(A26,[1]!TablaMateriales[#Data],2,FALSE),0) -> 20000 | E26: =B26*D26 -> 400000
A27: Cinta de seguridad amarilla/negra x 500 | B27: 5 | D27: =IFERROR(VLOOKUP(A27,[1]!TablaMateriales[#Data],2,FALSE),0) -> 55000 | E27: =B27*D27 -> 275000
D30: =IFERROR(VLOOKUP(A30,[1]!TablaMateriales[#Data],2,FALSE),0) -> 0
D31: =IFERROR(VLOOKUP(A31,[1]!TablaMateriales[#Data],2,FALSE),0) -> 0 | E31: =B31*D31 -> 0
F32: =SUM(E19:E31) -> 1817500
A33: MANO DE OBRA | B33: CANT | C33: REND/DIA | D33: SALARIO | E33: VR.PARCIAL
A34: Capataz | B34: 1 | C34: 3.52 | D34: ='tabla salarial'!AS4 -> 555393.74 | E34: =B34*C34*D34 -> 1954986
A35: Hse | B35: 1 | C35: 3.52 | D35: ='tabla salarial'!AS4 -> 555393.74 | E35: =B35*C35*D35 -> 1954986
A36: Oficial construccion | B36: 1 | C36: 10.5 | D36: ='tabla salarial'!AS7 -> 371571.33 | E36: =B36*C36*D36 -> 3901499
A37: Auxiliar Administrativo | B37: 1 | C37: 3.52 | D37: ='tabla salarial'!AS8 -> 355821.88 | E37: =B37*C37*D37 -> 1252493
A38: Auxiliar civil | B38: 1 | C38: 10.5 | D38: ='tabla salarial'!AS9 -> 382109.06 | E38: =B38*C38*D38 -> 4012145.1
F41: =SUM(E34:E38) -> 13076109
A42: TRANSPORTE | B42: CANT | C42: REND/DIA | D42: TARIFA | E42: VR.PARCIAL
E43: =B43*C43*D43 -> 0
A44: buseta acpm | B44: 1 | C44: 2 | D44: 550000 | E44: =B44*C44*D44 -> 1100000
D45: =IFERROR(VLOOKUP(A45,[1]!TablaTransporte[#Data],2,FALSE),0) -> 0
F46: =SUM(E43:E44) -> 1100000
F47: =F17+F32+F41+F46 -> 17568009
F48: =F47*A48 -> 0
F49: =F47+F48 -> 17568009
F50: =F49*A50 -> 0
F51: =F49+F50 -> 17568009
F52: =F51/F3 -> 22494.25

Sheet cerramiento 
A1: CERRAMIENTO PROVISIONAL
A2: EQUIPOS | B2: CANT | C2: REND/DIA | D2: TARIFA/DIA | E2: VR.PARCIAL | F2: ML
F3: 510
A4: Machete con funda | B4: 1 | C4: 12 | D4: =IFERROR(VLOOKUP(A4,[1]!TablaEquipos[#Data],2,FALSE),0) -> 1500 | E4: =B4*C4*D4 -> 18000
A5: Lima triangular | B5: 1 | C5: 12 | D5: =IFERROR(VLOOKUP(A5,[1]!TablaEquipos[#Data],2,FALSE),0) -> 700 | E5: =B5*C5*D5 -> 8400
A6: Martillo | B6: 1 | C6: 12 | D6: =IFERROR(VLOOKUP(A6,[1]!TablaEquipos[#Data],2,FALSE),0) -> 700 | E6: =B6*C6*D6 -> 8400
A7: Pala | B7: 1 | C7: 12 | D7: =IFERROR(VLOOKUP(A7,[1]!TablaEquipos[#Data],2,FALSE),0) -> 700 | E7: =B7*C7*D7 -> 8400
A8: Barra | B8: 1 | C8: 12 | D8: =IFERROR(VLOOKUP(A8,[1]!TablaEquipos[#Data],2,FALSE),0) -> 1500 | E8: =B8*C8*D8 -> 18000
A9: Sierra circular | B9: 1 | C9: 12 | D9: =IFERROR(VLOOKUP(A9,[1]!TablaEquipos[#Data],2,FALSE),0) -> 15000 | E9: =B9*C9*D9 -> 180000
A10: Paladraga | B10: 2 | C10: 12 | D10: =IFERROR(VLOOKUP(A10,[1]!TablaEquipos[#Data],2,FALSE),0) -> 1500 | E10: =B10*C10*D10 -> 36000
A11: Alicate diablo | B11: 2 | C11: 12 | D11: =IFERROR(VLOOKUP(A11,[1]!TablaEquipos[#Data],2,FALSE),0) -> 500 | E11: =B11*C11*D11 -> 12000
A12: Alicate universal | B12: 1 | C12: 12 | D12: =IFERROR(VLOOKUP(A12,[1]!TablaEquipos[#Data],2,FALSE),0) -> 500 | E12: =B12*C12*D12 -> 6000
A13: Carretilla | B13: 2 | C13: 12 | D13: =IFERROR(VLOOKUP(A13,[1]!TablaEquipos[#Data],2,FALSE),0) -> 1500 | E13: =B13*C13*D13 -> 36000
B14: 2 | D14: =IFERROR(VLOOKUP(A14,[1]!TablaEquipos[#Data],2,FALSE),0) -> 0
B15: 2 | D15: =IFERROR(VLOOKUP(A15,[1]!TablaEquipos[#Data],2,FALSE),0) -> 0
B16: 2 | D16: =IFERROR(VLOOKUP(A16,[1]!TablaEquipos[#Data],2,FALSE),0) -> 0
B17: 2 | D17: =IFERROR(VLOOKUP(A17,[1]!TablaEquipos[#Data],2,FALSE),0) -> 0
F18: =SUM(E4:E17) -> 331200
A19: MATERIALES | B19: CANT | C19: REND/DIA | D19: TARIFA | E19: VR.PARCIAL
A20: madera redonda 3" x 2.5m | B20: 180 | D20: =IFERROR(VLOOKUP(A20,[1]!TablaMateriales[#Data],2,FALSE),0) -> 25000 | E20: =B20*D20 -> 4500000
A21: Grapa | B21: 4 | D21: =IFERROR(VLOOKUP(A21,[1]!TablaMateriales[#Data],2,FALSE),0) -> 15900 | E21: =B21*D21 -> 63600
A22: Alambre HG calibre 14 | B22: 55 | D22: =IFERROR(VLOOKUP(A22,[1]!TablaMateriales[#Data],2,FALSE),0) -> 14000 | E22: =B22*D22 -> 770000
A23: Tela verde de 2 metros | B23: 570 | D23: =IFERROR(VLOOKUP(A23,[1]!TablaMateriales[#Data],2,FALSE),0) -> 3800 | E23: =B23*D23 -> 2166000
D24: =IFERROR(VLOOKUP(A24,[1]!TablaMateriales[#Data],2,FALSE),0) -> 0 | E24: =B24*D24 -> 0
D25: =IFERROR(VLOOKUP(A25,[1]!TablaMateriales[#Data],2,FALSE),0) -> 0
D26: =IFERROR(VLOOKUP(A26,[1]!TablaMateriales[#Data],2,FALSE),0) -> 0
D27: =IFERROR(VLOOKUP(A27,[1]!TablaMateriales[#Data],2,FALSE),0) -> 0
D28: =IFERROR(VLOOKUP(A28,[1]!TablaMateriales[#Data],2,FALSE),0) -> 0
F29: =SUM(E20:E28) -> 7499600
A30: MANO DE OBRA | B30: CANT | C30: REND/DIA | D30: SALARIO | E30: VR.PARCIAL
A31: Capataz | B31: 1 | C31: 6.46 | D31: ='tabla salarial'!AS4 -> 555393.74 | E31: =B31*C31*D31 -> 3587843.6
A32: Hse | B32: 1 | C32: 6.46 | D32: ='tabla salarial'!AS4 -> 555393.74 | E32: =B32*C32*D32 -> 3587843.6
A33: Oficial construccion | B33: 1 | C33: 19.7 | D33: ='tabla salarial'!AS7 -> 371571.33 | E33: =B33*C33*D33 -> 7319955.2
A34: Auxiliar Administrativo | B34: 1 | C34: 6.46 | D34: ='tabla salarial'!AS8 -> 355821.88 | E34: =B34*C34*D34 -> 2298609.3
A35: Auxiliar civil | B35: 4 | C35: 19.7 | D35: ='tabla salarial'!AS9 -> 382109.06 | E35: =B35*C35*D35 -> 30110194
F36: =SUM(E31:E35) -> 46904446
A37: TRANSPORTE | B37: CANT | C37: REND/DIA | D37: TARIFA | E37: VR.PARCIAL
A38: Camión doble cabina | B38: 1 | C38: 1 | D38: =IFERROR(VLOOKUP(A38,[1]!TablaTransporte[#Data],2,FALSE),0) -> 550000 | E38: =B38*C38*D38 -> 550000
A39: buseta acpm | B39: 1 | C39: 6 | D39: 550000 | E39: =B39*C39*D39 -> 3300000
D40: =IFERROR(VLOOKUP(A40,[1]!TablaTransporte[#Data],2,FALSE),0) -> 0
D41: =IFERROR(VLOOKUP(A41,[1]!TablaTransporte[#Data],2,FALSE),0) -> 0
F42: =SUM(E38:E41) -> 3850000
F43: =F18+F29+F36+F42 -> 58585246
F44: =F43*A44 -> 0
F45: =F43+F44 -> 58585246
F46: =F45*A46 -> 0
F47: =F45+F46 -> 58585246
F48: =F47/F3 -> 114873.03

Sheet campamento
A1: CAMPAMENTO DE OBRA
A2: EQUIPOS | B2: CANT | C2: REND/DIA | D2: TARIFA/DIA | E2: VR.PARCIAL | F2: global
F3: 9
A4: Machete | B4: 2 | C4: 24 | D4: =IFERROR(VLOOKUP(A4,[1]!TablaEquipos[#Data],2,FALSE),0) -> 1500 | E4: =B4*C4*D4 -> 72000
A5: Martillo | B5: 2 | C5: 24 | D5: =IFERROR(VLOOKUP(A5,[1]!TablaEquipos[#Data],2,FALSE),0) -> 700 | E5: =B5*C5*D5 -> 33600
A6: Pala | B6: 1 | C6: 24 | D6: =IFERROR(VLOOKUP(A6,[1]!TablaEquipos[#Data],2,FALSE),0) -> 700 | E6: =B6*C6*D6 -> 16800
A7: Barra | B7: 1 | C7: 24 | D7: =IFERROR(VLOOKUP(A7,[1]!TablaEquipos[#Data],2,FALSE),0) -> 1500 | E7: =B7*C7*D7 -> 36000
A8: Sierra circular | B8: 1 | C8: 24 | D8: =IFERROR(VLOOKUP(A8,[1]!TablaEquipos[#Data],2,FALSE),0) -> 15000 | E8: =B8*C8*D8 -> 360000
A9: Paladraga | B9: 2 | C9: 24 | D9: =IFERROR(VLOOKUP(A9,[1]!TablaEquipos[#Data],2,FALSE),0) -> 1500 | E9: =B9*C9*D9 -> 72000
A10: Alicate diablo | B10: 1 | C10: 24 | D10: =IFERROR(VLOOKUP(A10,[1]!TablaEquipos[#Data],2,FALSE),0) -> 500 | E10: =B10*C10*D10 -> 12000
A11: Alicate universal | B11: 1 | C11: 24 | D11: =IFERROR(VLOOKUP(A11,[1]!TablaEquipos[#Data],2,FALSE),0) -> 500 | E11: =B11*C11*D11 -> 12000
A12: Carretilla | B12: 2 | C12: 24 | D12: =IFERROR(VLOOKUP(A12,[1]!TablaEquipos[#Data],2,FALSE),0) -> 1500 | E12: =B12*C12*D12 -> 72000
A13: Carpa plastica 4x4 | B13: 2 | C13: 240 | D13: =IFERROR(VLOOKUP(A13,[1]!TablaEquipos[#Data],2,FALSE),0) -> 27500 | E13: =B13*C13*D13 -> 13200000
A14: Carpa plastica 6x4 | B14: 1 | C14: 240 | D14: =IFERROR(VLOOKUP(A14,[1]!TablaEquipos[#Data],2,FALSE),0) -> 30000 | E14: =B14*C14*D14 -> 7200000
A15: Mesa de madera | B15: 2 | C15: 240 | D15: =IFERROR(VLOOKUP(A15,[1]!TablaEquipos[#Data],2,FALSE),0) -> 5000 | E15: =B15*C15*D15 -> 2400000
... A25: Extintor Co2 | B25: 1 | C25: 240 | D25: =IFERROR(VLOOKUP(A25,[1]!TablaEquipos[#Data],2,FALSE),0) -> 1500 | E25: =B25*C25*D25 -> 360000
C26: 240
C27: 240
D28: =IFERROR(VLOOKUP(A28,[1]!TablaEquipos[#Data],2,FALSE),0) -> 0 | E28: =B28*C28*D28 -> 0
F29: =SUM(E4:E28) -> 51974280
A30: MATERIALES | B30: CANT | C30: REND/DIA | D30: TARIFA | E30: VR.PARCIAL | XEX30: =SUM(D28) -> 0
A31: Listón de madera 2 x 1 x 3 | B31: 50 | D31: =IFERROR(VLOOKUP(A31,[1]!TablaMateriales[#Data],2,FALSE),0) -> 20000 | E31: =B31*D31 -> 1000000
A32: Puntilla de 2,5" | B32: 10 | D32: =IFERROR(VLOOKUP(A32,[1]!TablaMateriales[#Data],2,FALSE),0) -> 9500 | E32: =B32*D32 -> 95000
A33: Cinta de seguridad amarilla/negra x 500 | B33: 5 | D33: =IFERROR(VLOOKUP(A33,[1]!TablaMateriales[#Data],2,FALSE),0) -> 55000 | E33: =B33*D33 -> 275000
A34: Grapa | B34: 5 | D34: =IFERROR(VLOOKUP(A34,[1]!TablaMateriales[#Data],2,FALSE),0) -> 15900 | E34: =B34*D34 -> 79500
A35: Plástico negro | B35: 20 | D35: =IFERROR(VLOOKUP(A35,[1]!TablaMateriales[#Data],2,FALSE),0) -> 9500 | E35: =B35*D35 -> 190000
D36: =IFERROR(VLOOKUP(A36,[1]!TablaMateriales[#Data],2,FALSE),0) -> 0
D37: =IFERROR(VLOOKUP(A37,[1]!TablaMateriales[#Data],2,FALSE),0) -> 0
F38: =SUM(E31:E37) -> 1639500
A39: MANO DE OBRA | B39: CANT | C39: REND/DIA | D39: SALARIO | E39: VR.PARCIAL
A40: Capataz | B40: 1 | C40: 9.4 | D40: ='tabla salarial'!AS4 -> 555393.74 | E40: =B40*C40*D40 -> 5220701.2
A41: Hse | B41: 1 | C41: 9.4 | D41: ='tabla salarial'!AS4 -> 555393.74 | E41: =B41*C41*D41 -> 5220701.2
A42: Oficial construccion | B42: 1 | C42: 28.2 | D42: ='tabla salarial'!AS7 -> 371571.33 | E42: =B42*C42*D42 -> 10478311
A43: Auxiliar Administrativo | B43: 1 | C43: 9.4 | D43: ='tabla salarial'!AS8 -> 355821.88 | E43: =B43*C43*D43 -> 3344725.6
A44: Auxiliar civil | B44: 2 | C44: 28.2 | D44: ='tabla salarial'!AS9 -> 382109.06 | E44: =B44*C44*D44 -> 21550951
F45: =SUM(E40:E44) -> 45815390
A46: TRANSPORTE | B46: CANT | C46: REND/DIA | D46: TARIFA | E46: VR.PARCIAL
A47: Camión doble cabina | B47: 1 | C47: 2 | D47: =IFERROR(VLOOKUP(A47,[1]!TablaTransporte[#Data],2,FALSE),0) -> 550000 | E47: =B47*C47*D47 -> 1100000
A48: buseta acpm | B48: 1 | C48: 7 | D48: 550000 | E48: =B48*C48*D48 -> 3850000
F49: =SUM(E47:E48) -> 4950000
F50: =F29+F38+F45+F49 -> 1.0437917e+08
F51: =F50*A51 -> 0
F52: =F50+F51 -> 1.0437917e+08
F53: =F52*A53 -> 0
F54: =F52+F53 -> 1.0437917e+08
F55: =F54/F3 -> 11597686

Sheet andamios
A1: ARMADO, UTILIZACIÓN Y DESARMADO DE ANDAMIOS TIPO LAYDER
A2: EQUIPOS | B2: CANT | C2: REND/DIA | D2: TARIFA/DIA | E2: VR.PARCIAL | F2: seccion
F3: 295
A4: Almadana en bronce | B4: 1 | C4: 38 | D4: =IFERROR(VLOOKUP(A4,[1]!TablaEquipos[#Data],2,FALSE),0) -> 450 | E4: =B4*C4*D4 -> 17100
A5: Andamios Layher | B5: 1 | C5: 295 | D5: =IFERROR(VLOOKUP(A5,[1]!TablaEquipos[#Data],2,FALSE),0) -> 135000 | E5: =B5*C5*D5 -> 39825000
A6: Arnés de seguridad y Erlingas | B6: 1 | C6: 38 | D6: =IFERROR(VLOOKUP(A6,[1]!TablaEquipos[#Data],2,FALSE),0) -> 9000 | E6: =B6*C6*D6 -> 342000
A7: Nivel torpedo | B7: 2 | C7: 38 | D7: =IFERROR(VLOOKUP(A7,[1]!TablaEquipos[#Data],2,FALSE),0) -> 1000 | E7: =B7*C7*D7 -> 76000
A8: Carretilla | B8: 2 | C8: 38 | D8: =IFERROR(VLOOKUP(A8,[1]!TablaEquipos[#Data],2,FALSE),0) -> 1500 | E8: =B8*C8*D8 -> 114000
A9: Colombina | B9: 12 | C9: 38 | D9: =IFERROR(VLOOKUP(A9,[1]!TablaEquipos[#Data],2,FALSE),0) -> 1000 | E9: =B9*C9*D9 -> 456000
F13: =SUM(E4:E11) -> 40830100
A14: MATERIALES | B14: CANT | C14: REND/DIA | D14: TARIFA | E14: VR.PARCIAL
A15: Cinta de seguridad amarilla/negra x 500 | B15: 2 | D15: =IFERROR(VLOOKUP(A15,[1]!TablaMateriales[#Data],2,FALSE),0) -> 55000 | E15: =B15*D15 -> 110000
D16: =IFERROR(VLOOKUP(A16,[1]!TablaMateriales[#Data],2,FALSE),0) -> 0
D17: =IFERROR(VLOOKUP(A17,[1]!TablaMateriales[#Data],2,FALSE),0) -> 0
D18: =IFERROR(VLOOKUP(A18,[1]!TablaMateriales[#Data],2,FALSE),0) -> 0
D19: =IFERROR(VLOOKUP(A19,[1]!TablaMateriales[#Data],2,FALSE),0) -> 0
D20: =IFERROR(VLOOKUP(A20,[1]!TablaMateriales[#Data],2,FALSE),0) -> 0
F21: =SUM(E15:E20) -> 110000
A22: MANO DE OBRA | B22: CANT | C22: REND/DIA | D22: SALARIO | E22: VR.PARCIAL
A23: Capataz | B23: 1 | C23: 10.6 | D23: ='tabla salarial'!AS4 -> 555393.74 | E23: =B23*C23*D23 -> 5887173.7
A24: Hse | B24: 1 | C24: 10.6 | D24: ='tabla salarial'!AS4 -> 555393.74 | E24: =B24*C24*D24 -> 5887173.7
A25: cordinador de altura | B25: 1 | C25: 10.6 | D25: ='tabla salarial'!AS4 -> 555393.74 | E25: =B25*C25*D25 -> 5887173.7
A26: rescatista | B26: 1 | C26: 44.7 | D26: ='tabla salarial'!AS5 -> 443956.94 | E26: =C26*D26 -> 19844875
A27: Andamiero | B27: 1 | C27: 44.7 | D27: ='tabla salarial'!AS6 -> 407197.8 | E27: =B27*C27*D27 -> 18201742
A28: Oficial construccion | B28: 1 | D28: ='tabla salarial'!AS7 -> 371571.33 | E28: =B28*C28*D28 -> 0
A29: Auxiliar Administrativo | B29: 1 | C29: 10.6 | D29: ='tabla salarial'!AS8 -> 355821.88 | E29: =B29*C29*D29 -> 3771711.9
A30: Auxiliar civil | B30: 2 | D30: ='tabla salarial'!AS9 -> 382109.06 | E30: =B30*C30*D30 -> 0
F31: =SUM(E23:E30) -> 59479850
A32: TRANSPORTE | B32: CANT | C32: REND/DIA | D32: TARIFA | E32: VR.PARCIAL
A33: Camión doble cabina | B33: 1 | C33: 10 | D33: =IFERROR(VLOOKUP(A33,[1]!TablaTransporte[#Data],2,FALSE),0) -> 550000 | E33: =B33*C33*D33 -> 5500000
F34: =E33 -> 5500000
F35: =F13+F21+F31+F34 -> 1.0591995e+08
F36: =F35*A36 -> 0
F37: =F35+F36 -> 1.0591995e+08
F38: =F37*A38 -> 0
F39: =F37+F38 -> 1.0591995e+08
F40: =F39/F3 -> 359050.68

Sheet topografia
A1: REPLANTEO TOPOGRÁFICO
A2: EQUIPOS | B2: CANT | C2: REND/DIA | D2: TARIFA/DIA | E2: VR.PARCIAL | F2: jornada
F3: 10
A4: Machete | B4: 2 | C4: 10 | D4: 2500 | E4: =B4*C4*D4 -> 50000
A5: Martillo | B5: 1 | C5: 10 | D5: =IFERROR(VLOOKUP(A5,[1]!TablaEquipos[#Data],2,FALSE),0) -> 700 | E5: =B5*C5*D5 -> 7000
A6: Carretilla | B6: 1 | C6: 10 | D6: 4500 | E6: =B6*C6*D6 -> 45000
A7: Camilla primeros auxilios | B7: 1 | C7: 10 | D7: 2500 | E7: =B7*C7*D7 -> 25000
A8: Botiquin primeros auxilios | B8: 1 | C8: 10 | D8: 2500 | E8: =B8*C8*D8 -> 25000
A9: Equipo topografico | B9: 1 | C9: 10 | D9: 500000 | E9: =B9*C9*D9 -> 5000000
D13: =IFERROR(VLOOKUP(A13,[1]!TablaEquipos[#Data],2,FALSE),0) -> 0
D14: =IFERROR(VLOOKUP(A14,[1]!TablaEquipos[#Data],2,FALSE),0) -> 0
D15: =IFERROR(VLOOKUP(A15,[1]!TablaEquipos[#Data],2,FALSE),0) -> 0
D16: =IFERROR(VLOOKUP(A16,[1]!TablaEquipos[#Data],2,FALSE),0) -> 0
D17: =IFERROR(VLOOKUP(A17,[1]!TablaEquipos[#Data],2,FALSE),0) -> 0
A18: =#REF!*#REF! -> #REF! | F18: =SUM(E4:E17) -> 5152000
A19: MATERIALES | B19: CANT | C19: REND/DIA | D19: TARIFA | E19: =B22*D22 -> 30000
A20: Listón de madera 2 x 1 x 3 | B20: 50 | D20: =IFERROR(VLOOKUP(A20,[1]!TablaMateriales[#Data],2,FALSE),0) -> 20000 | E20: =B20*D20 -> 1000000
A21: Puntilla de 2,5" | B21: 2 | C21: 10 | D21: =IFERROR(VLOOKUP(A21,[1]!TablaMateriales[#Data],2,FALSE),0) -> 9500 | E21: =B21*D21 -> 19000
A22: Clavo de acero de 3" | B22: 2 | C22: 10 | D22: =IFERROR(VLOOKUP(A22,[1]!TablaMateriales[#Data],2,FALSE),0) -> 15000 | E22: =B22*D22 -> 30000
A23: Pintura en aerosol | B23: 20 | C23: 10 | D23: =IFERROR(VLOOKUP(A23,[1]!TablaMateriales[#Data],2,FALSE),0) -> 20000 | E23: =B23*D23 -> 400000
F33: =SUM(E19:E32) -> 1479000
A34: MANO DE OBRA | B34: CANT | C34: REND/DIA | D34: SALARIO | E34: VR.PARCIAL
A35: Capataz | B35: 1 | D35: ='tabla salarial'!AS4 -> 555393.74 | E35: =B35*C35*D35 -> 0
A36: Hse | B36: 1 | D36: ='tabla salarial'!AS4 -> 555393.74 | E36: =B36*C36*D36 -> 0
A37: Topografo | B37: 1 | C37: 13 | D37: ='tabla salarial'!AS4 -> 555393.74 | E37: =B37*C37*D37 -> 7220118.6
A38: Cadenero 1 | B38: 1.5 | C38: 13 | D38: ='tabla salarial'!AS6 -> 407197.8 | E38: =B38*C38*D38 -> 7940357.2
A39: Andamiero | B39: 2 | D39: ='tabla salarial'!AS6 -> 407197.8 | E39: =B39*C39*D39 -> 0
A40: Oficial construccion | B40: 1 | D40: ='tabla salarial'!AS7 -> 371571.33 | E40: =B40*C40*D40 -> 0
A41: Auxiliar Administrativo | B41: 1 | D41: ='tabla salarial'!AS8 -> 355821.88 | E41: =B41*C41*D41 -> 0
A42: Auxiliar civil | B42: 1 | C42: 13 | D42: ='tabla salarial'!AS9 -> 382109.06 | E42: =B42*C42*D42 -> 4967417.8
A43: 3 | F43: =SUM(E35:E42) -> 20127894
A44: TRANSPORTE | B44: CANT | C44: REND/DIA | D44: TARIFA | E44: VR.PARCIAL
A45: Buseta | B45: 1 | C45: 3 | D45: 550000 | E45: =B45*C45*D45 -> 1650000
F46: =E45 -> 1650000
F47: =F18+F33+F43+F46 -> 28408894
F48: =F47*A48 -> 0
F49: =F47+F48 -> 28408894
F50: =F49*A50 -> 0
F51: =F49+F50 -> 28408894
F52: =F51/F3 -> 2840889.4

Sheet acarreobotadero
A1: ACARREO MATERIAL BOTADERO
A2: EQUIPOS | B2: CANT | C2: REND/DIA | D2: TARIFA/DIA | E2: VR.PARCIAL | F2: m3/km
F3: 57
A4: Pala | B4: 2 | C4: 3 | D4: =IFERROR(VLOOKUP(A4,[1]!TablaEquipos[#Data],2,FALSE),0) -> 700 | E4: =B4*C4*D4 -> 4200
F10: =SUM(E4:E9) -> 4200
A11: MATERIALES | B11: CANT | C11: REND/DIA | D11: TARIFA | E11: VR.PARCIAL
A12: Plastico negro | B12: 50 | D12: =IFERROR(VLOOKUP(A12,[1]!TablaMateriales[#Data],2,FALSE),0) -> 9500 | E12: =B12*D12 -> 475000
D13: =IFERROR(VLOOKUP(A13,[1]!TablaMateriales[#Data],2,FALSE),0) -> 0
F16: =SUM(E12:E13) -> 475000
A17: MANO DE OBRA | B17: CANT | C17: REND/DIA | D17: SALARIO | E17: VR.PARCIAL
A18: Capataz | B18: 1 | C18: 0.38 | D18: ='tabla salarial'!AS4 -> 555393.74 | E18: =B18*C18*D18 -> 211049.62
A19: Hse | B19: 1 | C19: 0.38 | D19: ='tabla salarial'!AS4 -> 555393.74 | E19: =B19*C19*D19 -> 211049.62
A20: Oficial construccion | B20: 1 | C20: 0.38 | D20: ='tabla salarial'!AS7 -> 371571.33 | E20: =B20*C20*D20 -> 141197.11
A21: Auxiliar Administrativo | B21: 1 | C21: 0.38 | D21: ='tabla salarial'!AS8 -> 355821.88 | E21: =B21*C21*D21 -> 135212.31
A22: Auxiliar civil | B22: 1 | C22: 4.7 | D22: ='tabla salarial'!AS9 -> 382109.06 | E22: =B22*C22*D22 -> 1795912.6
A23: 3 | F23: =SUM(E18:E22) -> 2494421.2
A24: TRANSPORTE | B24: CANT | C24: REND/DIA | D24: TARIFA | E24: VR.PARCIAL
A26: Acarreo por km | B26: 1 | C26: 57 | D26: =IFERROR(VLOOKUP(A26,[1]!TablaTransporte[#Data],2,FALSE),0) -> 65000 | E26: =B26*C26*D26 -> 3705000
A27: Retroexcavadora de llantas | B27: 1 | C27: 1 | D27: =IFERROR(VLOOKUP(A27,[1]!TablaTransporte[#Data],2,FALSE),0) -> 1330000 | E27: =B27*C27*D27 -> 1330000
D28: =IFERROR(VLOOKUP(A28,[1]!TablaTransporte[#Data],2,FALSE),0) -> 0
F29: =SUM(E25:E28) -> 5035000
F30: =F10+F16+F23+F29 -> 8008621.2
F31: =F30*A31 -> 0
F32: =F30+F31 -> 8008621.2
F33: =F32*A33 -> 0
F34: =F32+F33 -> 8008621.2
F35: =F34/F3 -> 140502.13

Sheet movimiento tierra
A1: MOVIMIENTO DE TIERRA INTERNO
A2: EQUIPOS | B2: CANT | C2: REND/DIA | D2: TARIFA/DIA | E2: VR.PARCIAL | F2: JORNADA
F3: 62
A4: Pala | B4: 2 | C4: 62 | D4: =IFERROR(VLOOKUP(A4,[1]!TablaEquipos[#Data],2,FALSE),0) -> 700 | E4: =B4*C4*D4 -> 86800
A5: Barra | B5: 4 | C5: 62 | D5: =IFERROR(VLOOKUP(A5,[1]!TablaEquipos[#Data],2,FALSE),0) -> 1500 | E5: =B5*C5*D5 -> 372000
A6: Carretilla | B6: 2 | C6: 62 | D6: =IFERROR(VLOOKUP(A6,[1]!TablaEquipos[#Data],2,FALSE),0) -> 1500 | E6: =B6*C6*D6 -> 186000
A7: Colombina | B7: 12 | C7: 62 | D7: =IFERROR(VLOOKUP(A7,[1]!TablaEquipos[#Data],2,FALSE),0) -> 1000 | E7: =B7*C7*D7 -> 744000
A8: Avisos de seguridad | B8: 20 | C8: 62 | D8: 500 | E8: =B8*C8*D8 -> 620000
A9: Paletas | B9: 2 | C9: 62 | D9: 500 | E9: =B9*C9*D9 -> 62000
D10: 40000 | E10: =B10*C10*D10 -> 0
D13: =IFERROR(VLOOKUP(A13,[1]!TablaEquipos[#Data],2,FALSE),0) -> 0
D14: =IFERROR(VLOOKUP(A14,[1]!TablaEquipos[#Data],2,FALSE),0) -> 0
D15: =IFERROR(VLOOKUP(A15,[1]!TablaEquipos[#Data],2,FALSE),0) -> 0
F16: =SUM(E4:E15) -> 2070800
A17: MATERIALES | B17: CANT | C17: REND/DIA | D17: TARIFA | E17: VR.PARCIAL
A18: Plástico negro | B18: 150 | D18: =IFERROR(VLOOKUP(A18,[1]!TablaMateriales[#Data],2,FALSE),0) -> 9500 | E18: =B18*D18 -> 1425000
A19: Chaleco Reflectivo | B19: 2 | D19: =IFERROR(VLOOKUP(A19,[1]!TablaMateriales[#Data],2,FALSE),0) -> 20000 | E19: =B19*D19 -> 40000
D22: =IFERROR(VLOOKUP(A22,[1]!TablaMateriales[#Data],2,FALSE),0) -> 0
F23: =SUM(E18:E22) -> 1465000
A24: MANO DE OBRA | B24: CANT | C24: REND/DIA | D24: SALARIO | E24: VR.PARCIAL
A25: Capataz | B25: 1 | C25: 28.8 | D25: ='tabla salarial'!AS4 -> 555393.74 | E25: =B25*C25*D25 -> 15995340
A26: Hse | B26: 1 | C26: 28.8 | D26: ='tabla salarial'!AS4 -> 555393.74 | E26: =B26*C26*D26 -> 15995340
A27: Oficial construccion | B27: 1 | C27: 86 | D27: ='tabla salarial'!AS7 -> 371571.33 | E27: =B27*C27*D27 -> 31955134
A28: Oficinista 2 | B28: 1 | C28: 28.8 | D28: ='tabla salarial'!AS8 -> 355821.88 | E28: =B28*C28*D28 -> 10247670
A29: Auxiliar civil | B29: 2 | C29: 86 | D29: ='tabla salarial'!AS9 -> 382109.06 | E29: =B29*C29*D29 -> 65722758
F30: =SUM(E25:E29) -> 1.3991624e+08
A31: TRANSPORTE | B31: CANT | C31: REND/DIA | D31: TARIFA | E31: VR.PARCIAL
A32: Buseta | B32: 1 | C32: 20 | D32: 550000 | E32: =B32*C32*D32 -> 11000000
A33: retro excavadora de llanta | B33: 1 | C33: 62 | D33: =IFERROR(VLOOKUP(A33,[1]!TablaTransporte[#Data],2,FALSE),0) -> 1330000 | E33: =B33*C33*D33 -> 82460000
A34: Volqueta de 14 m³ | B34: 1 | C34: 62 | D34: =IFERROR(VLOOKUP(A34,[1]!TablaTransporte[#Data],2,FALSE),0) -> 1350000 | E34: =B34*C34*D34 -> 83700000
F35: =SUM(E32:E34) -> 177160000
F36: =F16+F23+F30+F35 -> 3.2061204e+08
F37: =F36*A37 -> 0
F38: =F36+F37 -> 3.2061204e+08
F39: =F38*A39 -> 0
F40: =F38+F39 -> 3.2061204e+08
F41: =F40/F3 -> 5171162

Sheet  excavacion -1,20mts
A1: EXCAVACIÓN MANUAL MENOR A 1,20MTS
A2: EQUIPOS | B2: CANT | C2: REND/DIA | D2: TARIFA/DIA | E2: VR.PARCIAL | F2: M3
F3: 657
A4: Pala | B4: 8 | C4: 85 | D4: =IFERROR(VLOOKUP(A4,[1]!TablaEquipos[#Data],2,FALSE),0) -> 700 | E4: =B4*C4*D4 -> 476000
A5: Pica | B5: 8 | C5: 85 | D5: =IFERROR(VLOOKUP(A5,[1]!TablaEquipos[#Data],2,FALSE),0) -> 700 | E5: =B5*C5*D5 -> 476000
A6: Palín | B6: 8 | C6: 85 | D6: =IFERROR(VLOOKUP(A6,[1]!TablaEquipos[#Data],2,FALSE),0) -> 700 | E6: =B6*C6*D6 -> 476000
A7: Paladraga | B7: 4 | C7: 85 | D7: =IFERROR(VLOOKUP(A7,[1]!TablaEquipos[#Data],2,FALSE),0) -> 1500 | E7: =B7*C7*D7 -> 510000
A8: Barra | B8: 4 | C8: 85 | D8: =IFERROR(VLOOKUP(A8,[1]!TablaEquipos[#Data],2,FALSE),0) -> 1500 | E8: =B8*C8*D8 -> 510000
A9: Herramientero | B9: 1 | C9: 85 | D9: =IFERROR(VLOOKUP(A9,[1]!TablaEquipos[#Data],2,FALSE),0) -> 1500 | E9: =B9*C9*D9 -> 127500
A10: Carretilla | B10: 6 | C10: 85 | D10: =IFERROR(VLOOKUP(A10,[1]!TablaEquipos[#Data],2,FALSE),0) -> 1500 | E10: =B10*C10*D10 -> 765000
A11: Avisos de seguridad | B11: 30 | C11: 85 | D11: 500 | E11: =B11*C11*D11 -> 1275000
XFD12: =SUM(G12:XFC12) -> 0
D17: =IFERROR(VLOOKUP(A17,[1]!TablaEquipos[#Data],2,FALSE),0) -> 0 | E17: =B17*C17*D17 -> 0
D18: =IFERROR(VLOOKUP(A18,[1]!TablaEquipos[#Data],2,FALSE),0) -> 0 | E18: =B18*C18*D18 -> 0
F19: =SUM(E4:E18) -> 4615500
A20: MATERIALES | B20: CANT | C20: REND/DIA | D20: TARIFA | E20: VR.PARCIAL
A21: Listón de madera 2 x 4 x 3 | B21: 20 | D21: =IFERROR(VLOOKUP(A21,[1]!TablaMateriales[#Data],2,FALSE),0) -> 35000 | E21: =B21*D21 -> 700000
A22: Listón de madera 2 x 1 x 3 | B22: 30 | D22: =IFERROR(VLOOKUP(A22,[1]!TablaMateriales[#Data],2,FALSE),0) -> 20000 | E22: =B22*D22 -> 600000
A23: Puntilla de 3,5" | B23: 5 | D23: =IFERROR(VLOOKUP(A23,[1]!TablaMateriales[#Data],2,FALSE),0) -> 9500 | E23: =B23*D23 -> 47500
A24: Cinta de seguridad amarilla/negra x 500 | B24: 2 | D24: =IFERROR(VLOOKUP(A24,[1]!TablaMateriales[#Data],2,FALSE),0) -> 55000 | E24: =B24*D24 -> 110000
A25: Plastico negro | B25: 150 | D25: 9500 | E25: =B25*D25 -> 1425000
D28: =IFERROR(VLOOKUP(A28,[1]!TablaMateriales[#Data],2,FALSE),0) -> 0
D29: =IFERROR(VLOOKUP(A29,[1]!TablaMateriales[#Data],2,FALSE),0) -> 0
D30: =IFERROR(VLOOKUP(A30,[1]!TablaMateriales[#Data],2,FALSE),0) -> 0
D31: =IFERROR(VLOOKUP(A31,[1]!TablaMateriales[#Data],2,FALSE),0) -> 0
F32: =SUM(E21:E31) -> 2882500
A33: MANO DE OBRA | B33: CANT | C33: REND/DIA | D33: SALARIO | E33: VR.PARCIAL
A34: Capataz | B34: 1 | C34: 34 | D34: ='tabla salarial'!AS4 -> 555393.74 | E34: =B34*C34*D34 -> 18883387
A35: Hse | B35: 1 | C35: 34 | D35: ='tabla salarial'!AS4 -> 555393.74 | E35: =B35*C35*D35 -> 18883387
A36: Oficial construccion | B36: 2 | C36: 102 | D36: ='tabla salarial'!AS7 -> 371571.33 | E36: =B36*C36*D36 -> 75800551
A37: Oficinista 2 | B37: 1 | C37: 34 | D37: ='tabla salarial'!AS8 -> 355821.88 | E37: =B37*C37*D37 -> 12097944
A38: Auxiliar civil | B38: 8 | C38: 102 | D38: ='tabla salarial'!AS9 -> 382109.06 | E38: =B38*C38*D38 -> 3.1180099e+08
A39: 3 | F39: =SUM(E34:E38) -> 4.3746626e+08
A40: TRANSPORTE | B40: CANT | C40: REND/DIA | D40: TARIFA | E40: VR.PARCIAL
A41: Buseta | B41: 1 | C41: 85 | D41: 600000 | E41: =B41*C41*D41 -> 51000000
A42: Retroexcavadora con llantas | B42: 1 | C42: 4 | D42: 1330000 | E42: =B42*C42*D42 -> 5320000
A43: Volqueta de 14 m³ | B43: 1 | C43: 4 | D43: 1390000 | E43: =B43*C43*D43 -> 5560000
A44: Traslado de equipos | B44: 1 | C44: 1 | D44: 1650000 | E44: =B44*C44*D44 -> 1650000
F47: =SUM(E41:E46) -> 63530000
F48: =F19+F32+F39+F47 -> 5.0849426e+08
F49: =F48*A49 -> 0
F50: =F48+F49 -> 5.0849426e+08
F51: =F50*A51 -> 0
F52: =F50+F51 -> 5.0849426e+08
F53: =F52/F3 -> 773963.87

Sheet excavación +1,20mts
A1: EXCAVACIÓN MANUAL MAYOR A 1,20MTS
A2: EQUIPOS | B2: CANT | C2: REND/DIA | D2: TARIFA/DIA | E2: VR.PARCIAL | F2: M3
F3: 525
A4: Machete | B4: 1 | C4: 15 | D4: =IFERROR(VLOOKUP(A4,[1]!TablaEquipos[#Data],2,FALSE),0) -> 1500 | E4: =B4*C4*D4 -> 22500
A5: Martillo | B5: 1 | C5: 15 | D5: =IFERROR(VLOOKUP(A5,[1]!TablaEquipos[#Data],2,FALSE),0) -> 700 | E5: =B5*C5*D5 -> 10500
A6: Pala | B6: 8 | C6: 87.5 | D6: =IFERROR(VLOOKUP(A6,[1]!TablaEquipos[#Data],2,FALSE),0) -> 700 | E6: =B6*C6*D6 -> 490000
A7: Pica | B7: 8 | C7: 87.5 | D7: =IFERROR(VLOOKUP(A7,[1]!TablaEquipos[#Data],2,FALSE),0) -> 700 | E7: =B7*C7*D7 -> 490000
A8: Palín | B8: 8 | C8: 87.5 | D8: =IFERROR(VLOOKUP(A8,[1]!TablaEquipos[#Data],2,FALSE),0) -> 700 | E8: =B8*C8*D8 -> 490000
A9: Paladraga | B9: 2 | C9: 40 | D9: =IFERROR(VLOOKUP(A9,[1]!TablaEquipos[#Data],2,FALSE),0) -> 1500 | E9: =B9*C9*D9 -> 120000
A10: Barra | B10: 2 | C10: 87.5 | D10: =IFERROR(VLOOKUP(A10,[1]!TablaEquipos[#Data],2,FALSE),0) -> 1500 | E10: =B10*C10*D10 -> 262500
A11: Herramientero | B11: 1 | C11: 87.5 | D11: =IFERROR(VLOOKUP(A11,[1]!TablaEquipos[#Data],2,FALSE),0) -> 1500 | E11: =B11*C11*D11 -> 131250
A12: Sierra circular | B12: 1 | C12: 15 | D12: =IFERROR(VLOOKUP(A12,[1]!TablaEquipos[#Data],2,FALSE),0) -> 15000 | E12: =B12*C12*D12 -> 225000
A13: Carretilla | B13: 6 | C13: 87.5 | D13: =IFERROR(VLOOKUP(A13,[1]!TablaEquipos[#Data],2,FALSE),0) -> 1500 | E13: =B13*C13*D13 -> 787500
A14: Balde concretero | B14: 12 | C14: 87.5 | D14: =IFERROR(VLOOKUP(A14,[1]!TablaEquipos[#Data],2,FALSE),0) -> 500 | E14: =B14*C14*D14 -> 525000
A15: Avisos de seguridad | B15: 30 | C15: 87.5 | D15: =IFERROR(VLOOKUP(A15,[1]!TablaEquipos[#Data],2,FALSE),0) -> 1000 | E15: =B15*C15*D15 -> 2625000
E16: =B16*C16*D16 -> 0
D18: =IFERROR(VLOOKUP(A18,[1]!TablaEquipos[#Data],2,FALSE),0) -> 0 | E18: =B18*C18*D18 -> 0
D19: =IFERROR(VLOOKUP(A19,[1]!TablaEquipos[#Data],2,FALSE),0) -> 0 | E19: =B19*C19*D19 -> 0
F20: =SUM(E4:E19) -> 6179250
A21: MATERIALES | B21: CANT | C21: REND/DIA | D21: TARIFA | E21: VR.PARCIAL
A22: Listón de madera 2 x 4 x 3 | B22: 20 | D22: =IFERROR(VLOOKUP(A22,[1]!TablaMateriales[#Data],2,FALSE),0) -> 35000 | E22: =B22*D22 -> 700000
A23: Listón de madera 2 x 1 x 3 | B23: 30 | D23: =IFERROR(VLOOKUP(A23,[1]!TablaMateriales[#Data],2,FALSE),0) -> 20000 | E23: =B23*D23 -> 600000
A24: Tabla | B24: 20 | D24: 45000 | E24: =B24*D24 -> 900000
A25: Puntilla de 3,5" | B25: 5 | D25: =IFERROR(VLOOKUP(A25,[1]!TablaMateriales[#Data],2,FALSE),0) -> 9500 | E25: =B25*D25 -> 47500
A26: Cinta de seguridad amarilla/negra x 500 | B26: 4 | D26: =IFERROR(VLOOKUP(A26,[1]!TablaMateriales[#Data],2,FALSE),0) -> 55000 | E26: =B26*D26 -> 220000
A27: Cabo para pala | B27: 10 | D27: 20000 | E27: =B27*D27 -> 200000
A28: Manila 5/16 | B28: 100 | D28: =IFERROR(VLOOKUP(A28,[1]!TablaMateriales[#Data],2,FALSE),0) -> 2850 | E28: =B28*D28 -> 285000
A29: Acpm | B29: 50 | D29: =IFERROR(VLOOKUP(A29,[1]!TablaMateriales[#Data],2,FALSE),0) -> 0 | E29: =B29*D29 -> 0
D35: =IFERROR(VLOOKUP(A35,[1]!TablaMateriales[#Data],2,FALSE),0) -> 0
D36: =IFERROR(VLOOKUP(A36,[1]!TablaMateriales[#Data],2,FALSE),0) -> 0
F37: =SUM(E22:E36) -> 2952500
A38: MANO DE OBRA | B38: CANT | C38: REND/DIA | D38: SALARIO | E38: VR.PARCIAL
A39: Capataz | B39: 1 | C39: 40 | D39: ='tabla salarial'!AS4 -> 555393.74 | E39: =B39*C39*D39 -> 22215750
A40: Hse | B40: 1 | C40: 40 | D40: ='tabla salarial'!AS4 -> 555393.74 | E40: =B40*C40*D40 -> 22215750
A41: Rescatista | B41: 1 | C41: 63 | D41: ='tabla salarial'!AS5 -> 443956.94 | E41: =B41*C41*D41 -> 27969287
A42: Oficial construccion | B42: 2 | C42: 121 | D42: ='tabla salarial'!AS7 -> 371571.33 | E42: =B42*C42*D42 -> 89920262
A43: auxiliar administracion | B43: 1 | C43: 40 | D43: ='tabla salarial'!AS8 -> 355821.88 | E43: =B43*C43*D43 -> 14232875
A44: Auxiliar civil | B44: 8 | C44: 121 | D44: ='tabla salarial'!AS9 -> 382109.06 | E44: =B44*C44*D44 -> 3.6988157e+08
A45: 3 | F45: =SUM(E39:E44) -> 5.4643549e+08
A46: TRANSPORTE | B46: CANT | C46: REND/DIA | D46: TARIFA | E46: VR.PARCIAL
A47: Camión doble cabina | B47: 1 | C47: 3 | D47: =IFERROR(VLOOKUP(A47,[1]!TablaTransporte[#Data],2,FALSE),0) -> 550000 | E47: =B47*C47*D47 -> 1650000
A48: traslado de equipos | B48: 1 | C48: 1 | D48: =IFERROR(VLOOKUP(A48,[1]!TablaTransporte[#Data],2,FALSE),0) -> 1650000 | E48: =B48*C48*D48 -> 1650000
A49: Retroexcavadora con llantas | B49: 1 | C49: 11 | D49: =IFERROR(VLOOKUP(A49,[1]!TablaTransporte[#Data],2,FALSE),0) -> 190000 | E49: =B49*C49*D49 -> 2090000
A50: Volqueta de 14 m³ | B50: 1 | C50: 11 | D50: =IFERROR(VLOOKUP(A50,[1]!TablaTransporte[#Data],2,FALSE),0) -> 1350000 | E50: =B50*C50*D50 -> 14850000
A51: Buseta | B51: 1 | C51: 87 | D51: 550000 | E51: =B51*C51*D51 -> 47850000 | F51: =SUM(E47:E50) -> 20240000
F52: =F20+F37+F45+F51 -> 5.7580724e+08
F53: =F52*A53 -> 0
F54: =F52+F53 -> 5.7580724e+08
F55: =F54*A55 -> 0
F56: =F54+F55 -> 5.7580724e+08
F57: =F56/F3 -> 1096775.7

Sheet excavación sin presencia
A1: EXCAVACIÓN MECANICA SIN PRESENCIA DE TUBERÍA O FACILIDAD ENTERRADA
A2: EQUIPOS | B2: CANT | C2: REND/DIA | D2: TARIFA/DIA | E2: VR.PARCIAL | F2: M3
F3: 29
A4: Pala | B4: 2 | C4: 0.5 | D4: =IFERROR(VLOOKUP(A4,[1]!TablaEquipos[#Data],2,FALSE),0) -> 700 | E4: =B4*C4*D4 -> 700
A5: Pica | B5: 2 | C5: 0.5 | D5: =IFERROR(VLOOKUP(A5,[1]!TablaEquipos[#Data],2,FALSE),0) -> 700 | E5: =B5*C5*D5 -> 700
A6: Barra | B6: 2 | C6: 1 | D6: =IFERROR(VLOOKUP(A6,[1]!TablaEquipos[#Data],2,FALSE),0) -> 1500 | E6: =B6*C6*D6 -> 3000
A7: Carretilla | B7: 2 | C7: 1 | D7: =IFERROR(VLOOKUP(A7,[1]!TablaEquipos[#Data],2,FALSE),0) -> 1500 | E7: =B7*C7*D7 -> 3000
D8: 45000 | E8: =B8*C8*D8 -> 0
A9: Termo agua | B9: 1 | C9: 2 | D9: 4000 | E9: =B9*C9*D9 -> 8000
A10: Botiquin primeros auxilios | B10: 1 | C10: 2 | D10: 4000 | E10: =B10*C10*D10 -> 8000
A11: Camilla primeros auxilios | B11: 1 | C11: 2 | D11: 3000 | E11: =B11*C11*D11 -> 6000
A12: Colombianas de seguridad | B12: 10 | C12: 2 | D12: 1000 | E12: =B12*C12*D12 -> 20000
A13: Avisos de seguridad | B13: 20 | C13: 2 | D13: 500 | E13: =B13*C13*D13 -> 20000
D18: =IFERROR(VLOOKUP(A18,[1]!TablaEquipos[#Data],2,FALSE),0) -> 0 | E18: =B18*C18*D18 -> 0
D19: =IFERROR(VLOOKUP(A19,[1]!TablaEquipos[#Data],2,FALSE),0) -> 0 | E19: =B19*C19*D19 -> 0
F20: =SUM(E4:E18) -> 69400
A21: MATERIALES | B21: CANT | C21: REND/DIA | D21: TARIFA | E21: VR.PARCIAL
A22: Cinta de seguridad amarilla/negra x 500 | B22: 1 | D22: =IFERROR(VLOOKUP(A22,[1]!TablaMateriales[#Data],2,FALSE),0) -> 55000 | E22: =B22*D22 -> 55000
D23: =IFERROR(VLOOKUP(A23,[1]!TablaMateriales[#Data],2,FALSE),0) -> 0
D24: =IFERROR(VLOOKUP(A24,[1]!TablaMateriales[#Data],2,FALSE),0) -> 0
D25: =IFERROR(VLOOKUP(A25,[1]!TablaMateriales[#Data],2,FALSE),0) -> 0
D26: =IFERROR(VLOOKUP(A26,[1]!TablaMateriales[#Data],2,FALSE),0) -> 0
F27: =SUM(E22:E26) -> 55000
A28: MANO DE OBRA | B28: CANT | C28: REND/DIA | D28: SALARIO | E28: VR.PARCIAL
A29: Capataz | B29: 1 | C29: 0.58 | D29: ='tabla salarial'!AS4 -> 555393.74 | E29: =B29*C29*D29 -> 322128.37
A30: Hse | B30: 1 | C30: 0.58 | D30: ='tabla salarial'!AS4 -> 555393.74 | E30: =B30*C30*D30 -> 322128.37
A31: auxiliar administracion | B31: 1 | C31: 0.58 | D31: ='tabla salarial'!AS8 -> 355821.88 | E31: =B31*C31*D31 -> 206376.69
A32: Oficial construccion | B32: 1 | C32: 1.57 | D32: ='tabla salarial'!AS7 -> 371571.33 | E32: =B32*C32*D32 -> 583366.99
A33: Auxiliar civil | B33: 1 | C33: 1.57 | D33: ='tabla salarial'!AS9 -> 382109.06 | E33: =B33*C33*D33 -> 599911.22
A34: 3 | F34: =SUM(E29:E33) -> 2033911.6
A35: TRANSPORTE | B35: CANT | C35: REND/DIA | D35: TARIFA | E35: VR.PARCIAL
A36: retro excavadora de llanta | B36: 1 | C36: 1.5 | D36: =IFERROR(VLOOKUP(A36,[1]!TablaTransporte[#Data],2,FALSE),0) -> 1330000 | E36: =B36*C36*D36 -> 1995000
A37: Volqueta de 14 m³ | B37: 1 | C37: 1.5 | D37: =IFERROR(VLOOKUP(A37,[1]!TablaTransporte[#Data],2,FALSE),0) -> 1350000 | E37: =B37*C37*D37 -> 2025000
A38: trasporte de equipos | B38: 1 | C38: 0.33 | D38: =IFERROR(VLOOKUP(A38,[1]!TablaTransporte[#Data],2,FALSE),0) -> 1650000 | E38: =B38*C38*D38 -> 544500
D39: =IFERROR(VLOOKUP(A39,[1]!TablaTransporte[#Data],2,FALSE),0) -> 0
F40: =SUM(E36:E38) -> 4564500
F41: =F20+F27+F34+F40 -> 6722811.6
F42: =F41*A42 -> 0
F43: =F41+F42 -> 6722811.6
F44: =F43*A44 -> 0
F45: =F43+F44 -> 6722811.6
F46: =F45/F3 -> 231821.09

Sheet excavación con presencia 
A1: EXCAVACIÓN MECANICA CON PRESENCIA DE TUBERÍA O FACILIDAD ENTERRADA
A2: EQUIPOS | B2: CANT | C2: REND/DIA | D2: TARIFA/DIA | E2: VR.PARCIAL | F2: M3
F3: 820
A4: pala | B4: 4 | C4: 23.4 | D4: =IFERROR(VLOOKUP(A4,[1]!TablaEquipos[#Data],2,FALSE),0) -> 700 | E4: =B4*C4*D4 -> 65520
A5: Pica | B5: 1 | C5: 23.4 | D5: =IFERROR(VLOOKUP(A5,[1]!TablaEquipos[#Data],2,FALSE),0) -> 700 | E5: =B5*C5*D5 -> 16380
A6: Palín | B6: 4 | C6: 23.4 | D6: =IFERROR(VLOOKUP(A6,[1]!TablaEquipos[#Data],2,FALSE),0) -> 700 | E6: =B6*C6*D6 -> 65520
A7: Paladraga | B7: 1 | C7: 23.4 | D7: =IFERROR(VLOOKUP(A7,[1]!TablaEquipos[#Data],2,FALSE),0) -> 1500 | E7: =B7*C7*D7 -> 35100
A8: Barra | B8: 1 | C8: 23.4 | D8: =IFERROR(VLOOKUP(A8,[1]!TablaEquipos[#Data],2,FALSE),0) -> 1500 | E8: =B8*C8*D8 -> 35100
A9: Herramientero | B9: 1 | C9: 23.4 | D9: =IFERROR(VLOOKUP(A9,[1]!TablaEquipos[#Data],2,FALSE),0) -> 1500 | E9: =B9*C9*D9 -> 35100
A10: Sierra circular | B10: 1 | C10: 2 | D10: =IFERROR(VLOOKUP(A10,[1]!TablaEquipos[#Data],2,FALSE),0) -> 15000 | E10: =B10*C10*D10 -> 30000
A11: Carretilla | B11: 3 | C11: 23.4 | D11: =IFERROR(VLOOKUP(A11,[1]!TablaEquipos[#Data],2,FALSE),0) -> 1500 | E11: =B11*C11*D11 -> 105300
A12: Botiquin primeros auxilios | B12: 1 | C12: 23.4 | D12: =IFERROR(VLOOKUP(A12,[1]!TablaEquipos[#Data],2,FALSE),0) -> 4000 | E12: =B12*C12*D12 -> 93600
A13: Camilla primeros auxilios | B13: 1 | C13: 23.4 | D13: =IFERROR(VLOOKUP(A13,[1]!TablaEquipos[#Data],2,FALSE),0) -> 3000 | E13: =B13*C13*D13 -> 70200
A14: Thermo agua | B14: 2 | C14: 23.4 | D14: =IFERROR(VLOOKUP(A14,[1]!TablaEquipos[#Data],2,FALSE),0) -> 1750 | E14: =B14*C14*D14 -> 81900
D15: =IFERROR(VLOOKUP(A15,[1]!TablaEquipos[#Data],2,FALSE),0) -> 0 | E15: =B15*C15*D15 -> 0
F16: =SUM(E4:E15) -> 633720
A17: MATERIALES | B17: CANT | C17: REND/DIA | D17: TARIFA | E17: VR.PARCIAL
A18: Listón de madera 2 x 1 x 3 | B18: 25 | D18: =IFERROR(VLOOKUP(A18,[1]!TablaMateriales[#Data],2,FALSE),0) -> 20000 | E18: =B18*D18 -> 500000
A19: Manila 5/16" | B19: 80 | D19: 3200 | E19: =B19*D19 -> 256000
D20: =IFERROR(VLOOKUP(A20,[1]!TablaMateriales[#Data],2,FALSE),0) -> 0
D21: =IFERROR(VLOOKUP(A21,[1]!TablaMateriales[#Data],2,FALSE),0) -> 0
D22: =IFERROR(VLOOKUP(A22,[1]!TablaMateriales[#Data],2,FALSE),0) -> 0
F23: =SUM(E18:E22) -> 756000
A24: MANO DE OBRA | B24: CANT | C24: REND/DIA | D24: SALARIO | E24: VR.PARCIAL
A25: Capataz | B25: 1 | C25: 13 | D25: ='tabla salarial'!AS4 -> 555393.74 | E25: =B25*C25*D25 -> 7220118.6
A26: Hse | B26: 1 | C26: 13 | D26: ='tabla salarial'!AS4 -> 555393.74 | E26: =B26*C26*D26 -> 7220118.6
A27: Rescatista | B27: 1 | C27: 38 | D27: ='tabla salarial'!AS5 -> 443956.94 | E27: =B27*C27*D27 -> 16870364
A28: Auxiliar Administrativo | B28: 1 | C28: 13 | D28: ='tabla salarial'!AS8 -> 355821.88 | E28: =B28*C28*D28 -> 4625684.4
A29: Oficial construccion | B29: 1 | C29: 38 | D29: ='tabla salarial'!AS7 -> 371571.33 | E29: =B29*C29*D29 -> 14119711
A30: Auxiliar civil | B30: 4 | C30: 38 | D30: ='tabla salarial'!AS9 -> 382109.06 | E30: =B30*C30*D30 -> 58080577
A31: 3 | F31: =SUM(E25:E30) -> 1.0813657e+08
A32: TRANSPORTE | B32: CANT | C32: REND/DIA | D32: TARIFA | E32: VR.PARCIAL
A33: Retroexcavadora de oruga | B33: 1 | C33: 23.4 | D33: =IFERROR(VLOOKUP(A33,[1]!TablaTransporte[#Data],2,FALSE),0) -> 322000 | E33: =B33*C33*D33 -> 7534800
A34: trasporte de equipo | B34: 1 | C34: 2 | D34: =IFERROR(VLOOKUP(A34,[1]!TablaTransporte[#Data],2,FALSE),0) -> 4500000 | E34: =B34*C34*D34 -> 9000000
A35: Buseta Acpm | B35: 1 | C35: 24 | D35: =IFERROR(VLOOKUP(A35,[1]!TablaTransporte[#Data],2,FALSE),0) -> 600000 | E35: =B35*C35*D35 -> 14400000 | F35: =SUM(E33:E34) -> 16534800
F36: =F16+F23+F31+F35 -> 1.2606109e+08
F37: =F36*A37 -> 0
F38: =F36+F37 -> 1.2606109e+08
F39: =F38*A39 -> 0
F40: =F38+F39 -> 1.2606109e+08
F41: =F40/F3 -> 153733.04

Sheet demolición concreto
A1: DEMOLICIÓN CONCRETO Y/O ROCA CON MARTILLO NEUMÁTICO
A2: EQUIPOS | B2: CANT | C2: REND/DIA | D2: TARIFA/DIA | E2: VR.PARCIAL | F2: M3
F3: 52
A4: Pala | B4: 4 | C4: 32 | D4: =IFERROR(VLOOKUP(A4,[1]!TablaEquipos[#Data],2,FALSE),0) -> 700 | E4: =B4*C4*D4 -> 89600
A5: Barra | B5: 4 | C5: 32 | D5: =IFERROR(VLOOKUP(A5,[1]!TablaEquipos[#Data],2,FALSE),0) -> 1500 | E5: =B5*C5*D5 -> 192000
A6: Herramientero | B6: 1 | C6: 32 | D6: =IFERROR(VLOOKUP(A6,[1]!TablaEquipos[#Data],2,FALSE),0) -> 1500 | E6: =B6*C6*D6 -> 48000
A7: Carretilla | B7: 6 | C7: 32 | D7: =IFERROR(VLOOKUP(A7,[1]!TablaEquipos[#Data],2,FALSE),0) -> 1500 | E7: =B7*C7*D7 -> 288000
A8: Martillo demoledor neumático/eléctrico | B8: 3 | C8: 32 | D8: =IFERROR(VLOOKUP(A8,[1]!TablaEquipos[#Data],2,FALSE),0) -> 80000 | E8: =B8*C8*D8 -> 7680000
A9: Pulidora 7" | B9: 1 | C9: 32 | D9: =IFERROR(VLOOKUP(A9,[1]!TablaEquipos[#Data],2,FALSE),0) -> 15000 | E9: =B9*C9*D9 -> 480000
A10: Extencion electrica 100mts | B10: 3 | C10: 32 | D10: =IFERROR(VLOOKUP(A10,[1]!TablaEquipos[#Data],2,FALSE),0) -> 15000 | E10: =B10*C10*D10 -> 1440000
A11: Planta electrica 7,5 kwa | B11: 1 | C11: 32 | D11: =IFERROR(VLOOKUP(A11,[1]!TablaEquipos[#Data],2,FALSE),0) -> 40000 | E11: =B11*C11*D11 -> 1280000
A12: taladro Rotomartillo | B12: 1 | C12: 32 | D12: 60000 | E12: =B12*C12*D12 -> 1920000
F19: =SUM(E4:E18) -> 13417600
A20: MATERIALES | B20: CANT | C20: REND/DIA | D20: TARIFA | E20: VR.PARCIAL
A21: Cinta de seguridad amarilla/negra x 500 | B21: 1 | D21: =IFERROR(VLOOKUP(A21,[1]!TablaMateriales[#Data],2,FALSE),0) -> 55000 | E21: =B21*D21 -> 55000 | H21: 100
A22: Broca tipo pala | B22: 15 | D22: =IFERROR(VLOOKUP(A22,[1]!TablaMateriales[#Data],2,FALSE),0) -> 65000 | E22: =B22*D22 -> 975000
A23: Broca tipo punta | B23: 15 | D23: =IFERROR(VLOOKUP(A23,[1]!TablaMateriales[#Data],2,FALSE),0) -> 65000 | E23: =B23*D23 -> 975000
A24: Aceite lubricante | B24: 1 | D24: =IFERROR(VLOOKUP(A24,[1]!TablaMateriales[#Data],2,FALSE),0) -> 65000 | E24: =B24*D24 -> 65000
A25: Aceite 15w40 | B25: 1 | D25: =IFERROR(VLOOKUP(A25,[1]!TablaMateriales[#Data],2,FALSE),0) -> 85000 | E25: =B25*D25 -> 85000
A26: Broca Rotomartillo 1 1/4 x 12" | B26: 1 | D26: =IFERROR(VLOOKUP(A26,[1]!TablaMateriales[#Data],2,FALSE),0) -> 455000 | E26: =B26*D26 -> 455000
A27: Sacos de polipropileno | B27: 100 | D27: =IFERROR(VLOOKUP(A27,[1]!TablaMateriales[#Data],2,FALSE),0) -> 1200 | E27: =B27*D27 -> 120000
A28: guantes antivibración | B28: 8 | D28: =IFERROR(VLOOKUP(A28,[1]!TablaMateriales[#Data],2,FALSE),0) -> 33200 | E28: =B28*D28 -> 265600
A29: careta de esmerilar para casco | B29: 8 | D29: =IFERROR(VLOOKUP(A29,[1]!TablaMateriales[#Data],2,FALSE),0) -> 42000 | E29: =B29*D29 -> 336000
A30: Suelo o arena para sacos con transporte | B30: 7 | D30: =IFERROR(VLOOKUP(A30,[1]!TablaMateriales[#Data],2,FALSE),0) -> 58000 | E30: =B30*D30 -> 406000
A31: discos de corte de 7" / discos diamantados o abrasivos | B31: 10 | D31: =IFERROR(VLOOKUP(A31,[1]!TablaMateriales[#Data],2,FALSE),0) -> 62000 | E31: =B31*D31 -> 620000
A32: Disco de corte 7" para metarl 1 1/16" | B32: 20 | D32: =IFERROR(VLOOKUP(A32,[1]!TablaMateriales[#Data],2,FALSE),0) -> 11500 | E32: =B32*D32 -> 230000
A33: Cras | B33: 1 | D33: =IFERROR(VLOOKUP(A33,[1]!TablaMateriales[#Data],2,FALSE),0) -> 1185900 | E33: =B33*D33 -> 1185900
A34: ACPM | B34: 10 | D34: =IFERROR(VLOOKUP(A34,[1]!TablaMateriales[#Data],2,FALSE),0) -> 0 | E34: =B34*D34 -> 0
F35: =SUM(E21:E34) -> 5773500
A36: MANO DE OBRA | B36: CANT | C36: REND/DIA | D36: SALARIO | E36: VR.PARCIAL
A37: Capataz | B37: 1 | C37: 40 | D37: ='tabla salarial'!AS4 -> 555393.74 | E37: =B37*C37*D37 -> 22215750
A38: Hse | B38: 1 | C38: 40 | D38: ='tabla salarial'!AS4 -> 555393.74 | E38: =B38*C38*D38 -> 22215750
A39: Oficial construccion | B39: 2 | C39: 40 | D39: ='tabla salarial'!AS7 -> 371571.33 | E39: =B39*C39*D39 -> 29725706
A40: Auxiliar Administrativo | B40: 1 | C40: 40 | D40: ='tabla salarial'!AS8 -> 355821.88 | E40: =B40*C40*D40 -> 14232875
A41: Auxiliar civil | B41: 12 | C41: 40 | D41: ='tabla salarial'!AS9 -> 382109.06 | E41: =B41*C41*D41 -> 1.8341235e+08
F42: =SUM(E37:E41) -> 2.7180243e+08
A43: TRANSPORTE | B43: CANT | C43: REND/DIA | D43: TARIFA | E43: VR.PARCIAL
A44: Camión doble cabina | B44: 1 | C44: 1 | D44: =IFERROR(VLOOKUP(A44,[1]!TablaTransporte[#Data],2,FALSE),0) -> 550000 | E44: =B44*C44*D44 -> 550000
A45: Acarreo por km | D45: =IFERROR(VLOOKUP(A45,[1]!TablaTransporte[#Data],2,FALSE),0) -> 65000 | E45: =B45*C45*D45 -> 0
A46: Retroexcavadora de llantas | B46: 1 | C46: 1 | D46: =IFERROR(VLOOKUP(A46,[1]!TablaTransporte[#Data],2,FALSE),0) -> 1330000 | E46: =B46*C46*D46 -> 1330000
A47: Volqueta de 14 m³ | D47: =IFERROR(VLOOKUP(A47,[1]!TablaTransporte[#Data],2,FALSE),0) -> 1350000 | E47: =B47*C47*D47 -> 0
A48: Buseta | B48: 1 | C48: 26 | D48: =IFERROR(VLOOKUP(A48,[1]!TablaTransporte[#Data],2,FALSE),0) -> 0 | E48: =B48*C48*D48 -> 0
A49: trasporte de equipo | B49: 1 | C49: 4 | D49: =IFERROR(VLOOKUP(A49,[1]!TablaTransporte[#Data],2,FALSE),0) -> 4500000 | E49: =B49*C49*D49 -> 18000000
F50: =SUM(E44:E49) -> 19880000
F51: =F19+F35+F42+F50 -> 3.1087353e+08
F52: =F51*A52 -> 0
F53: =F51+F52 -> 3.1087353e+08
F54: =F53*A54 -> 0
F55: =F53+F54 -> 3.1087353e+08
F56: =F55/F3 -> 5978337.1

Sheet relleno manual 
A1: RELLENO MANUAL COMPACTADO-MATERIAL DE SITIO, PRODUCTO DE EXCAVACIÓN
A2: EQUIPOS | B2: CANT | C2: REND/DIA | D2: TARIFA/DIA | E2: VR.PARCIAL | F2: M3
F3: 780
A4: Pala | B4: 8 | C4: 35 | D4: =IFERROR(VLOOKUP(A4,[1]!TablaEquipos[#Data],2,FALSE),0) -> 700 | E4: =B4*C4*D4 -> 196000
A5: Pica | B5: 8 | C5: 35 | D5: =IFERROR(VLOOKUP(A5,[1]!TablaEquipos[#Data],2,FALSE),0) -> 700 | E5: =B5*C5*D5 -> 196000
A6: Palín | B6: 8 | C6: 35 | D6: =IFERROR(VLOOKUP(A6,[1]!TablaEquipos[#Data],2,FALSE),0) -> 700 | E6: =B6*C6*D6 -> 196000
A7: Barra | B7: 2 | C7: 35 | D7: =IFERROR(VLOOKUP(A7,[1]!TablaEquipos[#Data],2,FALSE),0) -> 1500 | E7: =B7*C7*D7 -> 105000
A8: Herramientero | B8: 1 | C8: 35 | D8: =IFERROR(VLOOKUP(A8,[1]!TablaEquipos[#Data],2,FALSE),0) -> 1500 | E8: =B8*C8*D8 -> 52500
A9: Sierra circular | B9: 1 | D9: =IFERROR(VLOOKUP(A9,[1]!TablaEquipos[#Data],2,FALSE),0) -> 15000 | E9: =B9*C9*D9 -> 0
A10: Carretilla | B10: 6 | C10: 35 | D10: =IFERROR(VLOOKUP(A10,[1]!TablaEquipos[#Data],2,FALSE),0) -> 1500 | E10: =B10*C10*D10 -> 315000
A11: Vibrocompactador tipo rana | B11: 1 | C11: 20 | D11: =IFERROR(VLOOKUP(A11,[1]!TablaEquipos[#Data],2,FALSE),0) -> 40000 | E11: =B11*C11*D11 -> 800000
A12: Vibrocompactador tipo canguro | B12: 1 | C12: 15 | D12: =IFERROR(VLOOKUP(A12,[1]!TablaEquipos[#Data],2,FALSE),0) -> 60000 | E12: =B12*C12*D12 -> 900000
A13: Pizon manual | B13: 4 | C13: 35 | D13: =IFERROR(VLOOKUP(A13,[1]!TablaEquipos[#Data],2,FALSE),0) -> 1000 | E13: =B13*C13*D13 -> 140000
D14: =IFERROR(VLOOKUP(A14,[1]!TablaEquipos[#Data],2,FALSE),0) -> 0 | E14: =B14*C14*D14 -> 0
D15: 0 | E15: =B15*C15*D15 -> 0
F16: =SUM(E4:E15) -> 2900500
A17: MATERIALES | B17: CANT | C17: REND/DIA | D17: TARIFA | E17: VR.PARCIAL
A18: Plástico negro | B18: 100 | D18: =IFERROR(VLOOKUP(A18,[1]!TablaMateriales[#Data],2,FALSE),0) -> 9500 | E18: =B18*D18 -> 950000
A19: Acpm galon | B19: 15 | D19: =IFERROR(VLOOKUP(A19,[1]!TablaMateriales[#Data],2,FALSE),0) -> 11500 | E19: =B19*D19 -> 172500
A20: Agua m3 | B20: 40 | C20: 1 | D20: =IFERROR(VLOOKUP(A20,[1]!TablaMateriales[#Data],2,FALSE),0) -> 6000 | E20: =B20*D20 -> 240000
F23: =SUM(E18:E22) -> 1362500
A24: MANO DE OBRA | B24: CANT | C24: REND/DIA | D24: SALARIO | E24: VR.PARCIAL
A25: Capataz | B25: 1 | C25: 44 | D25: 539456.24 | E25: =B25*C25*D25 -> 23736075
A26: Hse | B26: 1 | C26: 44 | D26: 539456.24 | E26: =B26*C26*D26 -> 23736075
A27: Topografo | D27: 539456.24 | E27: =B27*C27*D27 -> 0
A28: Cadenero 1 | D28: 434781.14 | E28: =B28*C28*D28 -> 0
A29: Andamiero | D29: 434781.14 | E29: =B29*C29*D29 -> 0
A30: Oficial construccion | B30: 2 | C30: 44 | D30: 399154.66 | E30: =B30*C30*D30 -> 35125610
A31: Auxiliar Administrativo | B31: 1 | C31: 44 | D31: 383405.21 | E31: =B31*C31*D31 -> 16869829
A32: Auxiliar civil | B32: 8 | C32: 44 | D32: 355463.25 | E32: =B32*C32*D32 -> 1.2512306e+08
F33: =SUM(E25:E32) -> 2.2459065e+08
A34: TRANSPORTE | B34: CANT | C34: REND/DIA | D34: TARIFA | E34: VR.PARCIAL
A35: Camión doble cabina viaje | B35: 1 | C35: 10 | D35: =IFERROR(VLOOKUP(A35,[1]!TablaTransporte[#Data],2,FALSE),0) -> 0 | E35: =B35*C35*D35 -> 0
A36: Buseta | B36: 1 | C36: 28 | D36: =IFERROR(VLOOKUP(A36,[1]!TablaTransporte[#Data],2,FALSE),0) -> 0 | E36: =B36*C36*D36 -> 0
D37: =IFERROR(VLOOKUP(A37,[1]!TablaTransporte[#Data],2,FALSE),0) -> 0
F39: =SUM(E35:E36) -> 0
F40: =F16+F23+F33+F39 -> 2.2885365e+08
F41: =F40*A41 -> 0
F42: =F40+F41 -> 2.2885365e+08
F43: =F42*A43 -> 0
F44: =F42+F43 -> 2.2885365e+08
F45: =F44/F3 -> 293402.12

Sheet relleno mecanico
A1: RELLENO MECÁNICO COMPACTADO CON MATERIAL DE SITIO
A2: EQUIPOS | B2: CANT | C2: REND/DIA | D2: TARIFA/DIA | E2: VR.PARCIAL | F2: M3
F3: 269
A4: Machete | D4: =IFERROR(VLOOKUP(A4,[1]!TablaEquipos[#Data],2,FALSE),0) -> 1500 | E4: =B4*C4*D4 -> 0 | F4: =SUM(E4:E25) -> 1186750
A5: Martillo | D5: =IFERROR(VLOOKUP(A5,[1]!TablaEquipos[#Data],2,FALSE),0) -> 700 | E5: =B5*C5*D5 -> 0
A6: Pala | B6: 3 | C6: 15 | D6: =IFERROR(VLOOKUP(A6,[1]!TablaEquipos[#Data],2,FALSE),0) -> 700 | E6: =B6*C6*D6 -> 31500
A7: Pica | D7: =IFERROR(VLOOKUP(A7,[1]!TablaEquipos[#Data],2,FALSE),0) -> 700 | E7: =B7*C7*D7 -> 0
A8: Palín | B8: 3 | C8: 15 | D8: =IFERROR(VLOOKUP(A8,[1]!TablaEquipos[#Data],2,FALSE),0) -> 700 | E8: =B8*C8*D8 -> 31500
A9: Paladraga | D9: =IFERROR(VLOOKUP(A9,[1]!TablaEquipos[#Data],2,FALSE),0) -> 1500 | E9: =B9*C9*D9 -> 0
A10: Barra | B10: 1 | C10: 15 | D10: =IFERROR(VLOOKUP(A10,[1]!TablaEquipos[#Data],2,FALSE),0) -> 1500 | E10: =B10*C10*D10 -> 22500
A11: Herramientero | B11: 1 | C11: 15 | D11: =IFERROR(VLOOKUP(A11,[1]!TablaEquipos[#Data],2,FALSE),0) -> 1500 | E11: =B11*C11*D11 -> 22500
A12: Sierra circular | D12: =IFERROR(VLOOKUP(A12,[1]!TablaEquipos[#Data],2,FALSE),0) -> 15000 | E12: =B12*C12*D12 -> 0
A13: Alicate diablo | D13: =IFERROR(VLOOKUP(A13,[1]!TablaEquipos[#Data],2,FALSE),0) -> 500 | E13: =B13*C13*D13 -> 0
A14: Alicate universal | D14: =IFERROR(VLOOKUP(A14,[1]!TablaEquipos[#Data],2,FALSE),0) -> 500 | E14: =B14*C14*D14 -> 0
A15: Andamios Layher | D15: =IFERROR(VLOOKUP(A15,[1]!TablaEquipos[#Data],2,FALSE),0) -> 135000 | E15: =B15*C15*D15 -> 0
A16: Arnés de seguridad | D16: =IFERROR(VLOOKUP(A16,[1]!TablaEquipos[#Data],2,FALSE),0) -> 0 | E16: =B16*C16*D16 -> 0
A17: Línea de vida | D17: =IFERROR(VLOOKUP(A17,[1]!TablaEquipos[#Data],2,FALSE),0) -> 9000 | E17: =B17*C17*D17 -> 0
A18: Nivel torpedo | D18: =IFERROR(VLOOKUP(A18,[1]!TablaEquipos[#Data],2,FALSE),0) -> 1000 | E18: =B18*C18*D18 -> 0
A19: Carretilla | B19: 2 | C19: 15 | D19: =IFERROR(VLOOKUP(A19,[1]!TablaEquipos[#Data],2,FALSE),0) -> 1500 | E19: =B19*C19*D19 -> 45000
A20: Martillo demoledor neumático/eléctrico | D20: =IFERROR(VLOOKUP(A20,[1]!TablaEquipos[#Data],2,FALSE),0) -> 80000 | E20: =B20*C20*D20 -> 0
A21: Rodillo tipo Benitín | B21: 1 | C21: 10 | D21: =IFERROR(VLOOKUP(A21,[1]!TablaEquipos[#Data],2,FALSE),0) -> 100000 | E21: =B21*C21*D21 -> 1000000
A22: Vibrocompactador tipo rana | B22: 1 | D22: =IFERROR(VLOOKUP(A22,[1]!TablaEquipos[#Data],2,FALSE),0) -> 40000 | E22: =B22*C22*D22 -> 0
A23: Vibrocompactador tipo canguro | B23: 1 | D23: =IFERROR(VLOOKUP(A23,[1]!TablaEquipos[#Data],2,FALSE),0) -> 60000 | E23: =B23*C23*D23 -> 0
A24: Paletas | B24: 2 | C24: 15 | D24: =IFERROR(VLOOKUP(A24,[1]!TablaEquipos[#Data],2,FALSE),0) -> 500 | E24: =B24*C24*D24 -> 15000
A25: Chaleco reflectivo | B25: 2 | C25: 15 | D25: 625 | E25: =B25*C25*D25 -> 18750
A27: MATERIALES | B27: CANT | C27: REND/DIA | D27: TARIFA | E27: VR.PARCIAL
A28: Listón de madera 2 x 4 x 3 | D28: =IFERROR(VLOOKUP(A28,[1]!TablaMateriales[#Data],2,FALSE),0) -> 35000 | E28: =B28*D28 -> 0
A29: Listón de madera 2 x 1 x 3 | D29: =IFERROR(VLOOKUP(A29,[1]!TablaMateriales[#Data],2,FALSE),0) -> 20000 | E29: =B29*D29 -> 0
A30: Cal | D30: =IFERROR(VLOOKUP(A30,[1]!TablaMateriales[#Data],2,FALSE),0) -> 50000 | E30: =B30*D30 -> 0
A31: Nailon de color | D31: =IFERROR(VLOOKUP(A31,[1]!TablaMateriales[#Data],2,FALSE),0) -> 0 | E31: =B31*D31 -> 0
A32: Puntilla de 2,5" | D32: =IFERROR(VLOOKUP(A32,[1]!TablaMateriales[#Data],2,FALSE),0) -> 9500 | E32: =B32*D32 -> 0
A33: Puntilla de 3,5" | D33: =IFERROR(VLOOKUP(A33,[1]!TablaMateriales[#Data],2,FALSE),0) -> 9500 | E33: =B33*D33 -> 0
A34: Clavo de acero de 3" | D34: =IFERROR(VLOOKUP(A34,[1]!TablaMateriales[#Data],2,FALSE),0) -> 15000 | E34: =B34*D34 -> 0
A35: Pintura en aerosol | D35: =IFERROR(VLOOKUP(A35,[1]!TablaMateriales[#Data],2,FALSE),0) -> 20000 | E35: =B35*D35 -> 0
A36: Cinta de seguridad amarilla/negra x 500 | D36: =IFERROR(VLOOKUP(A36,[1]!TablaMateriales[#Data],2,FALSE),0) -> 55000 | E36: =B36*D36 -> 0
A37: Grapa | D37: =IFERROR(VLOOKUP(A37,[1]!TablaMateriales[#Data],2,FALSE),0) -> 15900 | E37: =B37*D37 -> 0
A38: Alambre HG calibre 14 | D38: =IFERROR(VLOOKUP(A38,[1]!TablaMateriales[#Data],2,FALSE),0) -> 14000 | E38: =B38*D38 -> 0
A39: Tela verde de 2 metros | D39: =IFERROR(VLOOKUP(A39,[1]!TablaMateriales[#Data],2,FALSE),0) -> 3800 | E39: =B39*D39 -> 0
... A42: Aceite lubricante | D42: =IFERROR(VLOOKUP(A42,[1]!TablaMateriales[#Data],2,FALSE),0) -> 65000 | E42: =B42*D42 -> 0
A43: Plástico negro | B43: 70 | D43: =IFERROR(VLOOKUP(A43,[1]!TablaMateriales[#Data],2,FALSE),0) -> 9500 | E43: =B43*D43 -> 665000
A44: Acpm Galon | B44: 15 | D44: =IFERROR(VLOOKUP(A44,[1]!TablaMateriales[#Data],2,FALSE),0) -> 11500 | E44: =B44*D44 -> 172500
A45: Carpa plastica 6x6 | D45: =IFERROR(VLOOKUP(A45,[1]!TablaMateriales[#Data],2,FALSE),0) -> 32500 | E45: =B45*D45 -> 0
A46: Carpa plastica 4x4 | D46: =IFERROR(VLOOKUP(A46,[1]!TablaMateriales[#Data],2,FALSE),0) -> 27500 | E46: =B46*D46 -> 0
A47: Agua m3 | B47: 13.45 | D47: =IFERROR(VLOOKUP(A47,[1]!TablaMateriales[#Data],2,FALSE),0) -> 6000 | E47: =B47*D47 -> 80700
A48: Liston 4x4x3 | B48: 8 | D48: 70000 | E48: =B48*D48 -> 560000
F49: =SUM(E28:E48) -> 1478200
A50: MANO DE OBRA | B50: CANT | C50: REND/DIA | D50: SALARIO | E50: VR.PARCIAL
A51: Capataz | B51: 1 | C51: 11 | D51: 539456.24 | E51: =B51*C51*D51 -> 5934018.6
A52: Hse | B52: 1 | C52: 11 | D52: 539456.24 | E52: =B52*C52*D52 -> 5934018.6
A53: Topografo | B53: 1 | D53: 539456.24 | E53: =B53*C53*D53 -> 0
A54: Cadenero 1 | B54: 1.5 | D54: 434781.14 | E54: =B54*C54*D54 -> 0
A55: Andamiero | B55: 2 | D55: 434781.14 | E55: =B55*C55*D55 -> 0
A56: Oficial construccion | B56: 1 | C56: 11 | D56: 399154.66 | E56: =B56*C56*D56 -> 4390701.3
A57: Auxiliar Administrativo | B57: 1 | C57: 11 | D57: 383405.21 | E57: =B57*C57*D57 -> 4217457.3
A58: Auxiliar civil | B58: 3 | C58: 11 | D58: 355463.25 | E58: =B58*C58*D58 -> 11730287
F59: =SUM(E51:E58) -> 32206483
A60: TRANSPORTE | B60: CANT | C60: REND/DIA | D60: TARIFA | E60: VR.PARCIAL
A61: Camión doble cabina | B61: 1 | C61: 2 | D61: =IFERROR(VLOOKUP(A61,[1]!TablaTransporte[#Data],2,FALSE),0) -> 550000 | E61: =B61*C61*D61 -> 1100000
A62: Acarreo por km | D62: =IFERROR(VLOOKUP(A62,[1]!TablaTransporte[#Data],2,FALSE),0) -> 65000 | E62: =B62*C62*D62 -> 0
A63: Retroexcavadora de oruga | B63: 1 | C63: 6 | D63: =IFERROR(VLOOKUP(A63,[1]!TablaTransporte[#Data],2,FALSE),0) -> 322000 | E63: =B63*C63*D63 -> 1932000
A64: Transporte de equipo | B64: 1 | C64: 4 | D64: =IFERROR(VLOOKUP(A64,[1]!TablaTransporte[#Data],2,FALSE),0) -> 0 | E64: =B64*C64*D64 -> 0
A65: Retroexcavadora con llantas | D65: =IFERROR(VLOOKUP(A65,[1]!TablaTransporte[#Data],2,FALSE),0) -> 190000 | E65: =B65*C65*D65 -> 0
A66: Volqueta de 14 m³ | D66: =IFERROR(VLOOKUP(A66,[1]!TablaTransporte[#Data],2,FALSE),0) -> 1350000 | E66: =B66*C66*D66 -> 0
A67: Vibro compactador grande | D67: =IFERROR(VLOOKUP(A67,[1]!TablaTransporte[#Data],2,FALSE),0) -> 1330000 | E67: =B67*C67*D67 -> 0
F68: =SUM(E61:E67) -> 3032000
F69: =F4+F49+F59+F68 -> 37903433
F70: =F69*A70 -> 0
F71: =F69+F70 -> 37903433
F72: =F71*A72 -> 0
F73: =F71+F72 -> 37903433
F74: =F73/F3 -> 140904.96

Sheet relleno con material
A1: RELLENO CON MATERIAL SELECCIONADO
A2: EQUIPOS | B2: CANT | C2: REND/DIA | D2: TARIFA/DIA | E2: VR.PARCIAL | F2: M3
F3: 728
A4: Machete | B4: 1 | D4: =IFERROR(VLOOKUP(A4,[1]!TablaEquipos[#Data],2,FALSE),0) -> 1500 | E4: =B4*C4*D4 -> 0
A5: Lima triangular | B5: 1 | D5: =IFERROR(VLOOKUP(A5,[1]!TablaEquipos[#Data],2,FALSE),0) -> 700 | E5: =B5*C5*D5 -> 0
A6: Martillo | B6: 1 | D6: =IFERROR(VLOOKUP(A6,[1]!TablaEquipos[#Data],2,FALSE),0) -> 700 | E6: =B6*C6*D6 -> 0
A7: Pala | B7: 8 | C7: 18 | D7: =IFERROR(VLOOKUP(A7,[1]!TablaEquipos[#Data],2,FALSE),0) -> 700 | E7: =B7*C7*D7 -> 100800
A8: Pica | B8: 8 | D8: =IFERROR(VLOOKUP(A8,[1]!TablaEquipos[#Data],2,FALSE),0) -> 700 | E8: =B8*C8*D8 -> 0
A9: Palín | B9: 8 | C9: 18 | D9: =IFERROR(VLOOKUP(A9,[1]!TablaEquipos[#Data],2,FALSE),0) -> 700 | E9: =B9*C9*D9 -> 100800
A10: Paladraga | B10: 4 | D10: =IFERROR(VLOOKUP(A10,[1]!TablaEquipos[#Data],2,FALSE),0) -> 1500 | E10: =B10*C10*D10 -> 0
A11: Barra | B11: 1 | C11: 18 | D11: =IFERROR(VLOOKUP(A11,[1]!TablaEquipos[#Data],2,FALSE),0) -> 1500 | E11: =B11*C11*D11 -> 27000
A12: Herramientero | B12: 1 | C12: 18 | D12: =IFERROR(VLOOKUP(A12,[1]!TablaEquipos[#Data],2,FALSE),0) -> 1500 | E12: =B12*C12*D12 -> 27000
A13: Sierra circular | B13: 1 | D13: =IFERROR(VLOOKUP(A13,[1]!TablaEquipos[#Data],2,FALSE),0) -> 15000 | E13: =B13*C13*D13 -> 0
A14: Alicate diablo | D14: =IFERROR(VLOOKUP(A14,[1]!TablaEquipos[#Data],2,FALSE),0) -> 500 | E14: =B14*C14*D14 -> 0
A15: Alicate universal | D15: =IFERROR(VLOOKUP(A15,[1]!TablaEquipos[#Data],2,FALSE),0) -> 500 | E15: =B15*C15*D15 -> 0
A16: Andamios Layher | D16: =IFERROR(VLOOKUP(A16,[1]!TablaEquipos[#Data],2,FALSE),0) -> 135000 | E16: =B16*C16*D16 -> 0
A17: Arnés de seguridad | D17: =IFERROR(VLOOKUP(A17,[1]!TablaEquipos[#Data],2,FALSE),0) -> 0 | E17: =B17*C17*D17 -> 0
A18: Línea de vida | D18: =IFERROR(VLOOKUP(A18,[1]!TablaEquipos[#Data],2,FALSE),0) -> 9000 | E18: =B18*C18*D18 -> 0
A19: Nivel torpedo | D19: =IFERROR(VLOOKUP(A19,[1]!TablaEquipos[#Data],2,FALSE),0) -> 1000 | E19: =B19*C19*D19 -> 0
A20: Carretilla | B20: 6 | C20: 18 | D20: =IFERROR(VLOOKUP(A20,[1]!TablaEquipos[#Data],2,FALSE),0) -> 1500 | E20: =B20*C20*D20 -> 162000
A21: Martillo demoledor neumático/eléctrico | D21: =IFERROR(VLOOKUP(A21,[1]!TablaEquipos[#Data],2,FALSE),0) -> 80000 | E21: =B21*C21*D21 -> 0
A22: Rodillo tipo Benitín | B22: 1 | C22: 2 | D22: =IFERROR(VLOOKUP(A22,[1]!TablaEquipos[#Data],2,FALSE),0) -> 100000 | E22: =B22*C22*D22 -> 200000
A23: Vibrocompactador tipo rana | B23: 1 | C23: 7 | D23: =IFERROR(VLOOKUP(A23,[1]!TablaEquipos[#Data],2,FALSE),0) -> 40000 | E23: =B23*C23*D23 -> 280000
A24: Vibrocompactador tipo canguro | B24: 1 | C24: 9 | D24: =IFERROR(VLOOKUP(A24,[1]!TablaEquipos[#Data],2,FALSE),0) -> 60000 | E24: =B24*C24*D24 -> 540000
A25: Paletas | B25: 2 | C25: 18 | D25: =IFERROR(VLOOKUP(A25,[1]!TablaEquipos[#Data],2,FALSE),0) -> 500 | E25: =B25*C25*D25 -> 18000
A26: Chaleco reflectivo | B26: 2 | C26: 18 | D26: =IFERROR(VLOOKUP(A26,[1]!TablaEquipos[#Data],2,FALSE),0) -> 625 | E26: =B26*C26*D26 -> 22500
F27: =SUM(E4:E26) -> 1478100
A28: MATERIALES | B28: CANT | C28: REND/DIA | D28: TARIFA | E28: VR.PARCIAL
A29: Listón de madera 2 x 4 x 3 | B29: 15 | D29: =IFERROR(VLOOKUP(A28,[1]!TablaMateriales[#Data],2,FALSE),0) -> 0 | E29: =B29*D29 -> 0
A30: Listón de madera 2 x 1 x 3 | B30: 15 | D30: =IFERROR(VLOOKUP(A29,[1]!TablaMateriales[#Data],2,FALSE),0) -> 35000 | E30: =B30*D30 -> 525000
A31: Cal | D31: =IFERROR(VLOOKUP(A30,[1]!TablaMateriales[#Data],2,FALSE),0) -> 20000 | E31: =B31*D31 -> 0
A32: Nailon de color | D32: =IFERROR(VLOOKUP(A31,[1]!TablaMateriales[#Data],2,FALSE),0) -> 50000 | E32: =B32*D32 -> 0
A33: Puntilla de 2,5" | D33: =IFERROR(VLOOKUP(A32,[1]!TablaMateriales[#Data],2,FALSE),0) -> 0 | E33: =B33*D33 -> 0
A34: Puntilla de 3,5" | B34: 5 | D34: =IFERROR(VLOOKUP(A33,[1]!TablaMateriales[#Data],2,FALSE),0) -> 9500 | E34: =B34*D34 -> 47500
A35: Clavo de acero de 3" | D35: =IFERROR(VLOOKUP(A34,[1]!TablaMateriales[#Data],2,FALSE),0) -> 9500 | E35: =B35*D35 -> 0
A36: Pintura en aerosol | D36: =IFERROR(VLOOKUP(A35,[1]!TablaMateriales[#Data],2,FALSE),0) -> 15000 | E36: =B36*D36 -> 0
A37: Cinta de seguridad amarilla/negra x 500 | B37: 3 | D37: =IFERROR(VLOOKUP(A36,[1]!TablaMateriales[#Data],2,FALSE),0) -> 20000 | E37: =B37*D37 -> 60000
A38: Grapa | D38: =IFERROR(VLOOKUP(A37,[1]!TablaMateriales[#Data],2,FALSE),0) -> 55000 | E38: =B38*D38 -> 0
A39: Alambre HG calibre 14 | D39: =IFERROR(VLOOKUP(A38,[1]!TablaMateriales[#Data],2,FALSE),0) -> 15900 | E39: =B39*D39 -> 0
A40: Tela verde de 2 metros | D40: =IFERROR(VLOOKUP(A39,[1]!TablaMateriales[#Data],2,FALSE),0) -> 14000 | E40: =B40*D40 -> 0
A41: Broca tipo pala | D41: =IFERROR(VLOOKUP(A40,[1]!TablaMateriales[#Data],2,FALSE),0) -> 3800 | E41: =B41*D41 -> 0
A42: Broca tipo punta | D42: =IFERROR(VLOOKUP(A41,[1]!TablaMateriales[#Data],2,FALSE),0) -> 65000 | E42: =B42*D42 -> 0
A43: Aceite lubricante | D43: =IFERROR(VLOOKUP(A42,[1]!TablaMateriales[#Data],2,FALSE),0) -> 65000 | E43: =B43*D43 -> 0
A44: Plástico negro | B44: 75 | D44: =IFERROR(VLOOKUP(A43,[1]!TablaMateriales[#Data],2,FALSE),0) -> 65000 | E44: =B44*D44 -> 4875000
A45: Acpm | B45: 15 | D45: =IFERROR(VLOOKUP(A44,[1]!TablaMateriales[#Data],2,FALSE),0) -> 9500 | E45: =B45*D45 -> 142500
A46: Material selecionado | B46: 728 | D46: =IFERROR(VLOOKUP(A45,[1]!TablaMateriales[#Data],2,FALSE),0) -> 0 | E46: =B46*D46 -> 0
F49: =SUM(E29:E48) -> 5650000
A50: MANO DE OBRA | B50: CANT | C50: REND/DIA | D50: SALARIO | E50: VR.PARCIAL
A51: Capataz | B51: 1 | C51: 22.7 | D51: 539456.24 | E51: =B51*C51*D51 -> 12245657
A52: Hse | B52: 1 | C52: 22.7 | D52: 539456.24 | E52: =B52*C52*D52 -> 12245657
A53: Topografo | B53: 1 | D53: 539456.24 | E53: =B53*C53*D53 -> 0
A54: Cadenero 1 | B54: 1.5 | D54: 434781.14 | E54: =B54*C54*D54 -> 0
A55: Andamiero | B55: 2 | D55: 434781.14 | E55: =B55*C55*D55 -> 0
A56: Oficial construccion | B56: 2 | C56: 22.7 | D56: 399154.66 | E56: =B56*C56*D56 -> 18121622
A57: Auxiliar Administrativo | B57: 1 | C57: 22.7 | D57: 383405.21 | E57: =B57*C57*D57 -> 8703298.3
A58: Auxiliar civil | B58: 10 | C58: 22.7 | D58: 355463.25 | E58: =B58*C58*D58 -> 80690157
F59: =SUM(E51:E58) -> 1.3200639e+08
A60: TRANSPORTE | B60: CANT | C60: REND/DIA | D60: TARIFA | E60: VR.PARCIAL
A61: Camión doble cabina | B61: 1 | D61: =IFERROR(VLOOKUP(A61,[1]!TablaTransporte[#Data],2,FALSE),0) -> 550000 | E61: =B61*C61*D61 -> 0
A62: Acarreo por km | B62: 1 | D62: =IFERROR(VLOOKUP(A62,[1]!TablaTransporte[#Data],2,FALSE),0) -> 65000 | E62: =B62*C62*D62 -> 0
A63: Retroexcavadora de oruga | B63: 1 | D63: =IFERROR(VLOOKUP(A63,[1]!TablaTransporte[#Data],2,FALSE),0) -> 322000 | E63: =B63*C63*D63 -> 0
A64: Retroexcavadora con llantas | D64: =IFERROR(VLOOKUP(A64,[1]!TablaTransporte[#Data],2,FALSE),0) -> 190000 | E64: =B64*C64*D64 -> 0
A65: Volqueta de 14 m³ | B65: 1 | C65: 13 | D65: =IFERROR(VLOOKUP(A65,[1]!TablaTransporte[#Data],2,FALSE),0) -> 1350000 | E65: =B65*C65*D65 -> 17550000
A66: Vibro compactador grande | B66: 1 | C66: 10 | D66: =IFERROR(VLOOKUP(A66,[1]!TablaTransporte[#Data],2,FALSE),0) -> 1330000 | E66: =B66*C66*D66 -> 13300000
A67: carpa plastica 6x6 | D67: =IFERROR(VLOOKUP(A67,[1]!TablaTransporte[#Data],2,FALSE),0) -> 0 | E67: =B67*C67*D67 -> 0
A68: carpa plastica 4x4 | D68: =IFERROR(VLOOKUP(A68,[1]!TablaTransporte[#Data],2,FALSE),0) -> 0 | E68: =B68*C68*D68 -> 0
A69: Transporte de equipo | B69: 1 | C69: 4 | D69: =IFERROR(VLOOKUP(A69,[1]!TablaTransporte[#Data],2,FALSE),0) -> 0 | E69: =B69*C69*D69 -> 0
A70: carpa plastica 6x4 | D70: =IFERROR(VLOOKUP(A70,[1]!TablaTransporte[#Data],2,FALSE),0) -> 0 | E70: =B70*C70*D70 -> 0
A71: Moto niveladora | B71: 1 | C71: 15 | D71: =IFERROR(VLOOKUP(A71,[1]!TablaTransporte[#Data],2,FALSE),0) -> 1820000 | E71: =B71*C71*D71 -> 27300000
A72: Camion sisterna | B72: 1 | C72: 10 | D72: =IFERROR(VLOOKUP(A72,[1]!TablaTransporte[#Data],2,FALSE),0) -> 0 | E72: =B72*C72*D72 -> 0
A73: minicargador | B73: 1 | C73: 13 | D73: =IFERROR(VLOOKUP(A73,[1]!TablaTransporte[#Data],2,FALSE),0) -> 840000 | E73: =B73*C73*D73 -> 10920000
F74: =SUM(E61:E66) -> 30850000
F75: =F27+F49+F59+F74 -> 1.6998449e+08
F76: =F75*A76 -> 0
F77: =F75+F76 -> 1.6998449e+08
F78: =F77*A78 -> 0
F79: =F77+F78 -> 1.6998449e+08
F80: =F79/F3 -> 233495.18

Sheet suministro y colocación 
A1: SUMINISTRO Y COLOCACIÓN DE AFIRMADO
A2: EQUIPOS | B2: CANT | C2: REND/DIA | D2: TARIFA/DIA | E2: VR.PARCIAL | F2: M3
F3: 89
A4: Machete | B4: 1 | D4: =IFERROR(VLOOKUP(A4,[1]!TablaEquipos[#Data],2,FALSE),0) -> 1500 | E4: =B4*C4*D4 -> 0
A5: Lima triangular | B5: 1 | D5: =IFERROR(VLOOKUP(A5,[1]!TablaEquipos[#Data],2,FALSE),0) -> 700 | E5: =B5*C5*D5 -> 0
A6: Martillo | B6: 1 | D6: =IFERROR(VLOOKUP(A6,[1]!TablaEquipos[#Data],2,FALSE),0) -> 700 | E6: =B6*C6*D6 -> 0
A7: Pala | B7: 8 | C7: 4 | D7: =IFERROR(VLOOKUP(A7,[1]!TablaEquipos[#Data],2,FALSE),0) -> 700 | E7: =B7*C7*D7 -> 22400
A8: Pica | B8: 8 | C8: 4 | D8: =IFERROR(VLOOKUP(A8,[1]!TablaEquipos[#Data],2,FALSE),0) -> 700 | E8: =B8*C8*D8 -> 22400
A9: Palín | D9: =IFERROR(VLOOKUP(A9,[1]!TablaEquipos[#Data],2,FALSE),0) -> 700 | E9: =B9*C9*D9 -> 0
A10: Paladraga | B10: 4 | D10: =IFERROR(VLOOKUP(A10,[1]!TablaEquipos[#Data],2,FALSE),0) -> 1500 | E10: =B10*C10*D10 -> 0
A11: Barra | B11: 1 | C11: 4 | D11: =IFERROR(VLOOKUP(A11,[1]!TablaEquipos[#Data],2,FALSE),0) -> 1500 | E11: =B11*C11*D11 -> 6000
A12: Herramientero | B12: 1 | D12: =IFERROR(VLOOKUP(A12,[1]!TablaEquipos[#Data],2,FALSE),0) -> 1500 | E12: =B12*C12*D12 -> 0
A13: Sierra circular | B13: 1 | D13: =IFERROR(VLOOKUP(A13,[1]!TablaEquipos[#Data],2,FALSE),0) -> 15000 | E13: =B13*C13*D13 -> 0
A14: Alicate diablo | D14: =IFERROR(VLOOKUP(A14,[1]!TablaEquipos[#Data],2,FALSE),0) -> 500 | E14: =B14*C14*D14 -> 0
A15: Alicate universal | D15: =IFERROR(VLOOKUP(A15,[1]!TablaEquipos[#Data],2,FALSE),0) -> 500 | E15: =B15*C15*D15 -> 0
A16: Andamios Layher | D16: =IFERROR(VLOOKUP(A16,[1]!TablaEquipos[#Data],2,FALSE),0) -> 135000 | E16: =B16*C16*D16 -> 0
A17: Arnés de seguridad | D17: =IFERROR(VLOOKUP(A17,[1]!TablaEquipos[#Data],2,FALSE),0) -> 0 | E17: =B17*C17*D17 -> 0
A18: Línea de vida | D18: =IFERROR(VLOOKUP(A18,[1]!TablaEquipos[#Data],2,FALSE),0) -> 9000 | E18: =B18*C18*D18 -> 0
A19: Nivel torpedo | D19: =IFERROR(VLOOKUP(A19,[1]!TablaEquipos[#Data],2,FALSE),0) -> 1000 | E19: =B19*C19*D19 -> 0
A20: Carretilla | B20: 4 | C20: 4 | D20: =IFERROR(VLOOKUP(A20,[1]!TablaEquipos[#Data],2,FALSE),0) -> 1500 | E20: =B20*C20*D20 -> 24000
A21: Martillo demoledor neumático/eléctrico | D21: =IFERROR(VLOOKUP(A21,[1]!TablaEquipos[#Data],2,FALSE),0) -> 80000 | E21: =B21*C21*D21 -> 0
A22: Rodillo tipo Benitín | B22: 1 | D22: =IFERROR(VLOOKUP(A22,[1]!TablaEquipos[#Data],2,FALSE),0) -> 100000 | E22: =B22*C22*D22 -> 0
A23: Vibrocompactador tipo rana | B23: 1 | D23: =IFERROR(VLOOKUP(A23,[1]!TablaEquipos[#Data],2,FALSE),0) -> 40000 | E23: =B23*C23*D23 -> 0
A24: Vibrocompactador tipo canguro | B24: 1 | D24: =IFERROR(VLOOKUP(A24,[1]!TablaEquipos[#Data],2,FALSE),0) -> 60000 | E24: =B24*C24*D24 -> 0
A25: colombina | B25: 16 | C25: 4 | D25: =IFERROR(VLOOKUP(A25,[1]!TablaEquipos[#Data],2,FALSE),0) -> 1000 | E25: =B25*C25*D25 -> 64000
A26: Avisos de seguridad | B26: 30 | C26: 4 | D26: =IFERROR(VLOOKUP(A26,[1]!TablaEquipos[#Data],2,FALSE),0) -> 1000 | E26: =B26*C26*D26 -> 120000
A27: Radio Comunicación | B27: 1 | C27: 4 | D27: =IFERROR(VLOOKUP(A27,[1]!TablaEquipos[#Data],2,FALSE),0) -> 8000 | E27: =B27*C27*D27 -> 32000
A28: Paletas | B28: 2 | C28: 4 | D28: =IFERROR(VLOOKUP(A28,[1]!TablaEquipos[#Data],2,FALSE),0) -> 500 | E28: =B28*C28*D28 -> 4000
A29: Chaleco reflectivo | B29: 2 | C29: 4 | D29: =IFERROR(VLOOKUP(A29,[1]!TablaEquipos[#Data],2,FALSE),0) -> 625 | E29: =B29*C29*D29 -> 5000
F30: =SUM(E4:E29) -> 299800
A31: MATERIALES | B31: CANT | C31: REND/DIA | D31: TARIFA | E31: VR.PARCIAL
A32: Listón de madera 2 x 4 x 3 | B32: 5 | D32: =IFERROR(VLOOKUP(A32,[1]!TablaMateriales[#Data],2,FALSE),0) -> 35000 | E32: =B32*D32 -> 175000
A33: Listón de madera 2 x 1 x 3 | B33: 5 | D33: =IFERROR(VLOOKUP(A33,[1]!TablaMateriales[#Data],2,FALSE),0) -> 20000 | E33: =B33*D33 -> 100000
A34: Cal | D34: =IFERROR(VLOOKUP(A34,[1]!TablaMateriales[#Data],2,FALSE),0) -> 50000 | E34: =B34*D34 -> 0
A35: Nailon de color | D35: =IFERROR(VLOOKUP(A35,[1]!TablaMateriales[#Data],2,FALSE),0) -> 0 | E35: =B35*D35 -> 0
A36: Puntilla de 2,5" | D36: =IFERROR(VLOOKUP(A36,[1]!TablaMateriales[#Data],2,FALSE),0) -> 9500 | E36: =B36*D36 -> 0
A37: Puntilla de 3,5" | D37: =IFERROR(VLOOKUP(A37,[1]!TablaMateriales[#Data],2,FALSE),0) -> 9500 | E37: =B37*D37 -> 0
A38: Clavo de acero de 3" | D38: =IFERROR(VLOOKUP(A38,[1]!TablaMateriales[#Data],2,FALSE),0) -> 15000 | E38: =B38*D38 -> 0
A39: Pintura en aerosol | D39: =IFERROR(VLOOKUP(A39,[1]!TablaMateriales[#Data],2,FALSE),0) -> 20000 | E39: =B39*D39 -> 0
A40: Cinta de seguridad amarilla/negra x 500 | B40: 3 | D40: =IFERROR(VLOOKUP(A40,[1]!TablaMateriales[#Data],2,FALSE),0) -> 55000 | E40: =B40*D40 -> 165000
A41: Grapa | D41: =IFERROR(VLOOKUP(A41,[1]!TablaMateriales[#Data],2,FALSE),0) -> 15900 | E41: =B41*D41 -> 0
A42: Alambre HG calibre 14 | D42: =IFERROR(VLOOKUP(A42,[1]!TablaMateriales[#Data],2,FALSE),0) -> 14000 | E42: =B42*D42 -> 0
A43: Tela verde de 2 metros | D43: =IFERROR(VLOOKUP(A43,[1]!TablaMateriales[#Data],2,FALSE),0) -> 3800 | E43: =B43*D43 -> 0
A44: Broca tipo pala | D44: =IFERROR(VLOOKUP(A44,[1]!TablaMateriales[#Data],2,FALSE),0) -> 65000 | E44: =B44*D44 -> 0
A45: Broca tipo punta | D45: =IFERROR(VLOOKUP(A45,[1]!TablaMateriales[#Data],2,FALSE),0) -> 65000 | E45: =B45*D45 -> 0
A46: Aceite lubricante | D46: =IFERROR(VLOOKUP(A46,[1]!TablaMateriales[#Data],2,FALSE),0) -> 65000 | E46: =B46*D46 -> 0
A47: Plástico negro | B47: 100 | D47: =IFERROR(VLOOKUP(A47,[1]!TablaMateriales[#Data],2,FALSE),0) -> 9500 | E47: =B47*D47 -> 950000
A48: Acpm | D48: =IFERROR(VLOOKUP(A48,[1]!TablaMateriales[#Data],2,FALSE),0) -> 0 | E48: =B48*D48 -> 0
A49: Material selecionado | D49: =IFERROR(VLOOKUP(A49,[1]!TablaMateriales[#Data],2,FALSE),0) -> 0 | E49: =B49*D49 -> 0
A50: Materia de afirmado | D50: =IFERROR(VLOOKUP(A50,[1]!TablaMateriales[#Data],2,FALSE),0) -> 0 | E50: =B50*D50 -> 0
A51: Carpa plastica 6x6 | D51: =IFERROR(VLOOKUP(A51,[1]!TablaMateriales[#Data],2,FALSE),0) -> 32500 | E51: =B51*D51 -> 0
A52: Carpa plastica 4x4 | D52: =IFERROR(VLOOKUP(A52,[1]!TablaMateriales[#Data],2,FALSE),0) -> 27500 | E52: =B52*D52 -> 0
A53: Carpa plastica 6x4 | D53: =IFERROR(VLOOKUP(A53,[1]!TablaMateriales[#Data],2,FALSE),0) -> 30000 | E53: =B53*D53 -> 0
A54: Material para afirmado de cantera | B54: 89 | D54: =IFERROR(VLOOKUP(A54,[1]!TablaMateriales[#Data],2,FALSE),0) -> 0 | E54: =B54*D54 -> 0
A55: Agua m3 | B55: 50 | D55: =IFERROR(VLOOKUP(A55,[1]!TablaMateriales[#Data],2,FALSE),0) -> 6000 | E55: =B55*D55 -> 300000
D56: =IFERROR(VLOOKUP(A56,[1]!TablaMateriales[#Data],2,FALSE),0) -> 0 | E56: =B56*D56 -> 0
D57: =IFERROR(VLOOKUP(A57,[1]!TablaMateriales[#Data],2,FALSE),0) -> 0 | E57: =B57*D57 -> 0
D58: =IFERROR(VLOOKUP(A58,[1]!TablaMateriales[#Data],2,FALSE),0) -> 0 | E58: =B58*D58 -> 0
F60: =SUM(E32:E59) -> 1690000
A61: MANO DE OBRA | B61: CANT | C61: REND/DIA | D61: SALARIO | E61: VR.PARCIAL
A62: Capataz | B62: 1 | C62: 5 | D62: 539456.24 | E62: =B62*C62*D62 -> 2697281.2
A63: Hse | B63: 1 | C63: 5 | D63: 539456.24 | E63: =B63*C63*D63 -> 2697281.2
A64: Topografo | B64: 1 | D64: 539456.24 | E64: =B64*C64*D64 -> 0
A65: Cadenero 1 | B65: 1.5 | D65: 434781.14 | E65: =B65*C65*D65 -> 0
A66: Andamiero | B66: 2 | D66: 434781.14 | E66: =B66*C66*D66 -> 0
A67: Oficial construccion | B67: 1 | C67: 5 | D67: 399154.66 | E67: =B67*C67*D67 -> 1995773.3
A68: Auxiliar Administrativo | B68: 1 | C68: 5 | D68: 383405.21 | E68: =B68*C68*D68 -> 1917026
A69: Auxiliar civil | B69: 8 | C69: 5 | D69: 355463.25 | E69: =B69*C69*D69 -> 14218530
F70: =SUM(E62:E69) -> 23525892
A71: TRANSPORTE | B71: CANT | C71: REND/DIA | D71: TARIFA | E71: VR.PARCIAL
A72: Camión doble cabina | B72: 1 | D72: =IFERROR(VLOOKUP(A72,[1]!TablaTransporte[#Data],2,FALSE),0) -> 550000 | E72: =B72*C72*D72 -> 0
A73: Acarreo por km | B73: 1 | D73: =IFERROR(VLOOKUP(A73,[1]!TablaTransporte[#Data],2,FALSE),0) -> 65000 | E73: =B73*C73*D73 -> 0
A74: Retroexcavadora de oruga | B74: 1 | D74: =IFERROR(VLOOKUP(A74,[1]!TablaTransporte[#Data],2,FALSE),0) -> 322000 | E74: =B74*C74*D74 -> 0
A75: Retroexcavadora con llantas | D75: =IFERROR(VLOOKUP(A75,[1]!TablaTransporte[#Data],2,FALSE),0) -> 190000 | E75: =C75*D75 -> 0
A76: Volqueta de 14 m³ | B76: 1 | C76: 3 | D76: =IFERROR(VLOOKUP(A76,[1]!TablaTransporte[#Data],2,FALSE),0) -> 1350000 | E76: =C76*D76 -> 4050000
A77: Vibro compactador grande | B77: 1 | C77: 2 | D77: =IFERROR(VLOOKUP(A77,[1]!TablaTransporte[#Data],2,FALSE),0) -> 1330000 | E77: =C77*D77 -> 2660000
A78: Transporte de equipo | B78: 1 | C78: 4 | D78: =IFERROR(VLOOKUP(A78,[1]!TablaTransporte[#Data],2,FALSE),0) -> 0 | E78: =B78*C78*D78 -> 0
A79: Moto niveladora | B79: 1 | C79: 2 | D79: =IFERROR(VLOOKUP(A79,[1]!TablaTransporte[#Data],2,FALSE),0) -> 1820000 | E79: =B79*C79*D79 -> 3640000
A80: Camion sisterna | B80: 1 | C80: 2 | D80: =IFERROR(VLOOKUP(A80,[1]!TablaTransporte[#Data],2,FALSE),0) -> 0 | E80: =B80*C80*D80 -> 0
A81: minicargador | B81: 1 | C81: 2 | D81: =IFERROR(VLOOKUP(A81,[1]!TablaTransporte[#Data],2,FALSE),0) -> 840000 | E81: =B81*C81*D81 -> 1680000
D82: =IFERROR(VLOOKUP(A82,[1]!TablaTransporte[#Data],2,FALSE),0) -> 0
D83: =IFERROR(VLOOKUP(A83,[1]!TablaTransporte[#Data],2,FALSE),0) -> 0
F84: =SUM(E72:E83) -> 12030000
F85: =F30+F60+F70+F84 -> 37545692
F86: =F85*A86 -> 0
F87: =F85+F86 -> 37545692
F88: =F87*A88 -> 0
F89: =F87+F88 -> 37545692
F90: =F89/F3 -> 421861.7

Sheet suministro e instalación 
A1: SUMINISTRO E INSTALACIÓN DE PAVIMENTO FLEXIBLE
A2: EQUIPOS | B2: CANT | C2: REND/DIA | D2: TARIFA/DIA | E2: VR.PARCIAL | F2: M3
F3: 32
A4: Pala | B4: 6 | C4: 3 | D4: =IFERROR(VLOOKUP(A4,[1]!TablaEquipos[#Data],2,FALSE),0) -> 700 | E4: =B4*C4*D4 -> 12600
A5: Carretilla | B5: 6 | C5: 3 | D5: =IFERROR(VLOOKUP(A5,[1]!TablaEquipos[#Data],2,FALSE),0) -> 1500 | E5: =B5*C5*D5 -> 27000
A6: Rodillo tipo Benitín | B6: 1 | C6: 3 | D6: =IFERROR(VLOOKUP(A6,[1]!TablaEquipos[#Data],2,FALSE),0) -> 100000 | E6: =B6*C6*D6 -> 300000
A7: Vibrocompactador tipo rana | B7: 1 | C7: 3 | D7: =IFERROR(VLOOKUP(A7,[1]!TablaEquipos[#Data],2,FALSE),0) -> 40000 | E7: =B7*C7*D7 -> 120000
A8: Paletas | B8: 2 | C8: 3 | D8: =IFERROR(VLOOKUP(A8,[1]!TablaEquipos[#Data],2,FALSE),0) -> 500 | E8: =B8*C8*D8 -> 3000
A9: Chaleco reflectivo | B9: 2 | C9: 3 | D9: =IFERROR(VLOOKUP(A9,[1]!TablaEquipos[#Data],2,FALSE),0) -> 625 | E9: =B9*C9*D9 -> 3750
A10: Avisos de seguridad | B10: 30 | C10: 3 | D10: =IFERROR(VLOOKUP(A10,[1]!TablaEquipos[#Data],2,FALSE),0) -> 1000 | E10: =B10*C10*D10 -> 90000
A11: Pala Madera | B11: 6 | C11: 3 | D11: =IFERROR(VLOOKUP(A11,[1]!TablaEquipos[#Data],2,FALSE),0) -> 15000 | E11: =B11*C11*D11 -> 270000
A12: Baldes Asfalto | B12: 12 | C12: 3 | D12: =IFERROR(VLOOKUP(A12,[1]!TablaEquipos[#Data],2,FALSE),0) -> 12000 | E12: =B12*C12*D12 -> 432000
A13: Escoba de varita | B13: 6 | C13: 3 | D13: =IFERROR(VLOOKUP(A13,[1]!TablaEquipos[#Data],2,FALSE),0) -> 20000 | E13: =B13*C13*D13 -> 360000
A14: Radio Comunicación | B14: 1 | C14: 3 | D14: =IFERROR(VLOOKUP(A14,[1]!TablaEquipos[#Data],2,FALSE),0) -> 8000 | E14: =B14*C14*D14 -> 24000
F20: =SUM(E4:E19) -> 1642350
A21: MATERIALES | B21: CANT | C21: REND/DIA | D21: TARIFA | E21: VR.PARCIAL
A22: Cinta de seguridad amarilla/negra x 500 | B22: 2 | D22: =IFERROR(VLOOKUP(A22,[1]!TablaMateriales[#Data],2,FALSE),0) -> 55000 | E22: =B22*D22 -> 110000
A23: Plástico negro | B23: 50 | D23: =IFERROR(VLOOKUP(A23,[1]!TablaMateriales[#Data],2,FALSE),0) -> 9500 | E23: =B23*D23 -> 475000
A24: Mezcla asfáltica compactada toneladas m3 | B24: 32 | D24: =IFERROR(VLOOKUP(A24,[1]!TablaMateriales[#Data],2,FALSE),0) -> 650000 | E24: 28000000
A25: Subbase granular m3 | B25: 32 | D25: =IFERROR(VLOOKUP(A25,[1]!TablaMateriales[#Data],2,FALSE),0) -> 59000 | E25: =B25*D25 -> 1888000
A26: Emulsión asfáltica para imprimación galon | B26: 70 | D26: =IFERROR(VLOOKUP(A26,[1]!TablaMateriales[#Data],2,FALSE),0) -> 30000 | E26: =B26*D26 -> 2100000
A27: Emulsión para riego de liga galon | B27: 20 | D27: =IFERROR(VLOOKUP(A27,[1]!TablaMateriales[#Data],2,FALSE),0) -> 25000 | E27: =B27*D27 -> 500000
A28: Base Granular m3 | B28: 32 | D28: =IFERROR(VLOOKUP(A28,[1]!TablaMateriales[#Data],2,FALSE),0) -> 76500 | E28: =B28*D28 -> 2448000
D29: =IFERROR(VLOOKUP(A29,[1]!TablaMateriales[#Data],2,FALSE),0) -> 0
D30: =IFERROR(VLOOKUP(A30,[1]!TablaMateriales[#Data],2,FALSE),0) -> 0
D31: =IFERROR(VLOOKUP(A31,[1]!TablaMateriales[#Data],2,FALSE),0) -> 0
F32: =SUM(E22:E31) -> 35521000
A33: MANO DE OBRA | B33: CANT | C33: REND/DIA | D33: SALARIO | E33: VR.PARCIAL
A34: Capataz | B34: 1 | C34: 19 | D34: 539456.24 | E34: =B34*C34*D34 -> 10249669
A35: Hse | B35: 1 | C35: 19 | D35: 539456.24 | E35: =B35*C35*D35 -> 10249669
A36: Oficial construccion | B36: 2 | C36: 19 | D36: 399154.66 | E36: =B36*C36*D36 -> 15167877
A37: Auxiliar Administrativo | B37: 1 | C37: 19 | D37: 383405.21 | E37: =B37*C37*D37 -> 7284699
A38: Auxiliar Civil Asfaltero | B38: 8 | C38: 19 | D38: ='tabla salarial'!AS9 -> 382109.06 | E38: =B38*C38*D38 -> 58080577
A39: Auxiliar Civil | B39: 8 | D39: ='tabla salarial'!AS9 -> 382109.06 | E39: =B39*C39*D39 -> 0
F40: =SUM(E34:E39) -> 1.0103249e+08
A41: TRANSPORTE | B41: CANT | C41: REND/DIA | D41: TARIFA | E41: VR.PARCIAL
A42: Camión doble cabina | B42: 1 | C42: 7 | D42: =IFERROR(VLOOKUP(A42,[1]!TablaTransporte[#Data],2,FALSE),0) -> 550000 | E42: =B42*C42*D42 -> 3850000
A43: Volqueta de 14 m³ | B43: 1 | C43: 4 | D43: =IFERROR(VLOOKUP(A43,[1]!TablaTransporte[#Data],2,FALSE),0) -> 1350000 | E43: =B43*C43*D43 -> 5400000
A44: Vibro compactador grande | B44: 1 | C44: 10 | D44: =IFERROR(VLOOKUP(A44,[1]!TablaTransporte[#Data],2,FALSE),0) -> 1330000 | E44: =B44*C44*D44 -> 13300000
A45: mini cargador | B45: 1 | C45: 8 | D45: =IFERROR(VLOOKUP(A45,[1]!TablaTransporte[#Data],2,FALSE),0) -> 840000 | E45: =B45*C45*D45 -> 6720000
A46: Transporte de equipo | B46: 1 | C46: 7 | D46: =IFERROR(VLOOKUP(A46,[1]!TablaTransporte[#Data],2,FALSE),0) -> 0 | E46: =B46*C46*D46 -> 0
A47: Pavimentadora | B47: 1 | C47: 4 | D47: =IFERROR(VLOOKUP(A47,[1]!TablaTransporte[#Data],2,FALSE),0) -> 4000000 | E47: =B47*C47*D47 -> 16000000
A48: Buseta Acpm | B48: 1 | C48: 8 | D48: =IFERROR(VLOOKUP(A48,[1]!TablaTransporte[#Data],2,FALSE),0) -> 600000 | E48: =B48*C48*D48 -> 4800000
A49: Camion Sisterna | B49: 1 | C49: 8 | D49: =IFERROR(VLOOKUP(A49,[1]!TablaTransporte[#Data],2,FALSE),0) -> 1500000 | E49: =B49*C49*D49 -> 12000000
D50: =IFERROR(VLOOKUP(A50,[1]!TablaTransporte[#Data],2,FALSE),0) -> 0
F51: =SUM(E42:E50) -> 62070000
F52: =F20+F32+F40+F51 -> 2.0026584e+08
F53: =F52*A53 -> 0
F54: =F52+F53 -> 2.0026584e+08
F55: =F54*A55 -> 0
F56: =F54+F55 -> 2.0026584e+08
F57: =F56/F3 -> 6258307.5

Sheet suministro e inst. en gravilla 
A1: SUMINISTRO E INSTALACIÓN DE GRAVILLA EN ÁREA INDUSTRIAL
A2: EQUIPOS | B2: CANT | C2: REND/DIA | D2: TARIFA/DIA | E2: VR.PARCIAL | F2: M3
F3: 21
A4: Pala | B4: 8 | C4: 2 | D4: =IFERROR(VLOOKUP(A4,[1]!TablaEquipos[#Data],2,FALSE),0) -> 700 | E4: =B4*C4*D4 -> 11200
A5: Pica | B5: 0 | D5: =IFERROR(VLOOKUP(A5,[1]!TablaEquipos[#Data],2,FALSE),0) -> 700 | E5: =B5*C5*D5 -> 0
A6: Palín | B6: 8 | C6: 2 | D6: =IFERROR(VLOOKUP(A6,[1]!TablaEquipos[#Data],2,FALSE),0) -> 700 | E6: =B6*C6*D6 -> 11200
A7: Barra | B7: 1 | D7: =IFERROR(VLOOKUP(A7,[1]!TablaEquipos[#Data],2,FALSE),0) -> 1500 | E7: =B7*C7*D7 -> 0
A8: Herramientero | B8: 1 | C8: 2 | D8: =IFERROR(VLOOKUP(A8,[1]!TablaEquipos[#Data],2,FALSE),0) -> 1500 | E8: =B8*C8*D8 -> 3000
A9: Carretilla | B9: 6 | C9: 2 | D9: =IFERROR(VLOOKUP(A9,[1]!TablaEquipos[#Data],2,FALSE),0) -> 1500 | E9: =B9*C9*D9 -> 18000
A10: Colombina | B10: 12 | C10: 2 | D10: =IFERROR(VLOOKUP(A10,[1]!TablaEquipos[#Data],2,FALSE),0) -> 1000 | E10: =B10*C10*D10 -> 24000
A11: Avisos de seguridad | B11: 10 | C11: 2 | D11: =IFERROR(VLOOKUP(A11,[1]!TablaEquipos[#Data],2,FALSE),0) -> 1000 | E11: =B11*C11*D11 -> 20000
A12: Rodillo tipo Benitín | B12: 1 | C12: 2 | D12: =IFERROR(VLOOKUP(A12,[1]!TablaEquipos[#Data],2,FALSE),0) -> 100000 | E12: =B12*C12*D12 -> 200000
A13: Vibrocompactador tipo rana | B13: 1 | C13: 2 | D13: =IFERROR(VLOOKUP(A13,[1]!TablaEquipos[#Data],2,FALSE),0) -> 40000 | E13: =B13*C13*D13 -> 80000
F21: =SUM(E4:E20) -> 367400
A22: MATERIALES | B22: CANT | C22: REND/DIA | D22: TARIFA | E22: VR.PARCIAL
A23: Cinta de seguridad amarilla/negra x 500 | B23: 1 | D23: =IFERROR(VLOOKUP(A23,[1]!TablaMateriales[#Data],2,FALSE),0) -> 55000 | E23: =B23*D23 -> 55000
A24: Plástico negro | B24: 10 | D24: =IFERROR(VLOOKUP(A24,[1]!TablaMateriales[#Data],2,FALSE),0) -> 9500 | E24: =B24*D24 -> 95000
A25: Acpm Galon | B25: 5 | D25: =IFERROR(VLOOKUP(A25,[1]!TablaMateriales[#Data],2,FALSE),0) -> 11500 | E25: =B25*D25 -> 57500
A26: Material selecionado | D26: =IFERROR(VLOOKUP(A26,[1]!TablaMateriales[#Data],2,FALSE),0) -> 0 | E26: =B26*D26 -> 0
A27: Material de afirmado | D27: =IFERROR(VLOOKUP(A27,[1]!TablaMateriales[#Data],2,FALSE),0) -> 0 | E27: =B27*D27 -> 0
A28: Material tipo base | D28: =IFERROR(VLOOKUP(A28,[1]!TablaMateriales[#Data],2,FALSE),0) -> 0 | E28: =B28*D28 -> 0
A29: Alfalto en caliente | D29: =IFERROR(VLOOKUP(A29,[1]!TablaMateriales[#Data],2,FALSE),0) -> 0 | E29: =B29*D29 -> 0
A30: Gravilla triturada Clasificada TM 3/4 | B30: 23 | D30: =IFERROR(VLOOKUP(A30,[1]!TablaMateriales[#Data],2,FALSE),0) -> 64000 | E30: =B30*D30 -> 1472000
D31: =IFERROR(VLOOKUP(A31,[1]!TablaMateriales[#Data],2,FALSE),0) -> 0
D32: =IFERROR(VLOOKUP(A32,[1]!TablaMateriales[#Data],2,FALSE),0) -> 0
D33: =IFERROR(VLOOKUP(A33,[1]!TablaMateriales[#Data],2,FALSE),0) -> 0
D34: =IFERROR(VLOOKUP(A34,[1]!TablaMateriales[#Data],2,FALSE),0) -> 0
D35: =IFERROR(VLOOKUP(A35,[1]!TablaMateriales[#Data],2,FALSE),0) -> 0
D36: =IFERROR(VLOOKUP(A36,[1]!TablaMateriales[#Data],2,FALSE),0) -> 0
F37: =SUM(E23:E36) -> 1679500
A38: MANO DE OBRA | B38: CANT | C38: REND/DIA | D38: SALARIO | E38: VR.PARCIAL
A39: Capataz | B39: 1 | C39: 2.5 | D39: 471540.27 | E39: =B39*C39*D39 -> 1178850.7
A40: Hse | B40: 1 | C40: 2.5 | D40: 471540.27 | E40: =B40*C40*D40 -> 1178850.7
A41: Topografo | B41: 1 | D41: 471540.27 | E41: =B41*C41*D41 -> 0
A42: Cadenero 1 | B42: 1.5 | D42: 399154.66 | E42: =B42*C42*D42 -> 0
A43: Andamiero | B43: 2 | D43: 399154.66 | E43: =B43*C43*D43 -> 0
A44: Oficial construccion | B44: 2 | C44: 2.5 | D44: 383405.21 | E44: =B44*C44*D44 -> 1917026
A45: Auxiliar Administrativo | B45: 1 | C45: 2.5 | D45: 355463.25 | E45: =B45*C45*D45 -> 888658.12
A46: Auxiliar civil | B46: 8 | C46: 2.5 | D46: 355463.25 | E46: =B46*C46*D46 -> 7109265
F47: =SUM(E39:E46) -> 12272650
A48: TRANSPORTE | B48: CANT | C48: REND/DIA | D48: TARIFA | E48: VR.PARCIAL
A49: Camión doble cabina | B49: 1 | C49: 2 | D49: =IFERROR(VLOOKUP(A49,[1]!TablaTransporte[#Data],2,FALSE),0) -> 550000 | E49: =B49*C49*D49 -> 1100000
A50: Volqueta de 14 m³ | B50: 1 | C50: 0.5 | D50: =IFERROR(VLOOKUP(A50,[1]!TablaTransporte[#Data],2,FALSE),0) -> 1350000 | E50: =C50*D50 -> 675000
A51: mini cargador | B51: 1 | C51: 0.5 | D51: =IFERROR(VLOOKUP(A51,[1]!TablaTransporte[#Data],2,FALSE),0) -> 840000 | E51: =B51*C51*D51 -> 420000
A52: Buseta Acpm | B52: 1 | C52: 1 | D52: =IFERROR(VLOOKUP(A52,[1]!TablaTransporte[#Data],2,FALSE),0) -> 600000 | E52: =B52*C52*D52 -> 600000
D53: =IFERROR(VLOOKUP(A53,[1]!TablaTransporte[#Data],2,FALSE),0) -> 0
D54: =IFERROR(VLOOKUP(A54,[1]!TablaTransporte[#Data],2,FALSE),0) -> 0
D55: =IFERROR(VLOOKUP(A55,[1]!TablaTransporte[#Data],2,FALSE),0) -> 0
D56: =IFERROR(VLOOKUP(A56,[1]!TablaTransporte[#Data],2,FALSE),0) -> 0
F58: =SUM(E49:E56) -> 2795000
F59: =F21+F37+F47+F58 -> 17114550
F60: =F59*A59 -> 0
F61: =F59+F60 -> 17114550
F62: =F61*A61 -> 0
F63: =F61+F62 -> 17114550
F64: =F63/F3 -> 814978.6

Sheet suministro e inst. de adoquin 
A1: SUMINISTRO E INSTALACIÓN DE ADOQUIN EN ÁREA INDUSTRIAL
A2: EQUIPOS | B2: CANT | C2: REND/DIA | D2: TARIFA/DIA | E2: VR.PARCIAL | F2: M2
F3: 6
A4: Pala | B4: 4 | C4: 2 | D4: =IFERROR(VLOOKUP(A4,[1]!TablaEquipos[#Data],2,FALSE),0) -> 700 | E4: =B4*C4*D4 -> 5600
A5: Pica | B5: 2 | D5: =IFERROR(VLOOKUP(A5,[1]!TablaEquipos[#Data],2,FALSE),0) -> 700 | E5: =B5*C5*D5 -> 0
A6: Palín | B6: 4 | C6: 2 | D6: =IFERROR(VLOOKUP(A6,[1]!TablaEquipos[#Data],2,FALSE),0) -> 700 | E6: =B6*C6*D6 -> 5600
A7: Paladraga | D7: =IFERROR(VLOOKUP(A7,[1]!TablaEquipos[#Data],2,FALSE),0) -> 1500 | E7: =B7*C7*D7 -> 0
A8: Barra | B8: 1 | D8: =IFERROR(VLOOKUP(A8,[1]!TablaEquipos[#Data],2,FALSE),0) -> 1500 | E8: =B8*C8*D8 -> 0
A9: Herramientero | B9: 1 | C9: 2 | D9: =IFERROR(VLOOKUP(A9,[1]!TablaEquipos[#Data],2,FALSE),0) -> 1500 | E9: =B9*C9*D9 -> 3000
A10: Sierra circular | D10: =IFERROR(VLOOKUP(A10,[1]!TablaEquipos[#Data],2,FALSE),0) -> 15000 | E10: =B10*C10*D10 -> 0
A11: Carretilla | B11: 4 | C11: 2 | D11: =IFERROR(VLOOKUP(A11,[1]!TablaEquipos[#Data],2,FALSE),0) -> 1500 | E11: =B11*C11*D11 -> 12000
A12: Rodillo tipo Benitín | B12: 1 | C12: 1 | D12: =IFERROR(VLOOKUP(A12,[1]!TablaEquipos[#Data],2,FALSE),0) -> 100000 | E12: =B12*C12*D12 -> 100000
A13: Vibrocompactador tipo rana | B13: 1 | D13: =IFERROR(VLOOKUP(A13,[1]!TablaEquipos[#Data],2,FALSE),0) -> 40000 | E13: =B13*C13*D13 -> 0
A14: Vibrocompactador tipo canguro | B14: 1 | D14: =IFERROR(VLOOKUP(A14,[1]!TablaEquipos[#Data],2,FALSE),0) -> 60000 | E14: =B14*C14*D14 -> 0
A15: Paletas | D15: =IFERROR(VLOOKUP(A15,[1]!TablaEquipos[#Data],2,FALSE),0) -> 500 | E15: =B15*C15*D15 -> 0
A16: Chaleco reflectivo | D16: =IFERROR(VLOOKUP(A16,[1]!TablaEquipos[#Data],2,FALSE),0) -> 625 | E16: =B16*C16*D16 -> 0
A17: Colombina | B17: 12 | C17: 2 | D17: =IFERROR(VLOOKUP(A17,[1]!TablaEquipos[#Data],2,FALSE),0) -> 1000 | E17: =B17*C17*D17 -> 24000
A18: Avisos de seguridad | B18: 10 | C18: 2 | D18: =IFERROR(VLOOKUP(A18,[1]!TablaEquipos[#Data],2,FALSE),0) -> 1000 | E18: =B18*C18*D18 -> 20000
F28: =SUM(E4:E27) -> 170200
A29: MATERIALES | B29: CANT | C29: REND/DIA | D29: TARIFA | E29: VR.PARCIAL
A30: Cinta de seguridad amarilla/negra x 500 | B30: 1 | D30: =IFERROR(VLOOKUP(A30,[1]!TablaMateriales[#Data],2,FALSE),0) -> 55000 | E30: =B30*D30 -> 55000
A31: Plástico negro | B31: 10 | D31: =IFERROR(VLOOKUP(A31,[1]!TablaMateriales[#Data],2,FALSE),0) -> 9500 | E31: =B31*D31 -> 95000
A32: Acpm Galon | B32: 5 | D32: =IFERROR(VLOOKUP(A32,[1]!TablaMateriales[#Data],2,FALSE),0) -> 11500 | E32: =B32*D32 -> 57500
A33: Adoquín tipo corbatin | B33: 300 | D33: =IFERROR(VLOOKUP(A33,[1]!TablaMateriales[#Data],2,FALSE),0) -> 2200 | E33: =B33*D33 -> 660000
A34: Arena para cama/capa de soporte | B34: 5 | D34: =IFERROR(VLOOKUP(A34,[1]!TablaMateriales[#Data],2,FALSE),0) -> 31000 | E34: =B34*D34 -> 155000
A35: Arena fina seca para sello de juntas | B35: 5 | D35: =IFERROR(VLOOKUP(A35,[1]!TablaMateriales[#Data],2,FALSE),0) -> 21000 | E35: =B35*D35 -> 105000
D36: =IFERROR(VLOOKUP(A36,[1]!TablaMateriales[#Data],2,FALSE),0) -> 0
F37: =SUM(E30:E36) -> 1127500
A38: MANO DE OBRA | B38: CANT | C38: REND/DIA | D38: SALARIO | E38: VR.PARCIAL
A39: Capataz | B39: 1 | C39: 3.16 | D39: 434781.14 | E39: =B39*C39*D39 -> 1373908.4
A40: Hse | B40: 1 | C40: 3.16 | D40: 434781.14 | E40: =B40*C40*D40 -> 1373908.4
A41: Topografo | B41: 1 | D41: 434781.14 | E41: =B41*C41*D41 -> 0
A42: Cadenero 1 | B42: 1.5 | D42: 383405.21 | E42: =B42*C42*D42 -> 0
A43: Andamiero | B43: 2 | D43: 383405.21 | E43: =B43*C43*D43 -> 0
A44: Oficial construccion | B44: 2 | C44: 3.16 | D44: 355463.25 | E44: =B44*C44*D44 -> 2246527.7
A45: Auxiliar Administrativo | B45: 1 | C45: 3.16 | D45: 383405.21 | E45: =B45*C45*D45 -> 1211560.5
A46: Auxiliar civil | B46: 8 | C46: 3.16 | D46: 355463.25 | E46: =B46*C46*D46 -> 8986110.9
F47: =SUM(E39:E46) -> 15192016
A48: TRANSPORTE | B48: CANT | C48: REND/DIA | D48: TARIFA | E48: VR.PARCIAL
A49: Camión doble cabina | B49: 1 | C49: 2 | D49: =IFERROR(VLOOKUP(A49,[1]!TablaTransporte[#Data],2,FALSE),0) -> 550000 | E49: =B49*C49*D49 -> 1100000
A50: Acarreo por km | B50: 1 | D50: =IFERROR(VLOOKUP(A50,[1]!TablaTransporte[#Data],2,FALSE),0) -> 65000 | E50: =B50*C50*D50 -> 0
A51: Retroexcavadora de oruga | B51: 1 | D51: =IFERROR(VLOOKUP(A51,[1]!TablaTransporte[#Data],2,FALSE),0) -> 322000 | E51: =B51*C51*D51 -> 0
A52: Retroexcavadora con llantas | B52: 1 | D52: =IFERROR(VLOOKUP(A52,[1]!TablaTransporte[#Data],2,FALSE),0) -> 190000 | E52: =C52*D52 -> 0
A53: Volqueta de 14 m³ | B53: 1 | C53: 0.05 | D53: =IFERROR(VLOOKUP(A53,[1]!TablaTransporte[#Data],2,FALSE),0) -> 1350000 | E53: =C53*D53 -> 67500
A54: Vibro compactador grande | D54: =IFERROR(VLOOKUP(A54,[1]!TablaTransporte[#Data],2,FALSE),0) -> 1330000 | E54: =C54*D54 -> 0
A55: mini cargador | B55: 1 | D55: =IFERROR(VLOOKUP(A55,[1]!TablaTransporte[#Data],2,FALSE),0) -> 840000 | E55: =B55*C55*D55 -> 0
A56: Buseta Acpm | B56: 1 | C56: 2 | D56: =IFERROR(VLOOKUP(A56,[1]!TablaTransporte[#Data],2,FALSE),0) -> 600000 | E56: =B56*C56*D56 -> 1200000
D57: =IFERROR(VLOOKUP(A57,[1]!TablaTransporte[#Data],2,FALSE),0) -> 0
D58: =IFERROR(VLOOKUP(A58,[1]!TablaTransporte[#Data],2,FALSE),0) -> 0
D59: =IFERROR(VLOOKUP(A59,[1]!TablaTransporte[#Data],2,FALSE),0) -> 0
D60: =IFERROR(VLOOKUP(A60,[1]!TablaTransporte[#Data],2,FALSE),0) -> 0
F61: =SUM(E49:E60) -> 2367500
F62: =F28+F37+F47+F61 -> 18857216
F63: =F62*A63 -> 0
F64: =F62+F63 -> 18857216
F65: =F64*A65 -> 0
F66: =F64+F65 -> 18857216
F67: =F66/F3 -> 3142869.3

Sheet suministro e inst. ladrillo 
A1: SUMINISTRO E INSTALACIÓN LADRILLO TOLETE PARA VÍAS EN ÁREA INDUSTRIAL
A2: EQUIPOS | B2: CANT | C2: REND/DIA | D2: TARIFA/DIA | E2: VR.PARCIAL | F2: M2
F3: 6
A4: Machete | B4: 1 | D4: 0 | E4: =B4*C4*D4 -> 0
A5: Lima triangular | B5: 1 | D5: 0 | E5: =B5*C5*D5 -> 0
A6: Martillo | B6: 1 | D6: 0 | E6: =B6*C6*D6 -> 0
A7: Pala | B7: 2 | C7: 2 | D7: 0 | E7: =B7*C7*D7 -> 0
A8: Pica | B8: 8 | D8: 0 | E8: =B8*C8*D8 -> 0
A9: Palín | B9: 8 | C9: 2 | D9: 0 | E9: =B9*C9*D9 -> 0
A10: Paladraga | B10: 4 | D10: 0 | E10: =B10*C10*D10 -> 0
A11: Barra | B11: 1 | D11: 0 | E11: =B11*C11*D11 -> 0
A12: Herramientero | B12: 1 | C12: 2 | D12: 0 | E12: =B12*C12*D12 -> 0
A13: Sierra circular | B13: 1 | D13: 0 | E13: =B13*C13*D13 -> 0
A14: Alicate diablo | D14: 0 | E14: =B14*C14*D14 -> 0
A15: Alicate universal | D15: 0 | E15: =B15*C15*D15 -> 0
A16: Andamios Layher | D16: 0 | E16: =B16*C16*D16 -> 0
A17: Arnés de seguridad | D17: 0 | E17: =B17*C17*D17 -> 0
A18: Línea de vida | D18: 0 | E18: =B18*C18*D18 -> 0
A19: Nivel torpedo | D19: 0 | E19: =B19*C19*D19 -> 0
A20: Carretilla | B20: 6 | C20: 2 | D20: 0 | E20: =B20*C20*D20 -> 0
A21: Martillo demoledor neumático/eléctrico | D21: 0 | E21: =B21*C21*D21 -> 0
A22: Rodillo tipo Benitín | B22: 1 | C22: 1 | D22: 0 | E22: =B22*C22*D22 -> 0
A23: Vibrocompactador tipo rana | B23: 1 | D23: 0 | E23: =B23*C23*D23 -> 0
A24: Vibrocompactador tipo canguro | B24: 1 | D24: 0 | E24: =B24*C24*D24 -> 0
A25: Paletas | B25: 2 | D25: 0 | E25: =B25*C25*D25 -> 0
A26: Chaleco reflectivo | B26: 2 | D26: 0 | E26: =B26*C26*D26 -> 0
A27: Colombiana | B27: 12 | C27: 2 | D27: 0 | E27: =B27*C27*D27 -> 0
A28: Avisos de seguridad | B28: 10 | C28: 2 | D28: 3000 | E28: =B28*C28*D28 -> 60000
A29: Carpa plastica 6x6
A30: Carpa plastica 4x4
A31: Carpa plastica 6x4
F38: =SUM(E4:E37) -> 60000
A39: MATERIALES | B39: CANT | C39: REND/DIA | D39: TARIFA | E39: VR.PARCIAL
A40: Listón de madera 2 x 4 x 3 | D40: =IFERROR(VLOOKUP(A40,[1]!TablaMateriales[#Data],2,FALSE),0) -> 35000 | E40: =B40*D40 -> 0
A41: Listón de madera 2 x 1 x 3 | D41: =IFERROR(VLOOKUP(A41,[1]!TablaMateriales[#Data],2,FALSE),0) -> 20000 | E41: =B41*D41 -> 0
A42: Cal | D42: =IFERROR(VLOOKUP(A42,[1]!TablaMateriales[#Data],2,FALSE),0) -> 50000 | E42: =B42*D42 -> 0
A43: Nailon de color | D43: =IFERROR(VLOOKUP(A43,[1]!TablaMateriales[#Data],2,FALSE),0) -> 0 | E43: =B43*D43 -> 0
A44: Puntilla de 2,5" | D44: =IFERROR(VLOOKUP(A44,[1]!TablaMateriales[#Data],2,FALSE),0) -> 9500 | E44: =B44*D44 -> 0
A45: Puntilla de 3,5" | D45: =IFERROR(VLOOKUP(A45,[1]!TablaMateriales[#Data],2,FALSE),0) -> 9500 | E45: =B45*D45 -> 0
A46: Clavo de acero de 3" | D46: =IFERROR(VLOOKUP(A46,[1]!TablaMateriales[#Data],2,FALSE),0) -> 15000 | E46: =B46*D46 -> 0
A47: Pintura en aerosol | D47: =IFERROR(VLOOKUP(A47,[1]!TablaMateriales[#Data],2,FALSE),0) -> 20000 | E47: =B47*D47 -> 0
A48: Cinta de seguridad amarilla/negra x 500 | B48: 1 | D48: =IFERROR(VLOOKUP(A48,[1]!TablaMateriales[#Data],2,FALSE),0) -> 55000 | E48: =B48*D48 -> 55000
A49: Grapa | D49: =IFERROR(VLOOKUP(A49,[1]!TablaMateriales[#Data],2,FALSE),0) -> 15900 | E49: =B49*D49 -> 0
A50: Alambre HG calibre 14 | D50: =IFERROR(VLOOKUP(A50,[1]!TablaMateriales[#Data],2,FALSE),0) -> 14000 | E50: =B50*D50 -> 0
A51: Tela verde de 2 metros | D51: =IFERROR(VLOOKUP(A51,[1]!TablaMateriales[#Data],2,FALSE),0) -> 3800 | E51: =B51*D51 -> 0
A52: Broca tipo pala | D52: =IFERROR(VLOOKUP(A52,[1]!TablaMateriales[#Data],2,FALSE),0) -> 65000 | E52: =B52*D52 -> 0
A53: Broca tipo punta | D53: =IFERROR(VLOOKUP(A53,[1]!TablaMateriales[#Data],2,FALSE),0) -> 65000 | E53: =B53*D53 -> 0
A54: Aceite lubricante | D54: =IFERROR(VLOOKUP(A54,[1]!TablaMateriales[#Data],2,FALSE),0) -> 65000 | E54: =B54*D54 -> 0
A55: Plástico negro | B55: 10 | D55: =IFERROR(VLOOKUP(A55,[1]!TablaMateriales[#Data],2,FALSE),0) -> 9500 | E55: =B55*D55 -> 95000
A56: Acpm | D56: =IFERROR(VLOOKUP(A56,[1]!TablaMateriales[#Data],2,FALSE),0) -> 0 | E56: =B56*D56 -> 0
A57: Material selecionado | D57: =IFERROR(VLOOKUP(A57,[1]!TablaMateriales[#Data],2,FALSE),0) -> 0 | E57: =B57*D57 -> 0
A58: Material de afirmado | D58: =IFERROR(VLOOKUP(A58,[1]!TablaMateriales[#Data],2,FALSE),0) -> 0 | E58: =B58*D58 -> 0
A59: Material tipo base | D59: =IFERROR(VLOOKUP(A59,[1]!TablaMateriales[#Data],2,FALSE),0) -> 0 | E59: =B59*D59 -> 0
A60: Alfalto en caliente | D60: =IFERROR(VLOOKUP(A60,[1]!TablaMateriales[#Data],2,FALSE),0) -> 0 | E60: =B60*D60 -> 0
A61: Triturado 3/4-1" | D61: =IFERROR(VLOOKUP(A61,[1]!TablaMateriales[#Data],2,FALSE),0) -> 0 | E61: =B61*D61 -> 0
A62: Arena | D62: =IFERROR(VLOOKUP(A62,[1]!TablaMateriales[#Data],2,FALSE),0) -> 0
A63: Adoquin | B63: 300 | D63: =IFERROR(VLOOKUP(A63,[1]!TablaMateriales[#Data],2,FALSE),0) -> 0 | E63: =B63*D63 -> 0
A64: Adoquin tolete | B64: 336 | D64: =IFERROR(VLOOKUP(A64,[1]!TablaMateriales[#Data],2,FALSE),0) -> 1800 | E64: =B64*D64 -> 604800
A65: Arena | B65: 4 | D65: =IFERROR(VLOOKUP(A65,[1]!TablaMateriales[#Data],2,FALSE),0) -> 0 | E65: =B65*D65 -> 0
A66: Cemento x 50 kilos | B66: 4 | D66: =IFERROR(VLOOKUP(A66,[1]!TablaMateriales[#Data],2,FALSE),0) -> 0 | E66: =B66*D66 -> 0
A67: Sikasel x kilo | B67: 2.6 | D67: =IFERROR(VLOOKUP(A67,[1]!TablaMateriales[#Data],2,FALSE),0) -> 0 | E67: =B67*D67 -> 0
D68: =IFERROR(VLOOKUP(A68,[1]!TablaMateriales[#Data],2,FALSE),0) -> 0
D69: =IFERROR(VLOOKUP(A69,[1]!TablaMateriales[#Data],2,FALSE),0) -> 0
D70: =IFERROR(VLOOKUP(A70,[1]!TablaMateriales[#Data],2,FALSE),0) -> 0
D71: =IFERROR(VLOOKUP(A71,[1]!TablaMateriales[#Data],2,FALSE),0) -> 0
D72: =IFERROR(VLOOKUP(A72,[1]!TablaMateriales[#Data],2,FALSE),0) -> 0
D73: =IFERROR(VLOOKUP(A73,[1]!TablaMateriales[#Data],2,FALSE),0) -> 0
D74: =IFERROR(VLOOKUP(A74,[1]!TablaMateriales[#Data],2,FALSE),0) -> 0
F75: =SUM(E40:E74) -> 754800
A76: MANO DE OBRA | B76: CANT | C76: REND/DIA | D76: SALARIO | E76: VR.PARCIAL
A77: Capataz | B77: 1 | C77: 1 | D77: 434781.14 | E77: =B77*C77*D77 -> 434781.14
A78: Hse | B78: 1 | C78: 1 | D78: 434781.14 | E78: =B78*C78*D78 -> 434781.14
A79: Topografo | B79: 1 | D79: 434781.14 | E79: =B79*C79*D79 -> 0
A80: Cadenero 1 | B80: 1.5 | D80: 383405.21 | E80: =B80*C80*D80 -> 0
A81: Andamiero | B81: 2 | D81: 383405.21 | E81: =B81*C81*D81 -> 0
A82: Oficial construccion | B82: 1 | C82: 1.5 | D82: 355463.25 | E82: =B82*C82*D82 -> 533194.87
A83: Auxiliar Administrativo | B83: 1 | C83: 2.5 | D83: 383405.21 | E83: =B83*C83*D83 -> 958513.02
A84: Auxiliar civil | B84: 2 | C84: 2.5 | D84: 355463.25 | E84: =B84*C84*D84 -> 1777316.2
F85: =SUM(E77:E84) -> 4138586.4
A86: TRANSPORTE | B86: CANT | C86: REND/DIA | D86: TARIFA | E86: VR.PARCIAL
A87: Camión doble cabina | B87: 1 | C87: 0.5 | D87: =IFERROR(VLOOKUP(A87,[1]!TablaTransporte[#Data],2,FALSE),0) -> 550000 | E87: =B87*C87*D87 -> 275000
A88: Acarreo por km | B88: 1 | D88: =IFERROR(VLOOKUP(A88,[1]!TablaTransporte[#Data],2,FALSE),0) -> 65000 | E88: =B88*C88*D88 -> 0
A89: Retroexcavadora de oruga | B89: 1 | D89: =IFERROR(VLOOKUP(A89,[1]!TablaTransporte[#Data],2,FALSE),0) -> 322000 | E89: =B89*C89*D89 -> 0
A90: Retroexcavadora con llantas | B90: 1 | D90: =IFERROR(VLOOKUP(A90,[1]!TablaTransporte[#Data],2,FALSE),0) -> 190000 | E90: =C90*D90 -> 0
A91: Volqueta de 14 m³ | B91: 1 | D91: =IFERROR(VLOOKUP(A91,[1]!TablaTransporte[#Data],2,FALSE),0) -> 1350000 | E91: =C91*D91 -> 0
A92: Vibro compactador grande | D92: =IFERROR(VLOOKUP(A92,[1]!TablaTransporte[#Data],2,FALSE),0) -> 1330000 | E92: =C92*D92 -> 0
A93: mini cargador | B93: 1 | D93: =IFERROR(VLOOKUP(A93,[1]!TablaTransporte[#Data],2,FALSE),0) -> 840000 | E93: =B93*C93*D93 -> 0
D94: =IFERROR(VLOOKUP(A94,[1]!TablaTransporte[#Data],2,FALSE),0) -> 0
D95: =IFERROR(VLOOKUP(A95,[1]!TablaTransporte[#Data],2,FALSE),0) -> 0
D96: =IFERROR(VLOOKUP(A96,[1]!TablaTransporte[#Data],2,FALSE),0) -> 0
D97: =IFERROR(VLOOKUP(A97,[1]!TablaTransporte[#Data],2,FALSE),0) -> 0
D98: =IFERROR(VLOOKUP(A98,[1]!TablaTransporte[#Data],2,FALSE),0) -> 0
F99: =SUM(E87:E98) -> 275000
F100: =F38+F75+F85+F99 -> 5228386.4
A101: 0.15 | F101: =F100*A101 -> 784257.96
F102: =F100+F101 -> 6012644.4
A103: 0.1 | F103: =F102*A103 -> 601264.44
F104: =F102+F103 -> 6613908.8
F105: =F104/F3 -> 1102318.1

Sheet revegetalización 
A1: REVEGETALIZACIÓN POR CESPEDÓN EN ÁREA INDUSTRIAL
A2: EQUIPOS | B2: CANT | C2: REND/DIA | D2: TARIFA/DIA | E2: VR.PARCIAL | F2: M2
F3: 306
A4: Machete | B4: 1 | C4: 5 | D4: =IFERROR(VLOOKUP(A4,[1]!TablaEquipos[#Data],2,FALSE),0) -> 1500 | E4: =B4*C4*D4 -> 7500
A5: Lima triangular | B5: 1 | C5: 5 | D5: =IFERROR(VLOOKUP(A5,[1]!TablaEquipos[#Data],2,FALSE),0) -> 700 | E5: =B5*C5*D5 -> 3500
A6: Azadon | B6: 4 | C6: 5 | D6: =IFERROR(VLOOKUP(A6,[1]!TablaEquipos[#Data],2,FALSE),0) -> 700 | E6: =B6*C6*D6 -> 14000
A7: Pica | B7: 4 | C7: 5 | D7: =IFERROR(VLOOKUP(A7,[1]!TablaEquipos[#Data],2,FALSE),0) -> 700 | E7: =B7*C7*D7 -> 14000
A8: Palín | B8: 4 | C8: 5 | D8: =IFERROR(VLOOKUP(A8,[1]!TablaEquipos[#Data],2,FALSE),0) -> 700 | E8: =B8*C8*D8 -> 14000
A9: Herramientero | B9: 1 | C9: 5 | D9: =IFERROR(VLOOKUP(A9,[1]!TablaEquipos[#Data],2,FALSE),0) -> 1500 | E9: =B9*C9*D9 -> 7500
A10: Carretilla | B10: 4 | C10: 5 | D10: =IFERROR(VLOOKUP(A10,[1]!TablaEquipos[#Data],2,FALSE),0) -> 1500 | E10: =B10*C10*D10 -> 30000
A11: Buldron | B11: 1 | C11: 7.5 | D11: =IFERROR(VLOOKUP(A11,[1]!TablaEquipos[#Data],2,FALSE),0) -> 5000 | E11: =B11*C11*D11 -> 37500
A12: Colombina | B12: 12 | C12: 7.5 | D12: =IFERROR(VLOOKUP(A12,[1]!TablaEquipos[#Data],2,FALSE),0) -> 1000 | E12: =B12*C12*D12 -> 90000
A13: Pisones manuales | B13: 1 | C13: 5 | D13: =IFERROR(VLOOKUP(A13,[1]!TablaEquipos[#Data],2,FALSE),0) -> 700 | E13: =B13*C13*D13 -> 3500
A14: Avisos de seguridad | B14: 10 | C14: 7.5 | D14: =IFERROR(VLOOKUP(A14,[1]!TablaEquipos[#Data],2,FALSE),0) -> 1000 | E14: =B14*C14*D14 -> 75000
F15: =SUM(E4:E14) -> 296500
A16: MATERIALES | B16: CANT | C16: REND/DIA | D16: TARIFA | E16: VR.PARCIAL
A17: Listón de madera 2 x 1 x 3 | B17: 12 | D17: =IFERROR(VLOOKUP(A17,[1]!TablaMateriales[#Data],2,FALSE),0) -> 20000 | E17: =B17*D17 -> 240000
A18: Cinta de seguridad amarilla/negra x 500 | B18: 1 | D18: =IFERROR(VLOOKUP(A18,[1]!TablaMateriales[#Data],2,FALSE),0) -> 55000 | E18: =B18*D18 -> 55000
A19: Cespedon x M2 | B19: 322 | D19: =IFERROR(VLOOKUP(A19,[1]!TablaMateriales[#Data],2,FALSE),0) -> 35000 | E19: =B19*D19 -> 11270000
A20: Abono organico x M2 | B20: 306 | D20: =IFERROR(VLOOKUP(A20,[1]!TablaMateriales[#Data],2,FALSE),0) -> 5000 | E20: =B20*D20 -> 1530000
A21: Agua m3 | B21: 10 | D21: =IFERROR(VLOOKUP(A21,[1]!TablaMateriales[#Data],2,FALSE),0) -> 6000 | E21: =B21*D21 -> 60000
A22: Manguera mt | B22: 50 | D22: =IFERROR(VLOOKUP(A22,[1]!TablaMateriales[#Data],2,FALSE),0) -> 33400 | E22: =B22*D22 -> 1670000
A23: Aspersores | B23: 12 | D23: =IFERROR(VLOOKUP(A23,[1]!TablaMateriales[#Data],2,FALSE),0) -> 34900 | E23: =B23*D23 -> 418800
A24: Manguera para jardin | B24: 1 | D24: =IFERROR(VLOOKUP(A24,[1]!TablaMateriales[#Data],2,FALSE),0) -> 155000 | E24: =B24*D24 -> 155000
D25: =IFERROR(VLOOKUP(A25,[1]!TablaMateriales[#Data],2,FALSE),0) -> 0
F26: =SUM(E17:E25) -> 15398800
A27: MANO DE OBRA | B27: CANT | C27: REND/DIA | D27: SALARIO | E27: VR.PARCIAL
A28: Capataz | B28: 1 | C28: 9.48 | D28: 434781.14 | E28: =B28*C28*D28 -> 4121725.2
A29: Hse | B29: 1 | C29: 9.48 | D29: 434781.14 | E29: =B29*C29*D29 -> 4121725.2
A30: Topografo | B30: 1 | D30: 434781.14 | E30: =B30*C30*D30 -> 0
A31: Cadenero 1 | B31: 1.5 | D31: 383405.21 | E31: =B31*C31*D31 -> 0
A32: Andamiero | B32: 2 | D32: 383405.21 | E32: =B32*C32*D32 -> 0
A33: Oficial construccion | B33: 2 | C33: 9.48 | D33: 355463.25 | E33: =B33*C33*D33 -> 6739583.2
A34: Auxiliar Administrativo | B34: 1 | C34: 9.48 | D34: 383405.21 | E34: =B34*C34*D34 -> 3634681.4
A35: Auxiliar civil | B35: 8 | C35: 9.48 | D35: 355463.25 | E35: =B35*C35*D35 -> 26958333
F36: =SUM(E28:E35) -> 45576048
A37: TRANSPORTE | B37: CANT | C37: REND/DIA | D37: TARIFA | E37: VR.PARCIAL
A38: Camión doble cabina | B38: 1 | C38: 5 | D38: =IFERROR(VLOOKUP(A38,[1]!TablaTransporte[#Data],2,FALSE),0) -> 550000 | E38: =B38*C38*D38 -> 2750000
A39: Acarreo por km | B39: 1 | D39: =IFERROR(VLOOKUP(A39,[1]!TablaTransporte[#Data],2,FALSE),0) -> 65000 | E39: =B39*C39*D39 -> 0
A40: Retroexcavadora de oruga | B40: 1 | D40: =IFERROR(VLOOKUP(A40,[1]!TablaTransporte[#Data],2,FALSE),0) -> 322000 | E40: =B40*C40*D40 -> 0
A41: Retroexcavadora con llantas | B41: 1 | D41: =IFERROR(VLOOKUP(A41,[1]!TablaTransporte[#Data],2,FALSE),0) -> 190000 | E41: =C41*D41 -> 0
A42: Volqueta de 14 m³ | B42: 1 | D42: =IFERROR(VLOOKUP(A42,[1]!TablaTransporte[#Data],2,FALSE),0) -> 1350000 | E42: =C42*D42 -> 0
A43: Vibro compactador grande | D43: =IFERROR(VLOOKUP(A43,[1]!TablaTransporte[#Data],2,FALSE),0) -> 1330000 | E43: =C43*D43 -> 0
A44: mini cargador | B44: 1 | D44: =IFERROR(VLOOKUP(A44,[1]!TablaTransporte[#Data],2,FALSE),0) -> 840000 | E44: =B44*C44*D44 -> 0
A45: Buseta Acpm | B45: 1 | C45: 5 | D45: =IFERROR(VLOOKUP(A45,[1]!TablaTransporte[#Data],2,FALSE),0) -> 600000 | E45: =B45*C45*D45 -> 3000000
D46: =IFERROR(VLOOKUP(A46,[1]!TablaTransporte[#Data],2,FALSE),0) -> 0
D47: =IFERROR(VLOOKUP(A47,[1]!TablaTransporte[#Data],2,FALSE),0) -> 0
D48: =IFERROR(VLOOKUP(A48,[1]!TablaTransporte[#Data],2,FALSE),0) -> 0
D49: =IFERROR(VLOOKUP(A49,[1]!TablaTransporte[#Data],2,FALSE),0) -> 0
F50: =SUM(E38:E49) -> 5750000
F51: =F15+F26+F36+F50 -> 67021348
F52: =F51*A52 -> 0
F53: =F51+F52 -> 67021348
F54: =F53*A54 -> 0
F55: =F53+F54 -> 67021348
F56: =F55/F3 -> 219024.01

Sheet escarifitación 
A1: ESCARIFICACIÓN, CUNETEO Y COMPACTACIÓN DE VÍAS
A2: EQUIPOS | B2: CANT | C2: REND/DIA | D2: TARIFA/DIA | E2: VR.PARCIAL | F2: M2
F3: 10
A4: Machete | B4: 2 | C4: 2 | D4: =IFERROR(VLOOKUP(A4,[1]!TablaEquipos[#Data],2,FALSE),0) -> 1500 | E4: =B4*C4*D4 -> 6000
A5: Lima triangular | B5: 2 | C5: 2 | D5: =IFERROR(VLOOKUP(A5,[1]!TablaEquipos[#Data],2,FALSE),0) -> 700 | E5: =B5*C5*D5 -> 2800
A6: Martillo | B6: 1 | D6: =IFERROR(VLOOKUP(A6,[1]!TablaEquipos[#Data],2,FALSE),0) -> 700 | E6: =B6*C6*D6 -> 0
A7: Pala | B7: 2 | C7: 2 | D7: =IFERROR(VLOOKUP(A7,[1]!TablaEquipos[#Data],2,FALSE),0) -> 700 | E7: =B7*C7*D7 -> 2800
A8: Pica | B8: 2 | C8: 2 | D8: =IFERROR(VLOOKUP(A8,[1]!TablaEquipos[#Data],2,FALSE),0) -> 700 | E8: =B8*C8*D8 -> 2800
A9: Palín | B9: 8 | D9: =IFERROR(VLOOKUP(A9,[1]!TablaEquipos[#Data],2,FALSE),0) -> 700 | E9: =B9*C9*D9 -> 0
A10: Paladraga | B10: 4 | D10: =IFERROR(VLOOKUP(A10,[1]!TablaEquipos[#Data],2,FALSE),0) -> 1500 | E10: =B10*C10*D10 -> 0
A11: Barra | B11: 1 | C11: 2 | D11: =IFERROR(VLOOKUP(A11,[1]!TablaEquipos[#Data],2,FALSE),0) -> 1500 | E11: =B11*C11*D11 -> 3000
A12: Herramientero | B12: 1 | D12: =IFERROR(VLOOKUP(A12,[1]!TablaEquipos[#Data],2,FALSE),0) -> 1500 | E12: =B12*C12*D12 -> 0
A13: Sierra circular | B13: 1 | D13: =IFERROR(VLOOKUP(A13,[1]!TablaEquipos[#Data],2,FALSE),0) -> 15000 | E13: =B13*C13*D13 -> 0
A14: Alicate diablo | B14: 1 | C14: 2 | D14: =IFERROR(VLOOKUP(A14,[1]!TablaEquipos[#Data],2,FALSE),0) -> 500 | E14: =B14*C14*D14 -> 1000
A15: Alicate universal | D15: =IFERROR(VLOOKUP(A15,[1]!TablaEquipos[#Data],2,FALSE),0) -> 500 | E15: =B15*C15*D15 -> 0
A16: Andamios Layher | D16: =IFERROR(VLOOKUP(A16,[1]!TablaEquipos[#Data],2,FALSE),0) -> 135000 | E16: =B16*C16*D16 -> 0
A17: Arnés de seguridad | D17: =IFERROR(VLOOKUP(A17,[1]!TablaEquipos[#Data],2,FALSE),0) -> 0 | E17: =B17*C17*D17 -> 0
A18: Línea de vida | D18: =IFERROR(VLOOKUP(A18,[1]!TablaEquipos[#Data],2,FALSE),0) -> 9000 | E18: =B18*C18*D18 -> 0
A19: Nivel torpedo | D19: =IFERROR(VLOOKUP(A19,[1]!TablaEquipos[#Data],2,FALSE),0) -> 1000 | E19: =B19*C19*D19 -> 0
A20: Carretilla | B20: 2 | C20: 2 | D20: =IFERROR(VLOOKUP(A20,[1]!TablaEquipos[#Data],2,FALSE),0) -> 1500 | E20: =B20*C20*D20 -> 6000
A21: Martillo demoledor neumático/eléctrico | D21: =IFERROR(VLOOKUP(A21,[1]!TablaEquipos[#Data],2,FALSE),0) -> 80000 | E21: =B21*C21*D21 -> 0
A22: Rodillo tipo Benitín | B22: 1 | D22: =IFERROR(VLOOKUP(A22,[1]!TablaEquipos[#Data],2,FALSE),0) -> 100000 | E22: =B22*C22*D22 -> 0
A23: Vibrocompactador tipo rana | B23: 1 | D23: =IFERROR(VLOOKUP(A23,[1]!TablaEquipos[#Data],2,FALSE),0) -> 40000 | E23: =B23*C23*D23 -> 0
A24: Vibrocompactador tipo canguro | B24: 1 | D24: =IFERROR(VLOOKUP(A24,[1]!TablaEquipos[#Data],2,FALSE),0) -> 60000 | E24: =B24*C24*D24 -> 0
A25: Paletas | B25: 2 | D25: =IFERROR(VLOOKUP(A25,[1]!TablaEquipos[#Data],2,FALSE),0) -> 500 | E25: =B25*C25*D25 -> 0
A26: Chaleco reflectivo | B26: 2 | D26: =IFERROR(VLOOKUP(A26,[1]!TablaEquipos[#Data],2,FALSE),0) -> 625 | E26: =B26*C26*D26 -> 0
A27: Colombiana | B27: 12 | D27: =IFERROR(VLOOKUP(A27,[1]!TablaEquipos[#Data],2,FALSE),0) -> 0 | E27: =B27*C27*D27 -> 0
A28: Avisos de seguridad | B28: 10 | C28: 2 | D28: =IFERROR(VLOOKUP(A28,[1]!TablaEquipos[#Data],2,FALSE),0) -> 1000 | E28: =B28*C28*D28 -> 20000
A29: Carpa plastica 6x6
A30: Carpa plastica 4x4
A31: Carpa plastica 6x4
F38: =SUM(E4:E37) -> 44400
A39: MATERIALES | B39: CANT | C39: REND/DIA | D39: TARIFA | E39: VR.PARCIAL
A40: Listón de madera 2 x 4 x 3 | D40: =IFERROR(VLOOKUP(A40,[1]!TablaMateriales[#Data],2,FALSE),0) -> 35000 | E40: =B40*D40 -> 0
A41: Listón de madera 2 x 1 x 3 | D41: =IFERROR(VLOOKUP(A41,[1]!TablaMateriales[#Data],2,FALSE),0) -> 20000 | E41: =B41*D41 -> 0
A42: Cal | D42: =IFERROR(VLOOKUP(A42,[1]!TablaMateriales[#Data],2,FALSE),0) -> 50000 | E42: =B42*D42 -> 0
A43: Nailon de color | D43: =IFERROR(VLOOKUP(A43,[1]!TablaMateriales[#Data],2,FALSE),0) -> 0 | E43: =B43*D43 -> 0
A44: Puntilla de 2,5" | D44: =IFERROR(VLOOKUP(A44,[1]!TablaMateriales[#Data],2,FALSE),0) -> 9500 | E44: =B44*D44 -> 0
A45: Puntilla de 3,5" | D45: =IFERROR(VLOOKUP(A45,[1]!TablaMateriales[#Data],2,FALSE),0) -> 9500 | E45: =B45*D45 -> 0
A46: Clavo de acero de 3" | D46: =IFERROR(VLOOKUP(A46,[1]!TablaMateriales[#Data],2,FALSE),0) -> 15000 | E46: =B46*D46 -> 0
A47: Pintura en aerosol | D47: =IFERROR(VLOOKUP(A47,[1]!TablaMateriales[#Data],2,FALSE),0) -> 20000 | E47: =B47*D47 -> 0
A48: Cinta de seguridad amarilla/negra x 500 | D48: =IFERROR(VLOOKUP(A48,[1]!TablaMateriales[#Data],2,FALSE),0) -> 55000 | E48: =B48*D48 -> 0
A49: Grapa | D49: =IFERROR(VLOOKUP(A49,[1]!TablaMateriales[#Data],2,FALSE),0) -> 15900 | E49: =B49*D49 -> 0
A50: Alambre HG calibre 14 | D50: =IFERROR(VLOOKUP(A50,[1]!TablaMateriales[#Data],2,FALSE),0) -> 14000 | E50: =B50*D50 -> 0
A51: Tela verde de 2 metros | D51: =IFERROR(VLOOKUP(A51,[1]!TablaMateriales[#Data],2,FALSE),0) -> 3800 | E51: =B51*D51 -> 0
... A61: Triturado 3/4-1" | D61: =IFERROR(VLOOKUP(A61,[1]!TablaMateriales[#Data],2,FALSE),0) -> 0 | E61: =B61*D61 -> 0
A62: Arena | D62: =IFERROR(VLOOKUP(A62,[1]!TablaMateriales[#Data],2,FALSE),0) -> 0
A63: Adoquin | D63: =IFERROR(VLOOKUP(A63,[1]!TablaMateriales[#Data],2,FALSE),0) -> 0 | E63: =B63*D63 -> 0
A64: Ladrillo tolete | D64: =IFERROR(VLOOKUP(A64,[1]!TablaMateriales[#Data],2,FALSE),0) -> 0 | E64: =B64*D64 -> 0
A65: Arena | D65: =IFERROR(VLOOKUP(A65,[1]!TablaMateriales[#Data],2,FALSE),0) -> 0 | E65: =B65*D65 -> 0
A66: Cemento x 50 kilos | D66: =IFERROR(VLOOKUP(A66,[1]!TablaMateriales[#Data],2,FALSE),0) -> 0 | E66: =B66*D66 -> 0
A67: Sikasel x kilo | D67: =IFERROR(VLOOKUP(A67,[1]!TablaMateriales[#Data],2,FALSE),0) -> 0 | E67: =B67*D67 -> 0
A68: Cespedon x M2 | D68: =IFERROR(VLOOKUP(A68,[1]!TablaMateriales[#Data],2,FALSE),0) -> 35000 | E68: =B68*D68 -> 0
A69: Abono organico x M2 | D69: =IFERROR(VLOOKUP(A69,[1]!TablaMateriales[#Data],2,FALSE),0) -> 5000 | E69: =B69*D69 -> 0
A70: Hoga | B70: 0.2 | D70: =IFERROR(VLOOKUP(A70,[1]!TablaMateriales[#Data],2,FALSE),0) -> 450000 | E70: =B70*D70 -> 90000
D71: =IFERROR(VLOOKUP(A71,[1]!TablaMateriales[#Data],2,FALSE),0) -> 0
D72: =IFERROR(VLOOKUP(A72,[1]!TablaMateriales[#Data],2,FALSE),0) -> 0
D73: =IFERROR(VLOOKUP(A73,[1]!TablaMateriales[#Data],2,FALSE),0) -> 0
D74: =IFERROR(VLOOKUP(A74,[1]!TablaMateriales[#Data],2,FALSE),0) -> 0
F75: =SUM(E40:E74) -> 90000
A76: MANO DE OBRA | B76: CANT | C76: REND/DIA | D76: SALARIO | E76: VR.PARCIAL
A77: Capataz | B77: 1 | C77: 2.5 | D77: 434781.14 | E77: =B77*C77*D77 -> 1086952.8
A78: Hse | B78: 1 | C78: 2.5 | D78: 434781.14 | E78: =B78*C78*D78 -> 1086952.8
A79: Topografo | B79: 1 | D79: 434781.14 | E79: =B79*C79*D79 -> 0
A80: Cadenero 1 | B80: 1.5 | D80: 383405.21 | E80: =B80*C80*D80 -> 0
A81: Andamiero | B81: 2 | D81: 383405.21 | E81: =B81*C81*D81 -> 0
A82: Oficial construccion | B82: 1 | C82: 2.5 | D82: 355463.25 | E82: =B82*C82*D82 -> 888658.12
A83: Auxiliar Administrativo | B83: 1 | C83: 2.5 | D83: 383405.21 | E83: =B83*C83*D83 -> 958513.02
A84: Auxiliar civil | B84: 4 | C84: 2.5 | D84: 355463.25 | E84: =B84*C84*D84 -> 3554632.5
F85: =SUM(E77:E84) -> 7575709.3
A86: TRANSPORTE | B86: CANT | C86: REND/DIA | D86: TARIFA | E86: VR.PARCIAL
A87: Camión doble cabina | B87: 1 | D87: =IFERROR(VLOOKUP(A87,[1]!TablaTransporte[#Data],2,FALSE),0) -> 550000 | E87: =B87*C87*D87 -> 0
A88: Acarreo por km | B88: 1 | D88: =IFERROR(VLOOKUP(A88,[1]!TablaTransporte[#Data],2,FALSE),0) -> 65000 | E88: =B88*C88*D88 -> 0
A89: Retroexcavadora de oruga | B89: 1 | D89: =IFERROR(VLOOKUP(A89,[1]!TablaTransporte[#Data],2,FALSE),0) -> 322000 | E89: =B89*C89*D89 -> 0
A90: Retroexcavadora con llantas | B90: 1 | D90: =IFERROR(VLOOKUP(A90,[1]!TablaTransporte[#Data],2,FALSE),0) -> 190000 | E90: =C90*D90 -> 0
A91: Volqueta de 14 m³ | B91: 1 | C91: 1 | D91: =IFERROR(VLOOKUP(A91,[1]!TablaTransporte[#Data],2,FALSE),0) -> 1350000 | E91: =C91*D91 -> 1350000
A92: Vibro compactador grande | D92: =IFERROR(VLOOKUP(A92,[1]!TablaTransporte[#Data],2,FALSE),0) -> 1330000 | E92: =C92*D92 -> 0
A93: mini cargador | B93: 1 | C93: 2 | D93: =IFERROR(VLOOKUP(A93,[1]!TablaTransporte[#Data],2,FALSE),0) -> 840000 | E93: =B93*C93*D93 -> 1680000
A94: moto nieveladora | B94: 1 | C94: 2 | D94: =IFERROR(VLOOKUP(A94,[1]!TablaTransporte[#Data],2,FALSE),0) -> 1820000 | E94: =B94*C94*D94 -> 3640000
A95: camion cinterna | B95: 1 | C95: 2 | D95: =IFERROR(VLOOKUP(A95,[1]!TablaTransporte[#Data],2,FALSE),0) -> 1500000 | E95: =B95*C95*D95 -> 3000000
A96: trasporte de equipos | B96: 1 | C96: 2 | D96: =IFERROR(VLOOKUP(A96,[1]!TablaTransporte[#Data],2,FALSE),0) -> 1650000 | E96: =B96*C96*D96 -> 3300000
A97: Buseta Acpm | B97: 1 | C97: 2 | D97: =IFERROR(VLOOKUP(A97,[1]!TablaTransporte[#Data],2,FALSE),0) -> 600000 | E97: =B97*C97*D97 -> 1200000
D98: =IFERROR(VLOOKUP(A98,[1]!TablaTransporte[#Data],2,FALSE),0) -> 0
F99: =SUM(E87:E98) -> 14170000
F100: =F38+F75+F85+F99 -> 21880109
F101: =F100*A101 -> 0
F102: =F100+F101 -> 21880109
F103: =F102*A103 -> 0
F104: =F102+F103 -> 21880109
F105: =F104/F3 -> 2188010.9

Sheet construción alcantarilla 
A1: CONSTRUCIÓN DE ALCANTARILLA DE 30" A 36" L=6M
A2: EQUIPOS | B2: CANT | C2: REND/DIA | D2: TARIFA/DIA | E2: VR.PARCIAL | F2: JORNADA
F3: UNIDAD
A4: Machete | B4: 2 | C4: 15 | D4: =IFERROR(VLOOKUP(A4,[1]!TablaEquipos[#Data],3,FALSE),0) -> 1875 | E4: =B4*C4*D4 -> 56250 | F4: 3
A5: Lima triangular | B5: 1 | C5: 15 | D5: =IFERROR(VLOOKUP(A5,[1]!TablaEquipos[#Data],3,FALSE),0) -> 875 | E5: =B5*C5*D5 -> 13125
A6: Martillo | B6: 2 | C6: 15 | D6: =IFERROR(VLOOKUP(A6,[1]!TablaEquipos[#Data],3,FALSE),0) -> 875 | E6: =B6*C6*D6 -> 26250
A7: Pala | B7: 8 | C7: 15 | D7: =IFERROR(VLOOKUP(A7,[1]!TablaEquipos[#Data],3,FALSE),0) -> 875 | E7: =B7*C7*D7 -> 105000
A8: Pica | B8: 4 | C8: 15 | D8: =IFERROR(VLOOKUP(A8,[1]!TablaEquipos[#Data],3,FALSE),0) -> 875 | E8: =B8*C8*D8 -> 52500
A9: Palín | B9: 4 | C9: 15 | D9: =IFERROR(VLOOKUP(A9,[1]!TablaEquipos[#Data],3,FALSE),0) -> 875 | E9: =B9*C9*D9 -> 52500
A10: Paladraga | B10: 1 | C10: 15 | D10: =IFERROR(VLOOKUP(A10,[1]!TablaEquipos[#Data],3,FALSE),0) -> 1875 | E10: =B10*C10*D10 -> 28125
A11: Barra | B11: 1 | C11: 15 | D11: =IFERROR(VLOOKUP(A11,[1]!TablaEquipos[#Data],3,FALSE),0) -> 1875 | E11: =B11*C11*D11 -> 28125
A12: Herramientero | B12: 1 | C12: 15 | D12: =IFERROR(VLOOKUP(A12,[1]!TablaEquipos[#Data],3,FALSE),0) -> 1875 | E12: =B12*C12*D12 -> 28125
A13: Sierra circular | B13: 1 | C13: 15 | D13: =IFERROR(VLOOKUP(A13,[1]!TablaEquipos[#Data],3,FALSE),0) -> 18750 | E13: =B13*C13*D13 -> 281250
A14: Alicate diablo | B14: 1 | C14: 15 | D14: =IFERROR(VLOOKUP(A14,[1]!TablaEquipos[#Data],3,FALSE),0) -> 625 | E14: =B14*C14*D14 -> 9375
A15: Alicate universal | B15: 1 | C15: 15 | D15: =IFERROR(VLOOKUP(A15,[1]!TablaEquipos[#Data],3,FALSE),0) -> 625 | E15: =B15*C15*D15 -> 9375
A16: Nivel torpedo | B16: 1 | C16: 15 | D16: =IFERROR(VLOOKUP(A16,[1]!TablaEquipos[#Data],3,FALSE),0) -> 1250 | E16: =B16*C16*D16 -> 18750
... A31: Carpa plastica 4x4 | B31: 1 | C31: 15 | D31: =IFERROR(VLOOKUP(A31,[1]!TablaEquipos[#Data],3,FALSE),0) -> 34375 | E31: =B31*C31*D31 -> 515625
F32: =SUM(E4:E31) -> 6233125
A33: MATERIALES | B33: CANT | C33: REND/DIA | D33: TARIFA | E33: VR.PARCIAL
A34: Tubería de concreto reforzado D=36" Clase III | B34: 6 | D34: =IFERROR(VLOOKUP(A34,[1]!TablaMateriales[#Data],2,FALSE),0) -> 1460026 | E34: =B34*D34 -> 8760156
A35: Concreto 3000 psi para estructuras/cabezales/aletas | B35: 13 | D35: =IFERROR(VLOOKUP(A35,[1]!TablaMateriales[#Data],2,FALSE),0) -> 620000 | E35: =B35*D35 -> 8060000
A36: Concreto 2500 psi para solado/atraque | B36: 1 | D36: =IFERROR(VLOOKUP(A36,[1]!TablaMateriales[#Data],2,FALSE),0) -> 464823 | E36: =B36*D36 -> 464823
A37: Acero de refuerzo G-60 figurado | B37: 1180 | D37: =IFERROR(VLOOKUP(A37,[1]!TablaMateriales[#Data],2,FALSE),0) -> 4341 | E37: =B37*D37 -> 5122380
A39: Material seleccionado para relleno | B39: 22 | D39: =IFERROR(VLOOKUP(A39,[1]!TablaMateriales[#Data],2,FALSE),0) -> 56327 | E39: =B39*D39 -> 1239194
A40: Listón de madera 2 x 4 x 3 | B40: 30 | D40: =IFERROR(VLOOKUP(A40,[1]!TablaMateriales[#Data],2,FALSE),0) -> 35000 | E40: =B40*D40 -> 1050000
A41: Listón de madera 2 x 1 x 3 | B41: 15 | D41: =IFERROR(VLOOKUP(A41,[1]!TablaMateriales[#Data],2,FALSE),0) -> 20000 | E41: =B41*D41 -> 300000
A42: Puntilla de 2,5" | B42: 5 | D42: =IFERROR(VLOOKUP(A42,[1]!TablaMateriales[#Data],2,FALSE),0) -> 9500 | E42: =B42*D42 -> 47500
A43: Puntilla de 3,5" | B43: 5 | D43: =IFERROR(VLOOKUP(A43,[1]!TablaMateriales[#Data],2,FALSE),0) -> 9500 | E43: =B43*D43 -> 47500
A44: Tabla | B44: 70 | D44: =IFERROR(VLOOKUP(A44,[1]!TablaMateriales[#Data],2,FALSE),0) -> 30000 | E44: =B44*D44 -> 2100000
A45: Alambre negro para amarre | B45: 13 | D45: =IFERROR(VLOOKUP(A45,[1]!TablaMateriales[#Data],2,FALSE),0) -> 7592 | E45: =B45*D45 -> 98696
A46: Base Granular m3 | B46: 24 | D46: =IFERROR(VLOOKUP(A46,[1]!TablaMateriales[#Data],2,FALSE),0) -> 76500 | E46: =B46*D46 -> 1836000
... A51: Plástico negro | B51: 1 | D51: =IFERROR(VLOOKUP(A51,[1]!TablaMateriales[#Data],2,FALSE),0) -> 9500 | E51: =B51*D51 -> 9500
F52: =SUM(E34:E51) -> 30121749
A53: MANO DE OBRA | B53: CANT | C53: REND/DIA | D53: SALARIO | E53: VR.PARCIAL
A54: Capataz | B54: 1 | C54: 21 | D54: 399155 | E54: =B54*C54*D54 -> 8382255
A55: Hse | B55: 1 | C55: 21 | D55: 399155 | E55: =B55*C55*D55 -> 8382255
A56: Topografo | B56: 1 | C56: 4.5 | D56: 399155 | E56: =B56*C56*D56 -> 1796197.5
A57: Cadenero 1 | B57: 1 | C57: 5 | D57: 355463 | E57: =B57*C57*D57 -> 1777315
A58: Andamiero | B58: 0 | C58: 0 | D58: 355463 | E58: =B58*C58*D58 -> 0
A59: Oficial construccion | B59: 2 | C59: 21 | D59: 402655 | E59: =B59*C59*D59 -> 16911510
A60: Auxiliar Administrativo | B60: 1 | C60: 21 | D60: 355463 | E60: =B60*C60*D60 -> 7464723
A61: Auxiliar civil | B61: 8 | C61: 21 | D61: 406359 | E61: =B61*C61*D61 -> 68268312
F62: =SUM(E54:E61) -> 1.1298257e+08
A63: TRANSPORTE | B63: CANT | C63: REND/DIA | D63: TARIFA | E63: VR.PARCIAL
A64: Camión doble cabina | B64: 1 | C64: 7 | D64: =IFERROR(VLOOKUP(A64,[1]!TablaTransporte[#Data],2,FALSE),0) -> 550000 | E64: =B64*C64*D64 -> 3850000
A65: Retroexcavadora de oruga | B65: 1 | C65: 4 | D65: =IFERROR(VLOOKUP(A65,[1]!TablaTransporte[#Data],2,FALSE),0) -> 322000 | E65: =B65*C65*D65 -> 1288000
A66: Volqueta de 14 m³ | B66: 1 | C66: 4 | D66: =IFERROR(VLOOKUP(A66,[1]!TablaTransporte[#Data],2,FALSE),0) -> 1350000 | E66: =B66*C66*D66 -> 5400000
A67: Buseta Acpm | B67: 1 | C67: 15 | D67: =IFERROR(VLOOKUP(A67,[1]!TablaTransporte[#Data],2,FALSE),0) -> 600000 | E67: =C67*D67 -> 9000000
A68: Transporte de equipo | B68: 1 | C68: 6 | D68: =IFERROR(VLOOKUP(A68,[1]!TablaTransporte[#Data],2,FALSE),0) -> 0 | E68: =B68*C68*D68 -> 0
A69: Concretadora Bulto y Medio Acpm | B69: 1 | C69: 15 | D69: =IFERROR(VLOOKUP(A69,[1]!TablaTransporte[#Data],2,FALSE),0) -> 600000 | E69: =B69*C69*D69 -> 9000000
D70: =IFERROR(VLOOKUP(A70,[1]!TablaTransporte[#Data],2,FALSE),0) -> 0 | E70: =B70*C70*D70 -> 0
D71: =IFERROR(VLOOKUP(A71,[1]!TablaTransporte[#Data],2,FALSE),0) -> 0
D72: =IFERROR(VLOOKUP(A72,[1]!TablaTransporte[#Data],2,FALSE),0) -> 0
F73: =SUM(E64:E72) -> 28538000
F74: =F32+F52+F62+F73 -> 1.7787544e+08
A75: 0.15 | F75: =F74*A75 -> 26681316
F76: =F74+F75 -> 2.0455676e+08
A77: 0.1 | F77: =F76*A77 -> 20455676
F78: =F76+F77 -> 2.2501243e+08
F79: =F78/F4 -> 75004144

Sheet canal en piedra 
A1: CANAL EN PIEDRA PEGADA
A2: EQUIPOS | B2: CANT | C2: REND/DIA | D2: TARIFA/DIA | E2: VR.PARCIAL | F2: M2
F3: 12
A4: pala | B4: 3 | C4: 3 | D4: =IFERROR(VLOOKUP(A4,[1]!TablaEquipos[#Data],2,FALSE),0) -> 700 | E4: =B4*C4*D4 -> 6300
A5: Martillo | B5: 1 | C5: 3 | D5: =IFERROR(VLOOKUP(A5,[1]!TablaEquipos[#Data],2,FALSE),0) -> 700 | E5: =B5*C5*D5 -> 2100
A6: machete | B6: 1 | C6: 3 | D6: =IFERROR(VLOOKUP(A6,[1]!TablaEquipos[#Data],2,FALSE),0) -> 1500 | E6: =B6*C6*D6 -> 4500
A7: Barra | B7: 1 | C7: 3 | D7: =IFERROR(VLOOKUP(A7,[1]!TablaEquipos[#Data],2,FALSE),0) -> 1500 | E7: =B7*C7*D7 -> 4500
A8: Concretadora | B8: 1 | C8: 3 | D8: =IFERROR(VLOOKUP(A8,[1]!TablaEquipos[#Data],2,FALSE),0) -> 60000 | E8: =B8*C8*D8 -> 180000
A9: Llana metalica | B9: 2 | C9: 3 | D9: =IFERROR(VLOOKUP(A9,[1]!TablaEquipos[#Data],2,FALSE),0) -> 700 | E9: =B9*C9*D9 -> 4200
A10: Buldron | B10: 1 | C10: 7 | D10: =IFERROR(VLOOKUP(A10,[1]!TablaEquipos[#Data],2,FALSE),0) -> 5000 | E10: =B10*C10*D10 -> 35000
A11: Palín | B11: 2 | C11: 3 | D11: =IFERROR(VLOOKUP(A11,[1]!TablaEquipos[#Data],2,FALSE),0) -> 700 | E11: =B11*C11*D11 -> 4200
A12: azadon | B12: 2 | C12: 3 | D12: =IFERROR(VLOOKUP(A12,[1]!TablaEquipos[#Data],2,FALSE),0) -> 700 | E12: =B12*C12*D12 -> 4200
A13: pica | B13: 2 | C13: 3 | D13: =IFERROR(VLOOKUP(A13,[1]!TablaEquipos[#Data],2,FALSE),0) -> 700 | E13: =B13*C13*D13 -> 4200
A14: Balde concretero | B14: 4 | C14: 3 | D14: =IFERROR(VLOOKUP(A14,[1]!TablaEquipos[#Data],2,FALSE),0) -> 500 | E14: =B14*C14*D14 -> 6000
A15: Codo sanitaria 6" Reutilizar | B15: 1 | C15: 3 | D15: =IFERROR(VLOOKUP(A15,[1]!TablaEquipos[#Data],2,FALSE),0) -> 10000 | E15: =B15*C15*D15 -> 30000
... A17: Palustre / llana | B17: 2 | C17: 3 | D17: =IFERROR(VLOOKUP(A17,[1]!TablaEquipos[#Data],2,FALSE),0) -> 700 | E17: =B17*C17*D17 -> 4200
F18: =SUM(E4:E17) -> 379400
A19: MATERIALES | B19: CANT | C19: REND/DIA | D19: TARIFA | E19: VR.PARCIAL
A20: Plástico negro | B20: 20 | D20: =IFERROR(VLOOKUP(A20,[1]!TablaMateriales[#Data],2,FALSE),0) -> 9500 | E20: =B20*D20 -> 190000
A21: Listón de madera 2 x 1 x 3 | B21: 10 | D21: =IFERROR(VLOOKUP(A21,[1]!TablaMateriales[#Data],2,FALSE),0) -> 20000 | E21: =B21*D21 -> 200000
A22: Nailon de color | B22: 1 | D22: =IFERROR(VLOOKUP(A22,[1]!TablaMateriales[#Data],2,FALSE),0) -> 0 | E22: =B22*D22 -> 0
A23: Puntilla de 2,5" | B23: 1 | D23: =IFERROR(VLOOKUP(A23,[1]!TablaMateriales[#Data],2,FALSE),0) -> 9500 | E23: =B23*D23 -> 9500
A24: Cinta de seguridad amarilla/negra x 500 | B24: 1 | D24: =IFERROR(VLOOKUP(A24,[1]!TablaMateriales[#Data],2,FALSE),0) -> 55000 | E24: =B24*D24 -> 55000
A25: Cemento 50 kl | B25: 10 | D25: =IFERROR(VLOOKUP(A25,[1]!TablaMateriales[#Data],2,FALSE),0) -> 38000 | E25: =B25*D25 -> 380000
A26: Material seleccionado para relleno | B26: 1.5 | D26: =IFERROR(VLOOKUP(A26,[1]!TablaMateriales[#Data],2,FALSE),0) -> 56327 | E26: =B26*D26 -> 84490.5
A27: Piedra Filtro 3" maximo tamaño | B27: 1.5 | D27: =IFERROR(VLOOKUP(A27,[1]!TablaMateriales[#Data],2,FALSE),0) -> 53000 | E27: =B27*D27 -> 79500
A28: Agua m3 | B28: 0.5 | D28: =IFERROR(VLOOKUP(A28,[1]!TablaMateriales[#Data],2,FALSE),0) -> 6000 | E28: =B28*D28 -> 3000
A29: Sacos de polipropileno | B29: 20 | D29: =IFERROR(VLOOKUP(A29,[1]!TablaMateriales[#Data],2,FALSE),0) -> 1200 | E29: =B29*D29 -> 24000
A30: Sika Set L 2,5 kl | B30: 0.5 | D30: =IFERROR(VLOOKUP(A30,[1]!TablaMateriales[#Data],2,FALSE),0) -> 69900 | E30: =B30*D30 -> 34950
A31: Subbase granular m3 | B31: 0.5 | D31: =IFERROR(VLOOKUP(A31,[1]!TablaMateriales[#Data],2,FALSE),0) -> 59000 | E31: =B31*D31 -> 29500
F32: =SUM(E20:E31) -> 1089940.5
A33: MANO DE OBRA | B33: CANT | C33: REND/DIA | D33: SALARIO | E33: VR.PARCIAL
A34: Capataz | B34: 1 | C34: 5.77 | D34: ='tabla salarial'!AS4 -> 555393.74 | E34: =B34*C34*D34 -> 3204621.9
A35: Hse | B35: 1 | C35: 5.7 | D35: ='tabla salarial'!AS4 -> 555393.74 | E35: =B35*C35*D35 -> 3165744.3
A36: Topografo | B36: 1 | D36: ='tabla salarial'!AS4 -> 555393.74 | E36: =B36*C36*D36 -> 0
A37: Cadenero 1 | B37: 1.5 | D37: ='tabla salarial'!AS6 -> 407197.8 | E37: =B37*C37*D37 -> 0
A38: Andamiero | B38: 2 | D38: ='tabla salarial'!AS6 -> 407197.8 | E38: =B38*C38*D38 -> 0
A39: Oficial construccion | B39: 1 | C39: 5.77 | D39: ='tabla salarial'!AS7 -> 371571.33 | E39: =B39*C39*D39 -> 2143966.6
A40: Auxiliar Administrativo | B40: 1 | C40: 5.77 | D40: ='tabla salarial'!AS8 -> 355821.88 | E40: =B40*C40*D40 -> 2053092.2
A41: Auxiliar civil | B41: 3 | C41: 5.77 | D41: ='tabla salarial'!AS9 -> 382109.06 | E41: =B41*C41*D41 -> 6614307.8
F42: =SUM(E34:E41) -> 17181733
A43: TRANSPORTE | B43: CANT | C43: REND/DIA | D43: TARIFA | E43: VR.PARCIAL
A44: Camión doble cabina | B44: 1 | C44: 1 | D44: =IFERROR(VLOOKUP(A44,[1]!TablaTransporte[#Data],2,FALSE),0) -> 550000 | E44: =B44*C44*D44 -> 550000
A45: Buseta Acpm | B45: 1 | C45: 3 | D45: =IFERROR(VLOOKUP(A45,[1]!TablaTransporte[#Data],2,FALSE),0) -> 600000 | E45: =B45*C45*D45 -> 1800000
D46: =IFERROR(VLOOKUP(A46,[1]!TablaTransporte[#Data],2,FALSE),0) -> 0
F47: =SUM(E44:E45) -> 2350000
F48: =F18+F32+F42+F47 -> 21001073
F49: =F48*A49 -> 0
F50: =F48+F49 -> 21001073
F51: =F50*A51 -> 0
F52: =F50+F51 -> 21001073
F53: =F52/F3 -> 1750089.4

Sheet suministro e inst. de geodrén 
A1: SUMINISTRO E INSTALACIÓN DE GEODRÉN PLANAR
A2: EQUIPOS | B2: CANT | C2: REND/DIA | D2: TARIFA/DIA | E2: VR.PARCIAL | F2: M2
F3: 6
A4: Machete | B4: 1 | C4: 1 | D4: =IFERROR(VLOOKUP(A4,[1]!TablaEquipos[#Data],2,FALSE),0) -> 1500 | E4: =B4*C4*D4 -> 1500
A5: Martillo | B5: 1 | C5: 1 | D5: =IFERROR(VLOOKUP(A5,[1]!TablaEquipos[#Data],2,FALSE),0) -> 700 | E5: =B5*C5*D5 -> 700
A6: Pala | B6: 2 | C6: 1 | D6: =IFERROR(VLOOKUP(A6,[1]!TablaEquipos[#Data],2,FALSE),0) -> 700 | E6: =B6*C6*D6 -> 1400
A7: Barra | B7: 1 | C7: 1 | D7: =IFERROR(VLOOKUP(A7,[1]!TablaEquipos[#Data],2,FALSE),0) -> 1500 | E7: =B7*C7*D7 -> 1500
A8: Escoba de varita | B8: 1 | C8: 1 | D8: =IFERROR(VLOOKUP(A8,[1]!TablaEquipos[#Data],2,FALSE),0) -> 20000 | E8: =B8*C8*D8 -> 20000
A9: Carretilla | B9: 1 | C9: 1 | D9: =IFERROR(VLOOKUP(A9,[1]!TablaEquipos[#Data],2,FALSE),0) -> 1500 | E9: =B9*C9*D9 -> 1500
A10: Nivel torpedo | B10: 1 | C10: 1 | D10: =IFERROR(VLOOKUP(A10,[1]!TablaEquipos[#Data],2,FALSE),0) -> 1000 | E10: =B10*C10*D10 -> 1000
A11: pica | B11: 1 | C11: 1 | D11: =IFERROR(VLOOKUP(A11,[1]!TablaEquipos[#Data],2,FALSE),0) -> 700 | E11: =B11*C11*D11 -> 700
A12: Cúter industrial | B12: 2 | C12: 1 | D12: =IFERROR(VLOOKUP(A12,[1]!TablaEquipos[#Data],2,FALSE),0) -> 800 | E12: =B12*C12*D12 -> 1600
A13: Tijera industrial | B13: 1 | C13: 1 | D13: =IFERROR(VLOOKUP(A13,[1]!TablaEquipos[#Data],2,FALSE),0) -> 800 | E13: =B13*C13*D13 -> 800
A14: palín | B14: 1 | C14: 1 | D14: =IFERROR(VLOOKUP(A14,[1]!TablaEquipos[#Data],2,FALSE),0) -> 700 | E14: =B14*C14*D14 -> 700
A15: azadon | B15: 1 | C15: 1 | D15: =IFERROR(VLOOKUP(A15,[1]!TablaEquipos[#Data],2,FALSE),0) -> 700 | E15: =B15*C15*D15 -> 700
... A18: Vibrocompactador tipo rana | B18: 1 | C18: 1 | D18: =IFERROR(VLOOKUP(A18,[1]!TablaEquipos[#Data],2,FALSE),0) -> 40000 | E18: =B18*C18*D18 -> 40000
F19: =SUM(E4:E18) -> 112600
A20: MATERIALES | B20: CANT | C20: REND/DIA | D20: TARIFA | E20: VR.PARCIAL
A21: Listón de madera 2 x 4 x 3 | D21: =IFERROR(VLOOKUP(A21,[1]!TablaMateriales[#Data],2,FALSE),0) -> 35000 | E21: =B21*D21 -> 0
A22: Listón de madera 2 x 1 x 3 | B22: 10 | D22: =IFERROR(VLOOKUP(A22,[1]!TablaMateriales[#Data],2,FALSE),0) -> 20000 | E22: =B22*D22 -> 200000
A23: Cal | D23: =IFERROR(VLOOKUP(A23,[1]!TablaMateriales[#Data],2,FALSE),0) -> 50000 | E23: =B23*D23 -> 0
A24: Nailon de color | D24: =IFERROR(VLOOKUP(A24,[1]!TablaMateriales[#Data],2,FALSE),0) -> 0 | E24: =B24*D24 -> 0
A25: Puntilla de 2,5" | D25: =IFERROR(VLOOKUP(A25,[1]!TablaMateriales[#Data],2,FALSE),0) -> 9500 | E25: =B25*D25 -> 0
A26: Puntilla de 3,5" | D26: =IFERROR(VLOOKUP(A26,[1]!TablaMateriales[#Data],2,FALSE),0) -> 9500 | E26: =B26*D26 -> 0
A27: Clavo de acero de 3" | D27: =IFERROR(VLOOKUP(A27,[1]!TablaMateriales[#Data],2,FALSE),0) -> 15000 | E27: =B27*D27 -> 0
A28: Pintura en aerosol | D28: =IFERROR(VLOOKUP(A28,[1]!TablaMateriales[#Data],2,FALSE),0) -> 20000 | E28: =B28*D28 -> 0
A29: Cinta de seguridad amarilla/negra x 500 | D29: =IFERROR(VLOOKUP(A29,[1]!TablaMateriales[#Data],2,FALSE),0) -> 55000 | E29: =B29*D29 -> 0
A30: Grapa | D30: =IFERROR(VLOOKUP(A30,[1]!TablaMateriales[#Data],2,FALSE),0) -> 15900 | E30: =B30*D30 -> 0
A31: Alambre HG calibre 14 | D31: =IFERROR(VLOOKUP(A31,[1]!TablaMateriales[#Data],2,FALSE),0) -> 14000 | E31: =B31*D31 -> 0
A32: Tela verde de 2 metros | D32: =IFERROR(VLOOKUP(A32,[1]!TablaMateriales[#Data],2,FALSE),0) -> 3800 | E32: =B32*D32 -> 0
A33: Excavaciones menor a 1,2 m | B33: 1 | D33: 805421 | E33: =B33*D33 -> 805421
A34: Geodren planar | B34: 7 | D34: =IFERROR(VLOOKUP(A34,[1]!TablaMateriales[#Data],2,FALSE),0) -> 114000 | E34: =B34*D34 -> 798000
A35: Tuberia de Drenaje de 4" 10 m | B35: 7 | D35: =IFERROR(VLOOKUP(A35,[1]!TablaMateriales[#Data],2,FALSE),0) -> 150000 | E35: =B35*D35 -> 1050000
A36: Uniones para tubería perforada de 4" | B36: 1 | D36: =IFERROR(VLOOKUP(A36,[1]!TablaMateriales[#Data],2,FALSE),0) -> 12000 | E36: =B36*D36 -> 12000
A37: Piedra Filtro 3" maximo tamaño | B37: 0.7 | D37: =IFERROR(VLOOKUP(A37,[1]!TablaMateriales[#Data],2,FALSE),0) -> 53000 | E37: =B37*D37 -> 37100
F38: =SUM(E21:E37) -> 2902521
A39: MANO DE OBRA | B39: CANT | C39: REND/DIA | D39: SALARIO | E39: VR.PARCIAL
A40: Capataz | B40: 1 | C40: 1.5 | D40: ='tabla salarial'!AS4 -> 555393.74 | E40: =B40*C40*D40 -> 833090.61
A41: Hse | B41: 1 | C41: 1.5 | D41: ='tabla salarial'!AS4 -> 555393.74 | E41: =B41*C41*D41 -> 833090.61
A42: Topografo | B42: 1 | D42: ='tabla salarial'!AS4 -> 555393.74 | E42: =B42*C42*D42 -> 0
A43: Cadenero 1 | B43: 1.5 | D43: ='tabla salarial'!AS6 -> 407197.8 | E43: =B43*C43*D43 -> 0
A44: Andamiero | B44: 2 | D44: ='tabla salarial'!AS6 -> 407197.8 | E44: =B44*C44*D44 -> 0
A45: Oficial construccion | B45: 1 | C45: 1.5 | D45: ='tabla salarial'!AS7 -> 371571.33 | E45: =B45*C45*D45 -> 557356.99
A46: Auxiliar Administrativo | B46: 1 | C46: 1.5 | D46: ='tabla salarial'!AS8 -> 355821.88 | E46: =B46*C46*D46 -> 533732.81
A47: Auxiliar civil | B47: 2 | C47: 1.5 | D47: ='tabla salarial'!AS9 -> 382109.06 | E47: =B47*C47*D47 -> 1146327.2
A48: 3 | F48: =SUM(E40:E47) -> 3903598.2
A49: TRANSPORTE | B49: CANT | C49: REND/DIA | D49: TARIFA | E49: VR.PARCIAL
A50: Camión doble cabina | B50: 1 | C50: 1 | D50: =IFERROR(VLOOKUP(A50,[1]!TablaTransporte[#Data],2,FALSE),0) -> 550000 | E50: =B50*C50*D50 -> 550000
A51: Buseta Acpm | B51: 1 | C51: 1 | D51: =IFERROR(VLOOKUP(A51,[1]!TablaTransporte[#Data],2,FALSE),0) -> 600000 | E51: =B51*C51*D51 -> 600000
D53: =IFERROR(VLOOKUP(A53,[1]!TablaTransporte[#Data],2,FALSE),0) -> 0
F54: =E51 -> 600000
F55: =F19+F38+F48+F54 -> 7518719.2
A56: 0.15 | F56: =F55*A56 -> 1127807.9
F57: =F55+F56 -> 8646527.1
A58: 0.1 | F58: =F57*A58 -> 864652.71
F59: =F57+F58 -> 9511179.8
F60: =F59/F3 -> 1585196.6

Sheet colocación de geotextil 
A1: SUMINISTRO Y COLOCACIÓN DE GEOTEXTIL
A2: EQUIPOS | B2: CANT | C2: REND/DIA | D2: TARIFA/DIA | E2: VR.PARCIAL | F2: M2
A3: Cúter industrial | B3: 2 | C3: 0.5 | D3: =IFERROR(VLOOKUP(A3,[1]!TablaEquipos[#Data],2,FALSE),0) -> 800 | E3: =B3*C3*D3 -> 800 | F3: 18
A4: Flexómetro | B4: 2 | C4: 0.5 | D4: =IFERROR(VLOOKUP(A4,[1]!TablaEquipos[#Data],2,FALSE),0) -> 500 | E4: =B4*C4*D4 -> 500
A5: Martillo | B5: 1 | C5: 0.5 | D5: =IFERROR(VLOOKUP(A5,[1]!TablaEquipos[#Data],2,FALSE),0) -> 700 | E5: =B5*C5*D5 -> 350
D7: =IFERROR(VLOOKUP(A7,[1]!TablaEquipos[#Data],2,FALSE),0) -> 0
D8: =IFERROR(VLOOKUP(A8,[1]!TablaEquipos[#Data],2,FALSE),0) -> 0
F9: =SUM(E3:E8) -> 1650
A10: MATERIALES | B10: CANT | C10: REND/DIA | D10: TARIFA | E10: VR.PARCIAL
A11: Geotextil m2 | B11: 7 | D11: =IFERROR(VLOOKUP(A11,[1]!TablaMateriales[#Data],2,FALSE),0) -> 4300 | E11: =B11*D11 -> 30100
A12: Listón de madera 2 x 1 x 3 | B12: 5 | D12: =IFERROR(VLOOKUP(A12,[1]!TablaMateriales[#Data],2,FALSE),0) -> 20000 | E12: =B12*D12 -> 100000
A13: Cinta de seguridad amarilla/negra x 500 | B13: 0.3 | D13: =IFERROR(VLOOKUP(A13,[1]!TablaMateriales[#Data],2,FALSE),0) -> 55000 | E13: =B13*D13 -> 16500
D14: =IFERROR(VLOOKUP(A14,[1]!TablaMateriales[#Data],2,FALSE),0) -> 0 | E14: =B14*D14 -> 0
D15: =IFERROR(VLOOKUP(A15,[1]!TablaMateriales[#Data],2,FALSE),0) -> 0 | E15: =B15*D15 -> 0
D16: =IFERROR(VLOOKUP(A16,[1]!TablaMateriales[#Data],2,FALSE),0) -> 0 | E16: =B16*D16 -> 0
D17: =IFERROR(VLOOKUP(A17,[1]!TablaMateriales[#Data],2,FALSE),0) -> 0 | E17: =B17*D17 -> 0
D18: =IFERROR(VLOOKUP(A18,[1]!TablaMateriales[#Data],2,FALSE),0) -> 0
D19: =IFERROR(VLOOKUP(A19,[1]!TablaMateriales[#Data],2,FALSE),0) -> 0
D20: =IFERROR(VLOOKUP(A20,[1]!TablaMateriales[#Data],2,FALSE),0) -> 0
D21: =IFERROR(VLOOKUP(A21,[1]!TablaMateriales[#Data],2,FALSE),0) -> 0
D22: =IFERROR(VLOOKUP(A22,[1]!TablaMateriales[#Data],2,FALSE),0) -> 0
F23: =SUM(E11:E22) -> 146600
A24: MANO DE OBRA | B24: CANT | C24: REND/DIA | D24: SALARIO | E24: VR.PARCIAL
A25: Capataz | B25: 1 | C25: 0.44 | D25: ='tabla salarial'!AS4 -> 555393.74 | E25: =B25*C25*D25 -> 244373.25
A26: Hse | B26: 1 | C26: 0.44 | D26: ='tabla salarial'!AS4 -> 555393.74 | E26: =B26*C26*D26 -> 244373.25
A27: Topografo | B27: 1 | D27: ='tabla salarial'!AS4 -> 555393.74 | E27: =B27*C27*D27 -> 0
A28: Cadenero 1 | B28: 1.5 | D28: ='tabla salarial'!AS6 -> 407197.8 | E28: =B28*C28*D28 -> 0
A29: Andamiero | B29: 2 | D29: ='tabla salarial'!AS6 -> 407197.8 | E29: =B29*C29*D29 -> 0
A30: Oficial construccion | B30: 1 | C30: 0.44 | D30: ='tabla salarial'!AS7 -> 371571.33 | E30: =B30*C30*D30 -> 163491.39
A31: Auxiliar Administrativo | B31: 1 | C31: 0.44 | D31: ='tabla salarial'!AS8 -> 355821.88 | E31: =B31*C31*D31 -> 156561.63
A32: Auxiliar civil | B32: 2 | C32: 0.44 | D32: ='tabla salarial'!AS9 -> 382109.06 | E32: =B32*C32*D32 -> 336255.97
A33: 3 | F33: =SUM(E25:E32) -> 1145055.5
A34: TRANSPORTE | B34: CANT | C34: REND/DIA | D34: TARIFA | E34: VR.PARCIAL
A35: Camión doble cabina | B35: 1 | C35: 0.1 | D35: =IFERROR(VLOOKUP(A35,[1]!TablaTransporte[#Data],2,FALSE),0) -> 550000 | E35: =B35*C35*D35 -> 55000
A36: Buseta Acpm | B36: 1 | C36: 0.33 | D36: =IFERROR(VLOOKUP(A36,[1]!TablaTransporte[#Data],2,FALSE),0) -> 600000 | E36: =B36*C36*D36 -> 198000
D37: =IFERROR(VLOOKUP(A37,[1]!TablaTransporte[#Data],2,FALSE),0) -> 0
D38: =IFERROR(VLOOKUP(A38,[1]!TablaTransporte[#Data],2,FALSE),0) -> 0
F39: =SUM(E35:E37) -> 253000
F40: =F9+F23+F33+F39 -> 1546305.5
F41: =F40*A41 -> 0
F42: =F40+F41 -> 1546305.5
F43: =F42*A43 -> 0
F44: =F42+F43 -> 1546305.5
F45: =F44/F3 -> 85905.86

Sheet colocación de geomembrana 
A1: SUMINISTRO Y COLOCACIÓN DE GEOMEMBRANA
A2: EQUIPOS | B2: CANT | C2: REND/DIA | D2: TARIFA/DIA | E2: VR.PARCIAL | F2: M2
F3: 8
A4: Cúter industrial | B4: 2 | C4: 0.5 | D4: =IFERROR(VLOOKUP(A4,[1]!TablaEquipos[#Data],2,FALSE),0) -> 800 | E4: =B4*C4*D4 -> 800
A5: Flexómetro | B5: 2 | C5: 0.5 | D5: =IFERROR(VLOOKUP(A5,[1]!TablaEquipos[#Data],2,FALSE),0) -> 500 | E5: =B5*C5*D5 -> 500
A6: Martillo | B6: 1 | C6: 0.5 | D6: =IFERROR(VLOOKUP(A6,[1]!TablaEquipos[#Data],2,FALSE),0) -> 700 | E6: =B6*C6*D6 -> 350
D7: =IFERROR(VLOOKUP(A7,[1]!TablaEquipos[#Data],2,FALSE),0) -> 0
D8: =IFERROR(VLOOKUP(A8,[1]!TablaEquipos[#Data],2,FALSE),0) -> 0
D9: =IFERROR(VLOOKUP(A9,[1]!TablaEquipos[#Data],2,FALSE),0) -> 0
D10: =IFERROR(VLOOKUP(A10,[1]!TablaEquipos[#Data],2,FALSE),0) -> 0
F11: =SUM(E4:E10) -> 1650
A12: MATERIALES | B12: CANT | C12: REND/DIA | D12: TARIFA | E12: VR.PARCIAL
A13: Geomembra m2 | B13: 2 | D13: =IFERROR(VLOOKUP(A13,[1]!TablaMateriales[#Data],2,FALSE),0) -> 160000 | E13: =B13*D13 -> 320000
A14: Cinta de seguridad amarilla/negra x 500 | B14: 0.3 | D14: =IFERROR(VLOOKUP(A14,[1]!TablaMateriales[#Data],2,FALSE),0) -> 55000 | E14: =B14*D14 -> 16500
D15: =IFERROR(VLOOKUP(A15,[1]!TablaMateriales[#Data],2,FALSE),0) -> 0 | E15: =B15*D15 -> 0
D16: =IFERROR(VLOOKUP(A16,[1]!TablaMateriales[#Data],2,FALSE),0) -> 0 | E16: =B16*D16 -> 0
F17: =SUM(E13:E16) -> 336500
A18: MANO DE OBRA | B18: CANT | C18: REND/DIA | D18: SALARIO | E18: VR.PARCIAL
A19: Capataz | B19: 1 | C19: 0.41 | D19: ='tabla salarial'!AS4 -> 555393.74 | E19: =B19*C19*D19 -> 227711.43
A20: Hse | B20: 1 | C20: 0.41 | D20: ='tabla salarial'!AS4 -> 555393.74 | E20: =B20*C20*D20 -> 227711.43
A21: Topografo | B21: 1 | D21: ='tabla salarial'!AS4 -> 555393.74 | E21: =B21*C21*D21 -> 0
A22: Cadenero 1 | B22: 1.5 | D22: ='tabla salarial'!AS6 -> 407197.8 | E22: =B22*C22*D22 -> 0
A23: Andamiero | B23: 2 | D23: ='tabla salarial'!AS6 -> 407197.8 | E23: =B23*C23*D23 -> 0
A24: Oficial construccion | B24: 1 | C24: 0.41 | D24: ='tabla salarial'!AS7 -> 371571.33 | E24: =B24*C24*D24 -> 152344.25
A25: Auxiliar Administrativo | B25: 1 | C25: 0.41 | D25: ='tabla salarial'!AS8 -> 355821.88 | E25: =B25*C25*D25 -> 145886.97
A26: Auxiliar civil | B26: 2 | C26: 0.41 | D26: ='tabla salarial'!AS9 -> 382109.06 | E26: =B26*C26*D26 -> 313329.43
A27: 3 | F27: =SUM(E19:E26) -> 1066983.5
A28: TRANSPORTE | B28: CANT | C28: REND/DIA | D28: TARIFA | E28: VR.PARCIAL
A29: Camión doble cabina | B29: 1 | C29: 0.33 | D29: =IFERROR(VLOOKUP(A29,[1]!TablaTransporte[#Data],2,FALSE),0) -> 550000 | E29: =B29*C29*D29 -> 181500
A30: Buseta Acpm | B30: 1 | C30: 0.33 | D30: =IFERROR(VLOOKUP(A30,[1]!TablaTransporte[#Data],2,FALSE),0) -> 600000 | E30: =B30*C30*D30 -> 198000
D31: =IFERROR(VLOOKUP(A31,[1]!TablaTransporte[#Data],2,FALSE),0) -> 0
D32: =IFERROR(VLOOKUP(A32,[1]!TablaTransporte[#Data],2,FALSE),0) -> 0
F33: =SUM(E29:E31) -> 379500
F34: =F11+F17+F27+F33 -> 1784633.5
F35: =F34*A35 -> 0
F36: =F34+F35 -> 1784633.5
F37: =F36*A37 -> 0
F38: =F36+F37 -> 1784633.5
F39: =F38/F3 -> 223079.19

Sheet entibado en zanja 
A1: SUMINISTRO, COLOCACIÓN Y RETIRO DE ENTIBADO EN ZANJA
A2: EQUIPOS | B2: CANT | C2: REND/DIA | D2: TARIFA/DIA | E2: VR.PARCIAL | F2: M2
F3: 330
A4: Llave de Impacto dia | B4: 1 | C4: 14 | D4: =IFERROR(VLOOKUP(A4,[1]!TablaEquipos[#Data],2,FALSE),0) -> 5000 | E4: =B4*C4*D4 -> 70000
A5: barra | B5: 2 | C5: 14 | D5: =IFERROR(VLOOKUP(A5,[1]!TablaEquipos[#Data],2,FALSE),0) -> 1500 | E5: =B5*C5*D5 -> 42000
A6: pala | B6: 4 | C6: 14 | D6: =IFERROR(VLOOKUP(A6,[1]!TablaEquipos[#Data],2,FALSE),0) -> 700 | E6: =B6*C6*D6 -> 39200
A7: Planta electrica 7,5 kwa | B7: 1 | C7: 14 | D7: =IFERROR(VLOOKUP(A7,[1]!TablaEquipos[#Data],2,FALSE),0) -> 40000 | E7: =B7*C7*D7 -> 560000
A8: Reflectores dia | B8: 3 | C8: 14 | D8: =IFERROR(VLOOKUP(A8,[1]!TablaEquipos[#Data],2,FALSE),0) -> 25000 | E8: =B8*C8*D8 -> 1050000
A9: Entibado metalico 4x4x2 | B9: 4 | D9: 15000000 | E9: =B9*D9 -> 60000000
A10: paladraga | B10: 2 | C10: 14 | D10: =IFERROR(VLOOKUP(A10,[1]!TablaEquipos[#Data],2,FALSE),0) -> 1500 | E10: =B10*C10*D10 -> 42000
A11: Pistola de Impacto dia | B11: 1 | C11: 14 | D11: =IFERROR(VLOOKUP(A11,[1]!TablaEquipos[#Data],2,FALSE),0) -> 50000 | E11: =B11*C11*D11 -> 700000
A12: Arnés de seguridad | B12: 6 | C12: 14 | D12: =IFERROR(VLOOKUP(A12,[1]!TablaEquipos[#Data],2,FALSE),0) -> 0 | E12: =B12*C12*D12 -> 0
A13: Eslingas/aparejos certificados 3" x 4" | B13: 4 | C13: 1 | D13: =IFERROR(VLOOKUP(A13,[1]!TablaEquipos[#Data],2,FALSE),0) -> 0 | E13: =B13*C13*D13 -> 0
A14: Grillete 7/8 | B14: 2 | C14: 1 | D14: =IFERROR(VLOOKUP(A14,[1]!TablaEquipos[#Data],2,FALSE),0) -> 5000 | E14: =B14*C14*D14 -> 10000
F15: =SUM(E4:E14) -> 62513200
A16: MATERIALES | B16: CANT | C16: REND/DIA | D16: TARIFA | E16: VR.PARCIAL
A18: Manila 1/2" | B18: 200 | D18: =IFERROR(VLOOKUP(A18,[1]!TablaMateriales[#Data],2,FALSE),0) -> 2500 | E18: =B18*D18 -> 500000
A19: Polisombra 100m | B19: 100 | D19: =IFERROR(VLOOKUP(A19,[1]!TablaMateriales[#Data],2,FALSE),0) -> 12000 | E19: =B19*D19 -> 1200000
A20: Rollo Pita polipropileno | B20: 1 | D20: =IFERROR(VLOOKUP(A20,[1]!TablaMateriales[#Data],2,FALSE),0) -> 35000 | E20: =B20*D20 -> 35000
D21: =IFERROR(VLOOKUP(A21,[1]!TablaMateriales[#Data],2,FALSE),0) -> 0 | E21: =B21*D21 -> 0
D22: =IFERROR(VLOOKUP(A22,[1]!TablaMateriales[#Data],2,FALSE),0) -> 0 | E22: =B22*D22 -> 0
D23: =IFERROR(VLOOKUP(A23,[1]!TablaMateriales[#Data],2,FALSE),0) -> 0 | E23: =B23*D23 -> 0
D24: =IFERROR(VLOOKUP(A24,[1]!TablaMateriales[#Data],2,FALSE),0) -> 0 | E24: =B24*D24 -> 0
D25: =IFERROR(VLOOKUP(A25,[1]!TablaMateriales[#Data],2,FALSE),0) -> 0 | E25: =B25*D25 -> 0
D26: =IFERROR(VLOOKUP(A26,[1]!TablaMateriales[#Data],2,FALSE),0) -> 0
F27: =SUM(E17:E26) -> 1735000
A28: MANO DE OBRA | B28: CANT | C28: REND/DIA | D28: SALARIO | E28: VR.PARCIAL
A29: Capataz | B29: 1 | C29: 25 | D29: ='tabla salarial'!AS4 -> 555393.74 | E29: =B29*C29*D29 -> 13884844
A30: Hse | B30: 1 | C30: 25 | D30: ='tabla salarial'!AS4 -> 555393.74 | E30: =B30*C30*D30 -> 13884844
A31: Topografo | D31: ='tabla salarial'!AS4 -> 555393.74 | E31: =B31*C31*D31 -> 0
A32: Aparejador | B32: 1 | C32: 25 | D32: ='tabla salarial'!AS7 -> 371571.33 | E32: =B32*C32*D32 -> 9289283.2
A33: Ayudante Tecnico | B33: 2 | C33: 25 | D33: ='tabla salarial'!AS8 -> 355821.88 | E33: =B33*C33*D33 -> 17791094
A34: Oficial construccion | B34: 1 | C34: 25 | D34: ='tabla salarial'!AS7 -> 371571.33 | E34: =B34*C34*D34 -> 9289283.2
A35: Auxiliar Administrativo | B35: 1 | C35: 25 | D35: ='tabla salarial'!AS8 -> 355821.88 | E35: =B35*C35*D35 -> 8895546.9
A36: Auxiliar civil | B36: 3 | C36: 25 | D36: ='tabla salarial'!AS9 -> 382109.06 | E36: =B36*C36*D36 -> 28658180
A37: 3 | F37: =SUM(E29:E36) -> 1.0169307e+08
A38: TRANSPORTE | B38: CANT | C38: REND/DIA | D38: TARIFA | E38: VR.PARCIAL
A39: Camión doble cabina | B39: 1 | C39: 14 | D39: =IFERROR(VLOOKUP(A39,[1]!TablaTransporte[#Data],2,FALSE),0) -> 550000 | E39: =B39*C39*D39 -> 7700000
A40: Retroexcavadora de oruga | B40: 1 | C40: 12 | D40: =IFERROR(VLOOKUP(A40,[1]!TablaTransporte[#Data],2,FALSE),0) -> 322000 | E40: =B40*C40*D40 -> 3864000
A41: Transporte de equipo oruga | B41: 1 | C41: 6 | D41: =IFERROR(VLOOKUP(A41,[1]!TablaTransporte[#Data],2,FALSE),0) -> 4500000 | E41: =B41*C41*D41 -> 27000000
A42: Buseta Acpm | B42: 1 | C42: 20 | D42: =IFERROR(VLOOKUP(A42,[1]!TablaTransporte[#Data],2,FALSE),0) -> 600000
F43: =SUM(E39:E42) -> 38564000
F44: =F15+F27+F37+F43 -> 2.0450527e+08
F45: =F44*A45 -> 0
F46: =F44+F45 -> 2.0450527e+08
F47: =F46*A47 -> 0
F48: =F46+F47 -> 2.0450527e+08
F49: =F48/F3 -> 619712.95

Sheet construción de gaviones
A1: CONSTRUCIÓ DE GAVIONES EN PIEDRA
A2: EQUIPOS | B2: CANT | C2: REND/DIA | D2: TARIFA/DIA | E2: VR.PARCIAL | F2: M3
F3: 7
A4: Alicate universal | B4: 1 | C4: 3 | D4: =IFERROR(VLOOKUP(A4,[1]!TablaEquipos[#Data],2,FALSE),0) -> 500 | E4: =B4*C4*D4 -> 1500
A5: Alicate diablo | B5: 1 | C5: 3 | D5: =IFERROR(VLOOKUP(A5,[1]!TablaEquipos[#Data],2,FALSE),0) -> 500 | E5: =B5*C5*D5 -> 1500
A6: Nivel torpedo | B6: 1 | C6: 3 | D6: =IFERROR(VLOOKUP(A6,[1]!TablaEquipos[#Data],2,FALSE),0) -> 1000 | E6: =B6*C6*D6 -> 3000
A7: Codal Aluminio 3 m | B7: 1 | C7: 3 | D7: =IFERROR(VLOOKUP(A7,[1]!TablaEquipos[#Data],2,FALSE),0) -> 3000 | E7: =B7*C7*D7 -> 9000
A8: Palín | B8: 2 | C8: 3 | D8: =IFERROR(VLOOKUP(A8,[1]!TablaEquipos[#Data],2,FALSE),0) -> 700 | E8: =B8*C8*D8 -> 4200
A9: Carretilla | B9: 6 | C9: 3 | D9: =IFERROR(VLOOKUP(A9,[1]!TablaEquipos[#Data],2,FALSE),0) -> 1500 | E9: =B9*C9*D9 -> 27000
A10: Martillo | B10: 1 | C10: 3 | D10: =IFERROR(VLOOKUP(A10,[1]!TablaEquipos[#Data],2,FALSE),0) -> 700 | E10: =B10*C10*D10 -> 2100
A11: tenaza/cizalla para alambre | B11: 1 | C11: 3 | D11: =IFERROR(VLOOKUP(A11,[1]!TablaEquipos[#Data],2,FALSE),0) -> 1000 | E11: =B11*C11*D11 -> 3000
D12: =IFERROR(VLOOKUP(A12,[1]!TablaEquipos[#Data],2,FALSE),0) -> 0 | E12: =B12*C12*D12 -> 0
D13: =IFERROR(VLOOKUP(A13,[1]!TablaEquipos[#Data],2,FALSE),0) -> 0
D14: =IFERROR(VLOOKUP(A14,[1]!TablaEquipos[#Data],2,FALSE),0) -> 0
D15: =IFERROR(VLOOKUP(A15,[1]!TablaEquipos[#Data],2,FALSE),0) -> 0
D16: =IFERROR(VLOOKUP(A16,[1]!TablaEquipos[#Data],2,FALSE),0) -> 0
D17: =IFERROR(VLOOKUP(A17,[1]!TablaEquipos[#Data],2,FALSE),0) -> 0
D18: =IFERROR(VLOOKUP(A18,[1]!TablaEquipos[#Data],2,FALSE),0) -> 0
F19: =SUM(E4:E18) -> 51300
A20: MATERIALES | B20: CANT | C20: REND/DIA | D20: TARIFA | E20: VR.PARCIAL
A21: Alambre Galvanizado 14 - kilo | B21: 5 | D21: =IFERROR(VLOOKUP(A21,[1]!TablaMateriales[#Data],2,FALSE),0) -> 14000 | E21: =B21*D21 -> 70000
A22: malla de gaviones 2x1x1 | B22: 8 | D22: =IFERROR(VLOOKUP(A22,[1]!TablaMateriales[#Data],2,FALSE),0) -> 123700 | E22: =B22*D22 -> 989600
A23: Piedra Filtro 3" maximo tamaño | B23: 8 | D23: =IFERROR(VLOOKUP(A23,[1]!TablaMateriales[#Data],2,FALSE),0) -> 53000 | E23: =B23*D23 -> 424000
A24: Listón de madera 2 x 1 x 3 | B24: 8 | D24: =IFERROR(VLOOKUP(A24,[1]!TablaMateriales[#Data],2,FALSE),0) -> 20000 | E24: =B24*D24 -> 160000
A25: Polisombra 100m | B25: 10 | D25: =IFERROR(VLOOKUP(A25,[1]!TablaMateriales[#Data],2,FALSE),0) -> 12000 | E25: =B25*D25 -> 120000
A26: Geotextil m2 | B26: 14 | D26: =IFERROR(VLOOKUP(A26,[1]!TablaMateriales[#Data],2,FALSE),0) -> 4300 | E26: =B26*D26 -> 60200
D27: =IFERROR(VLOOKUP(A27,[1]!TablaMateriales[#Data],2,FALSE),0) -> 0
D28: =IFERROR(VLOOKUP(A28,[1]!TablaMateriales[#Data],2,FALSE),0) -> 0
F29: =SUM(E21:E28) -> 1823800
A30: MANO DE OBRA | B30: CANT | C30: REND/DIA | D30: SALARIO | E30: VR.PARCIAL
A31: Capataz | B31: 1 | C31: 3.79 | D31: ='tabla salarial'!AS4 -> 555393.74 | E31: =B31*C31*D31 -> 2104942.3
A32: Hse | B32: 1 | C32: 3.79 | D32: ='tabla salarial'!AS4 -> 555393.74 | E32: =B32*C32*D32 -> 2104942.3
A33: Topografo | D33: ='tabla salarial'!AS4 -> 555393.74 | E33: =B33*C33*D33 -> 0
A34: Cadenero 1 | D34: ='tabla salarial'!AS6 -> 407197.8 | E34: =B34*C34*D34 -> 0
A35: Andamiero | D35: ='tabla salarial'!AS6 -> 407197.8 | E35: =B35*C35*D35 -> 0
A36: Oficial construccion | B36: 2 | C36: 3.79 | D36: ='tabla salarial'!AS7 -> 371571.33 | E36: =B36*C36*D36 -> 2816510.7
A37: Auxiliar Administrativo | B37: 1 | C37: 3.79 | D37: ='tabla salarial'!AS8 -> 355821.88 | E37: =B37*C37*D37 -> 1348564.9
A38: Auxiliar civil | B38: 6 | C38: 3.79 | D38: ='tabla salarial'!AS9 -> 382109.06 | E38: =B38*C38*D38 -> 8689160
F39: =SUM(E31:E38) -> 17064120
A40: TRANSPORTE | B40: CANT | C40: REND/DIA | D40: TARIFA | E40: VR.PARCIAL
A41: Camión doble cabina | B41: 1 | C41: 1 | D41: =IFERROR(VLOOKUP(A41,[1]!TablaTransporte[#Data],2,FALSE),0) -> 550000 | E41: =B41*C41*D41 -> 550000
A42: Volqueta de 14 m³ | B42: 0.5 | C42: 2 | D42: =IFERROR(VLOOKUP(A42,[1]!TablaTransporte[#Data],2,FALSE),0) -> 1350000 | E42: =B42*C42*D42 -> 1350000
A43: Buseta Acpm | B43: 1 | C43: 3 | D43: =IFERROR(VLOOKUP(A43,[1]!TablaTransporte[#Data],2,FALSE),0) -> 600000 | E43: =B43*C43*D43 -> 1800000
D44: =IFERROR(VLOOKUP(A44,[1]!TablaTransporte[#Data],2,FALSE),0) -> 0
F45: =SUM(E41:E44) -> 3700000
F46: =F19+F29+F39+F45 -> 22639220
F47: =F46*A47 -> 0
F48: =F46+F47 -> 22639220
F49: =F48*A49 -> 0
F50: =F48+F49 -> 22639220
F51: =F50/F3 -> 3234174.3

Sheet gaviones en sacos 
A1: CONSTRUCCIÓN DE GAVIONES EN SACOS, SUELO-CEMENTO
A2: EQUIPOS | B2: CANT | C2: REND/DIA | D2: TARIFA/DIA | E2: VR.PARCIAL | F2: M3
F3: 9
A4: Palín | B4: 2 | C4: 4 | D4: =IFERROR(VLOOKUP(A4,[1]!TablaEquipos[#Data],2,FALSE),0) -> 700 | E4: =B4*C4*D4 -> 5600
A5: Buldron | B5: 1 | C5: 4 | D5: =IFERROR(VLOOKUP(A5,[1]!TablaEquipos[#Data],2,FALSE),0) -> 5000 | E5: =B5*C5*D5 -> 20000
A6: Pala | B6: 2 | C6: 4 | D6: =IFERROR(VLOOKUP(A6,[1]!TablaEquipos[#Data],2,FALSE),0) -> 700 | E6: =B6*C6*D6 -> 5600
A7: Pisones manuales | B7: 4 | C7: 4 | D7: =IFERROR(VLOOKUP(A7,[1]!TablaEquipos[#Data],2,FALSE),0) -> 700 | E7: =B7*C7*D7 -> 11200
A8: Aguja Capotera | B8: 3 | C8: 4 | D8: =IFERROR(VLOOKUP(A8,[1]!TablaEquipos[#Data],2,FALSE),0) -> 1000 | E8: =B8*C8*D8 -> 12000
A9: Alicate universal | B9: 1 | C9: 4 | D9: =IFERROR(VLOOKUP(A9,[1]!TablaEquipos[#Data],2,FALSE),0) -> 500 | E9: =B9*C9*D9 -> 2000
A10: Alicate diablo | B10: 1 | C10: 4 | D10: =IFERROR(VLOOKUP(A10,[1]!TablaEquipos[#Data],2,FALSE),0) -> 500 | E10: =B10*C10*D10 -> 2000
A11: Nivel torpedo | B11: 1 | C11: 4 | D11: =IFERROR(VLOOKUP(A11,[1]!TablaEquipos[#Data],2,FALSE),0) -> 1000 | E11: =B11*C11*D11 -> 4000
A12: Codal Aluminio 3 m | B12: 1 | C12: 4 | D12: =IFERROR(VLOOKUP(A12,[1]!TablaEquipos[#Data],2,FALSE),0) -> 3000 | E12: =B12*C12*D12 -> 12000
A13: Palín | B13: 2 | C13: 4 | D13: =IFERROR(VLOOKUP(A13,[1]!TablaEquipos[#Data],2,FALSE),0) -> 700 | E13: =B13*C13*D13 -> 5600
A14: Carretilla | B14: 5 | C14: 4 | D14: =IFERROR(VLOOKUP(A14,[1]!TablaEquipos[#Data],2,FALSE),0) -> 1500 | E14: =B14*C14*D14 -> 30000
A15: Martillo | B15: 1 | C15: 4 | D15: =IFERROR(VLOOKUP(A15,[1]!TablaEquipos[#Data],2,FALSE),0) -> 700 | E15: =B15*C15*D15 -> 2800
... A18: Balde concretero | B18: 5 | C18: 4 | D18: =IFERROR(VLOOKUP(A18,[1]!TablaEquipos[#Data],2,FALSE),0) -> 500 | E18: =B18*C18*D18 -> 10000
D19: =IFERROR(VLOOKUP(A19,[1]!TablaEquipos[#Data],2,FALSE),0) -> 0
D20: =IFERROR(VLOOKUP(A20,[1]!TablaEquipos[#Data],2,FALSE),0) -> 0
D21: =IFERROR(VLOOKUP(A21,[1]!TablaEquipos[#Data],2,FALSE),0) -> 0
F22: =SUM(E4:E21) -> 132400
A23: MATERIALES | B23: CANT | C23: REND/DIA | D23: TARIFA | E23: VR.PARCIAL
A24: Sacos de polipropileno | B24: 440 | D24: =IFERROR(VLOOKUP(A24,[1]!TablaMateriales[#Data],2,FALSE),0) -> 1200 | E24: =B24*D24 -> 528000
A25: Material seleccionado para relleno | B25: 16 | D25: =IFERROR(VLOOKUP(A25,[1]!TablaMateriales[#Data],2,FALSE),0) -> 56327 | E25: =B25*D25 -> 901232
A26: Rollo Pita polipropileno | B26: 3 | D26: =IFERROR(VLOOKUP(A26,[1]!TablaMateriales[#Data],2,FALSE),0) -> 35000 | E26: =B26*D26 -> 105000
D27: =IFERROR(VLOOKUP(A27,[1]!TablaMateriales[#Data],2,FALSE),0) -> 0 | E27: =B27*D27 -> 0
A28: malla de gaviones 2x1x1 | B28: 5 | D28: =IFERROR(VLOOKUP(A28,[1]!TablaMateriales[#Data],2,FALSE),0) -> 123700 | E28: =B28*D28 -> 618500
A29: Alambre Galvanizado 14 - kilo | B29: 6 | D29: =IFERROR(VLOOKUP(A29,[1]!TablaMateriales[#Data],2,FALSE),0) -> 14000 | E29: =B29*D29 -> 84000
A30: Geotextil m2 | B30: 10 | D30: =IFERROR(VLOOKUP(A30,[1]!TablaMateriales[#Data],2,FALSE),0) -> 4300 | E30: =B30*D30 -> 43000
A31: Cemento 50 kl | B31: 10 | D31: =IFERROR(VLOOKUP(A31,[1]!TablaMateriales[#Data],2,FALSE),0) -> 38000 | E31: =B31*D31 -> 380000
A32: Agua m3 | B32: 2 | D32: =IFERROR(VLOOKUP(A32,[1]!TablaMateriales[#Data],2,FALSE),0) -> 6000 | E32: =B32*D32 -> 12000
A33: Plastico negro | B33: 20 | D33: =IFERROR(VLOOKUP(A33,[1]!TablaMateriales[#Data],2,FALSE),0) -> 9500 | E33: =B33*D33 -> 190000
D34: =IFERROR(VLOOKUP(A34,[1]!TablaMateriales[#Data],2,FALSE),0) -> 0 | E34: =B34*D34 -> 0
D35: =IFERROR(VLOOKUP(A35,[1]!TablaMateriales[#Data],2,FALSE),0) -> 0 | E35: =B35*D35 -> 0
D36: =IFERROR(VLOOKUP(A36,[1]!TablaMateriales[#Data],2,FALSE),0) -> 0
D37: =IFERROR(VLOOKUP(A37,[1]!TablaMateriales[#Data],2,FALSE),0) -> 0
D38: =IFERROR(VLOOKUP(A38,[1]!TablaMateriales[#Data],2,FALSE),0) -> 0
D39: =IFERROR(VLOOKUP(A39,[1]!TablaMateriales[#Data],2,FALSE),0) -> 0
D40: =IFERROR(VLOOKUP(A40,[1]!TablaMateriales[#Data],2,FALSE),0) -> 0
F41: =SUM(E24:E40) -> 2861732
A42: MANO DE OBRA | B42: CANT | C42: REND/DIA | D42: SALARIO | E42: VR.PARCIAL
A43: Capataz | B43: 1 | C43: 3 | D43: ='tabla salarial'!AS4 -> 555393.74 | E43: =B43*C43*D43 -> 1666181.2
A44: Hse | B44: 1 | C44: 3 | D44: ='tabla salarial'!AS4 -> 555393.74 | E44: =B44*C44*D44 -> 1666181.2
A45: Topografo | D45: ='tabla salarial'!AS4 -> 555393.74 | E45: =B45*C45*D45 -> 0
A46: Cadenero 1 | D46: ='tabla salarial'!AS6 -> 407197.8 | E46: =B46*C46*D46 -> 0
A47: Andamiero | D47: ='tabla salarial'!AS6 -> 407197.8 | E47: =B47*C47*D47 -> 0
A48: Oficial construccion | B48: 1 | C48: 6 | D48: ='tabla salarial'!AS7 -> 371571.33 | E48: =B48*C48*D48 -> 2229428
A49: Auxiliar Administrativo | B49: 1 | C49: 3 | D49: ='tabla salarial'!AS8 -> 355821.88 | E49: =B49*C49*D49 -> 1067465.6
A50: Auxiliar civil | B50: 2 | C50: 6 | D50: ='tabla salarial'!AS9 -> 382109.06 | E50: =B50*C50*D50 -> 4585308.7
F51: =SUM(E43:E50) -> 11214565
A52: TRANSPORTE | B52: CANT | C52: REND/DIA | D52: TARIFA | E52: VR.PARCIAL
A54: Camión doble cabina | B54: 0.5 | C54: 1 | D54: =IFERROR(VLOOKUP(A54,[1]!TablaTransporte[#Data],2,FALSE),0) -> 550000 | E54: =B54*C54*D54 -> 275000
A55: Buseta Acpm | B55: 1 | C55: 8 | D55: =IFERROR(VLOOKUP(A55,[1]!TablaTransporte[#Data],2,FALSE),0) -> 600000 | E55: =B55*C55*D55 -> 4800000
A56: Volqueta de 14 m³ | B56: 1 | C56: 1 | D56: =IFERROR(VLOOKUP(A56,[1]!TablaTransporte[#Data],2,FALSE),0) -> 1350000 | E56: =B56*C56*D56 -> 1350000
F57: =SUM(E53:E56) -> 6425000
F58: =F22+F41+F51+F57 -> 20633697
F59: =F58*A59 -> 0
F60: =F58+F59 -> 20633697
F61: =F60*A61 -> 0
F62: =F60+F61 -> 20633697
F63: =F62/F3 -> 2292633

Sheet demolición de gaviones
A1: DEMOLICIÓN DE GAVIONES
A2: EQUIPOS | B2: CANT | C2: REND/DIA | D2: TARIFA/DIA | E2: VR.PARCIAL | F2: M3
F3: 12
A4: Alicate universal | B4: 1 | C4: 2.5 | D4: =IFERROR(VLOOKUP(A4,[1]!TablaEquipos[#Data],2,FALSE),0) -> 500 | E4: =B4*C4*D4 -> 1250
A5: tenaza/cizalla para alambre | B5: 1 | C5: 2.5 | D5: =IFERROR(VLOOKUP(A5,[1]!TablaEquipos[#Data],2,FALSE),0) -> 1000 | E5: =B5*C5*D5 -> 2500
A6: Alicate diablo | B6: 1 | C6: 2.5 | D6: =IFERROR(VLOOKUP(A6,[1]!TablaEquipos[#Data],2,FALSE),0) -> 500 | E6: =B6*C6*D6 -> 1250
A7: Barra | B7: 1 | C7: 2.5 | D7: =IFERROR(VLOOKUP(A7,[1]!TablaEquipos[#Data],2,FALSE),0) -> 1500 | E7: =B7*C7*D7 -> 3750
A8: Carretilla | B8: 6 | C8: 2.5 | D8: =IFERROR(VLOOKUP(A8,[1]!TablaEquipos[#Data],2,FALSE),0) -> 1500 | E8: =B8*C8*D8 -> 22500
A9: Machete | B9: 1 | C9: 2.5 | D9: =IFERROR(VLOOKUP(A9,[1]!TablaEquipos[#Data],2,FALSE),0) -> 1500 | E9: =B9*C9*D9 -> 3750
A10: Avisos de seguridad | B10: 10 | C10: 2.5 | D10: =IFERROR(VLOOKUP(A10,[1]!TablaEquipos[#Data],2,FALSE),0) -> 1000 | E10: =B10*C10*D10 -> 25000
A11: Colombina | B11: 8 | C11: 2.5 | D11: =IFERROR(VLOOKUP(A11,[1]!TablaEquipos[#Data],2,FALSE),0) -> 1000 | E11: =B11*C11*D11 -> 20000
D12: =IFERROR(VLOOKUP(A12,[1]!TablaEquipos[#Data],2,FALSE),0) -> 0
D13: =IFERROR(VLOOKUP(A13,[1]!TablaEquipos[#Data],2,FALSE),0) -> 0
D14: =IFERROR(VLOOKUP(A14,[1]!TablaEquipos[#Data],2,FALSE),0) -> 0
D15: =IFERROR(VLOOKUP(A15,[1]!TablaEquipos[#Data],2,FALSE),0) -> 0
D16: =IFERROR(VLOOKUP(A16,[1]!TablaEquipos[#Data],2,FALSE),0) -> 0
D17: =IFERROR(VLOOKUP(A17,[1]!TablaEquipos[#Data],2,FALSE),0) -> 0
F18: =SUM(E4:E17) -> 80000
A19: MATERIALES | B19: CANT | C19: REND/DIA | D19: TARIFA | E19: VR.PARCIAL
A20: Cinta de seguridad amarilla/negra x 500 | B20: 1 | D20: =IFERROR(VLOOKUP(A20,[1]!TablaMateriales[#Data],2,FALSE),0) -> 55000 | E20: =B20*D20 -> 55000
A21: Sacos de polipropileno | B21: 30 | D21: =IFERROR(VLOOKUP(A21,[1]!TablaMateriales[#Data],2,FALSE),0) -> 1200 | E21: =B21*D21 -> 36000
D22: =IFERROR(VLOOKUP(A22,[1]!TablaMateriales[#Data],2,FALSE),0) -> 0 | E22: =B22*D22 -> 0
D23: =IFERROR(VLOOKUP(A23,[1]!TablaMateriales[#Data],2,FALSE),0) -> 0 | E23: =B23*D23 -> 0
D24: =IFERROR(VLOOKUP(A24,[1]!TablaMateriales[#Data],2,FALSE),0) -> 0 | E24: =B24*D24 -> 0
D25: =IFERROR(VLOOKUP(A25,[1]!TablaMateriales[#Data],2,FALSE),0) -> 0 | E25: =B25*D25 -> 0
D26: =IFERROR(VLOOKUP(A26,[1]!TablaMateriales[#Data],2,FALSE),0) -> 0 | E26: =B26*D26 -> 0
D27: =IFERROR(VLOOKUP(A27,[1]!TablaMateriales[#Data],2,FALSE),0) -> 0 | E27: =B27*D27 -> 0
D28: =IFERROR(VLOOKUP(A28,[1]!TablaMateriales[#Data],2,FALSE),0) -> 0 | E28: =B28*D28 -> 0
D29: =IFERROR(VLOOKUP(A29,[1]!TablaMateriales[#Data],2,FALSE),0) -> 0 | E29: =B29*D29 -> 0
D30: =IFERROR(VLOOKUP(A30,[1]!TablaMateriales[#Data],2,FALSE),0) -> 0 | E30: =B30*D30 -> 0
D31: =IFERROR(VLOOKUP(A31,[1]!TablaMateriales[#Data],2,FALSE),0) -> 0 | E31: =B31*D31 -> 0
D32: =IFERROR(VLOOKUP(A32,[1]!TablaMateriales[#Data],2,FALSE),0) -> 0
D33: =IFERROR(VLOOKUP(A33,[1]!TablaMateriales[#Data],2,FALSE),0) -> 0
D34: =IFERROR(VLOOKUP(A34,[1]!TablaMateriales[#Data],2,FALSE),0) -> 0
D35: =IFERROR(VLOOKUP(A35,[1]!TablaMateriales[#Data],2,FALSE),0) -> 0
D36: =IFERROR(VLOOKUP(A36,[1]!TablaMateriales[#Data],2,FALSE),0) -> 0
F37: =SUM(E20:E36) -> 91000
A38: MANO DE OBRA | B38: CANT | C38: REND/DIA | D38: SALARIO | E38: VR.PARCIAL
A39: Capataz | B39: 1 | C39: 1.5 | D39: ='tabla salarial'!AS4 -> 555393.74 | E39: =B39*C39*D39 -> 833090.61
A40: Hse | B40: 1 | C40: 2.8 | D40: ='tabla salarial'!AS4 -> 555393.74 | E40: =B40*C40*D40 -> 1555102.5
A41: Topografo | D41: ='tabla salarial'!AS4 -> 555393.74 | E41: =B41*C41*D41 -> 0
A42: Cadenero 1 | D42: ='tabla salarial'!AS6 -> 407197.8 | E42: =B42*C42*D42 -> 0
A43: Andamiero | D43: ='tabla salarial'!AS6 -> 407197.8 | E43: =B43*C43*D43 -> 0
A44: Oficial construccion | B44: 1 | C44: 2.8 | D44: ='tabla salarial'!AS7 -> 371571.33 | E44: =B44*C44*D44 -> 1040399.7
A45: Auxiliar Administrativo | B45: 1 | C45: 1.5 | D45: ='tabla salarial'!AS8 -> 355821.88 | E45: =B45*C45*D45 -> 533732.81
A46: Auxiliar civil | B46: 2 | C46: 2.8 | D46: ='tabla salarial'!AS9 -> 382109.06 | E46: =B46*C46*D46 -> 2139810.7
F47: =SUM(E39:E46) -> 6102136.4
A48: TRANSPORTE | B48: CANT | C48: REND/DIA | D48: TARIFA | E48: VR.PARCIAL
A50: minicargador | B50: 1 | D50: =IFERROR(VLOOKUP(A50,[1]!TablaTransporte[#Data],2,FALSE),0) -> 840000 | E50: =B50*C50*D50 -> 0
A51: Volqueta de 14 m³ | B51: 1 | C51: 0.5 | D51: =IFERROR(VLOOKUP(A51,[1]!TablaTransporte[#Data],2,FALSE),0) -> 1350000 | E51: =B51*C51*D51 -> 675000
A52: Camión doble cabina | B52: 1 | D52: =IFERROR(VLOOKUP(A52,[1]!TablaTransporte[#Data],2,FALSE),0) -> 550000 | E52: =B52*C52*D52 -> 0
A53: Buseta Acpm | B53: 1 | C53: 3 | D53: =IFERROR(VLOOKUP(A53,[1]!TablaTransporte[#Data],2,FALSE),0) -> 600000 | E53: =B53*C53*D53 -> 1800000
F54: =SUM(E50:E53) -> 2475000
F55: =F18+F37+F47+F54 -> 8748136.4
F56: =F55*A56 -> 0
F57: =F55+F56 -> 8748136.4
F58: =F57*A58 -> 0
F59: =F57+F58 -> 8748136.4
F60: =F59/F3 -> 729011.36

Sheet construcción de diques
A1: CONSTRUCIÓN DE DIQUES EN SACOS DE POLIPROPILENO
A2: EQUIPOS | B2: CANT | C2: REND/DIA | D2: TARIFA/DIA | E2: VR.PARCIAL | F2: M3
F3: 6
A4: Machete | B4: 2 | C4: 2 | D4: =IFERROR(VLOOKUP(A4,[1]!TablaEquipos[#Data],2,FALSE),0) -> 1500 | E4: =B4*C4*D4 -> 6000
A5: Martillo | B5: 1 | D5: =IFERROR(VLOOKUP(A5,[1]!TablaEquipos[#Data],2,FALSE),0) -> 700 | E5: =B5*C5*D5 -> 0
A6: Pala | B6: 4 | C6: 2 | D6: =IFERROR(VLOOKUP(A6,[1]!TablaEquipos[#Data],2,FALSE),0) -> 700 | E6: =B6*C6*D6 -> 5600
A7: Palín | B7: 2 | C7: 2 | D7: =IFERROR(VLOOKUP(A7,[1]!TablaEquipos[#Data],2,FALSE),0) -> 700 | E7: =B7*C7*D7 -> 2800
A8: Azadon | B8: 2 | C8: 2 | D8: =IFERROR(VLOOKUP(A8,[1]!TablaEquipos[#Data],2,FALSE),0) -> 700 | E8: =B8*C8*D8 -> 2800
A9: Barra | B9: 4 | C9: 2 | D9: =IFERROR(VLOOKUP(A9,[1]!TablaEquipos[#Data],2,FALSE),0) -> 1500 | E9: =B9*C9*D9 -> 12000
A10: Pica | B10: 2 | C10: 2 | D10: =IFERROR(VLOOKUP(A10,[1]!TablaEquipos[#Data],2,FALSE),0) -> 700 | E10: =B10*C10*D10 -> 2800
A11: Carretilla | B11: 3 | C11: 2 | D11: =IFERROR(VLOOKUP(A11,[1]!TablaEquipos[#Data],2,FALSE),0) -> 1500 | E11: =B11*C11*D11 -> 9000
A12: Pisones manuales | B12: 3 | C12: 2 | D12: =IFERROR(VLOOKUP(A12,[1]!TablaEquipos[#Data],2,FALSE),0) -> 700 | E12: =B12*C12*D12 -> 4200
A13: Aguja Capotera | B13: 3 | C13: 2 | D13: =IFERROR(VLOOKUP(A13,[1]!TablaEquipos[#Data],2,FALSE),0) -> 1000 | E13: =B13*C13*D13 -> 6000
A14: Flexómetro | B14: 2 | C14: 2 | D14: =IFERROR(VLOOKUP(A14,[1]!TablaEquipos[#Data],2,FALSE),0) -> 500 | E14: =B14*C14*D14 -> 2000
D15: =IFERROR(VLOOKUP(A15,[1]!TablaEquipos[#Data],2,FALSE),0) -> 0
D16: =IFERROR(VLOOKUP(A16,[1]!TablaEquipos[#Data],2,FALSE),0) -> 0
D17: =IFERROR(VLOOKUP(A17,[1]!TablaEquipos[#Data],2,FALSE),0) -> 0
D18: =IFERROR(VLOOKUP(A18,[1]!TablaEquipos[#Data],2,FALSE),0) -> 0
D19: =IFERROR(VLOOKUP(A19,[1]!TablaEquipos[#Data],2,FALSE),0) -> 0
D20: =IFERROR(VLOOKUP(A20,[1]!TablaEquipos[#Data],2,FALSE),0) -> 0
F21: =SUM(E4:E20) -> 53200
A22: MATERIALES | B22: CANT | C22: REND/DIA | D22: TARIFA | E22: VR.PARCIAL
D23: =IFERROR(VLOOKUP(A23,[1]!TablaMateriales[#Data],2,FALSE),0) -> 0 | E23: =B23*D23 -> 0
A24: Listón de madera 2 x 1 x 3 | B24: 40 | D24: =IFERROR(VLOOKUP(A24,[1]!TablaMateriales[#Data],2,FALSE),0) -> 20000 | E24: =B24*D24 -> 800000
A25: Cal | D25: =IFERROR(VLOOKUP(A25,[1]!TablaMateriales[#Data],2,FALSE),0) -> 50000 | E25: =B25*D25 -> 0
A26: Nailon de color | D26: =IFERROR(VLOOKUP(A26,[1]!TablaMateriales[#Data],2,FALSE),0) -> 0 | E26: =B26*D26 -> 0
A27: Puntilla de 2,5" | D27: =IFERROR(VLOOKUP(A27,[1]!TablaMateriales[#Data],2,FALSE),0) -> 9500 | E27: =B27*D27 -> 0
A28: Puntilla de 3,5" | D28: =IFERROR(VLOOKUP(A28,[1]!TablaMateriales[#Data],2,FALSE),0) -> 9500 | E28: =B28*D28 -> 0
A29: Clavo de acero de 3" | D29: =IFERROR(VLOOKUP(A29,[1]!TablaMateriales[#Data],2,FALSE),0) -> 15000 | E29: =B29*D29 -> 0
A30: Pintura en aerosol | D30: =IFERROR(VLOOKUP(A30,[1]!TablaMateriales[#Data],2,FALSE),0) -> 20000 | E30: =B30*D30 -> 0
A31: Cinta de seguridad amarilla/negra x 500 | B31: 0.5 | D31: =IFERROR(VLOOKUP(A31,[1]!TablaMateriales[#Data],2,FALSE),0) -> 55000 | E31: =B31*D31 -> 27500
A32: Grapa | D32: =IFERROR(VLOOKUP(A32,[1]!TablaMateriales[#Data],2,FALSE),0) -> 15900 | E32: =B32*D32 -> 0
A33: Agua m3 | B33: 1 | D33: =IFERROR(VLOOKUP(A33,[1]!TablaMateriales[#Data],2,FALSE),0) -> 6000 | E33: =B33*D33 -> 6000
A34: Rollo Pita polipropileno | B34: 3 | D34: =IFERROR(VLOOKUP(A34,[1]!TablaMateriales[#Data],2,FALSE),0) -> 35000 | E34: =B34*D34 -> 105000
A35: Sacos de polipropileno | B35: 270 | D35: =IFERROR(VLOOKUP(A35,[1]!TablaMateriales[#Data],2,FALSE),0) -> 1200 | E35: =B35*D35 -> 324000
A36: Tierra Roja | B36: 8 | D36: =IFERROR(VLOOKUP(A36,[1]!TablaMateriales[#Data],2,FALSE),0) -> 31000 | E36: =B36*D36 -> 248000
D37: =IFERROR(VLOOKUP(A37,[1]!TablaMateriales[#Data],2,FALSE),0) -> 0
D38: =IFERROR(VLOOKUP(A38,[1]!TablaMateriales[#Data],2,FALSE),0) -> 0
D39: =IFERROR(VLOOKUP(A39,[1]!TablaMateriales[#Data],2,FALSE),0) -> 0
F40: =SUM(E23:E39) -> 1510500
A41: MANO DE OBRA | B41: CANT | C41: REND/DIA | D41: SALARIO | E41: VR.PARCIAL
A42: Capataz | B42: 1 | C42: 1.8 | D42: ='tabla salarial'!AS4 -> 555393.74 | E42: =B42*C42*D42 -> 999708.73
A43: Hse | B43: 1 | C43: 1.8 | D43: ='tabla salarial'!AS4 -> 555393.74 | E43: =B43*C43*D43 -> 999708.73
A44: Topografo | B44: 1 | D44: ='tabla salarial'!AS4 -> 555393.74 | E44: =B44*C44*D44 -> 0
A45: Cadenero 1 | B45: 1.5 | D45: ='tabla salarial'!AS6 -> 407197.8 | E45: =B45*C45*D45 -> 0
A46: Andamiero | B46: 2 | D46: ='tabla salarial'!AS6 -> 407197.8 | E46: =B46*C46*D46 -> 0
A47: Oficial construccion | B47: 1 | C47: 3.6 | D47: ='tabla salarial'!AS7 -> 371571.33 | E47: =B47*C47*D47 -> 1337656.8
A48: Auxiliar Administrativo | B48: 1 | C48: 1.8 | D48: ='tabla salarial'!AS8 -> 355821.88 | E48: =B48*C48*D48 -> 640479.38
A49: Auxiliar civil | B49: 3 | C49: 3.6 | D49: ='tabla salarial'!AS9 -> 382109.06 | E49: =B49*C49*D49 -> 4126777.9
A50: 3 | F50: =SUM(E42:E49) -> 8104331.5
A51: TRANSPORTE | B51: CANT | C51: REND/DIA | D51: TARIFA | E51: VR.PARCIAL
E52: =B52*C52*D52 -> 0
A53: Acarreo por km | B53: 1 | C53: 57 | D53: =IFERROR(VLOOKUP(A53,[1]!TablaTransporte[#Data],2,FALSE),0) -> 65000 | E53: =B53*C53*D53 -> 3705000
A54: Buseta Acpm | B54: 1 | C54: 0.5 | D54: =IFERROR(VLOOKUP(A54,[1]!TablaTransporte[#Data],2,FALSE),0) -> 600000 | E54: =B54*C54*D54 -> 300000
A55: Volqueta de 14 m³ | B55: 1 | C55: 0.6 | D55: =IFERROR(VLOOKUP(A55,[1]!TablaTransporte[#Data],2,FALSE),0) -> 1350000 | E55: =B55*C55*D55 -> 810000
F56: =E53 -> 3705000
F57: =F21+F40+F50+F56 -> 13373031
F58: =F57*A58 -> 0
F59: =F57+F58 -> 13373031
F60: =F59*A60 -> 0
F61: =F59+F60 -> 13373031
F62: =F61/F3 -> 2228838.6

Sheet trinchos en madera
A1: TRINCHOS EN MADERA
A2: EQUIPOS | B2: CANT | C2: REND/DIA | D2: TARIFA/DIA | E2: VR.PARCIAL | F2: ML
F3: 4
A4: pala | B4: 2 | C4: 1.5 | D4: =IFERROR(VLOOKUP(A4,[1]!TablaEquipos[#Data],2,FALSE),0) -> 700 | E4: =B4*C4*D4 -> 2100
A5: pica | B5: 1 | C5: 1.5 | D5: =IFERROR(VLOOKUP(A5,[1]!TablaEquipos[#Data],2,FALSE),0) -> 700 | E5: =B5*C5*D5 -> 1050
A6: martillo | B6: 1 | C6: 1.5 | D6: =IFERROR(VLOOKUP(A6,[1]!TablaEquipos[#Data],2,FALSE),0) -> 700 | E6: =B6*C6*D6 -> 1050
A7: machete | B7: 1 | C7: 1.5 | D7: =IFERROR(VLOOKUP(A7,[1]!TablaEquipos[#Data],2,FALSE),0) -> 1500 | E7: =B7*C7*D7 -> 2250
A8: serrucho | B8: 1 | C8: 1.5 | D8: =IFERROR(VLOOKUP(A8,[1]!TablaEquipos[#Data],2,FALSE),0) -> 1000 | E8: =B8*C8*D8 -> 1500
A9: Flexómetro | B9: 1 | C9: 1.5 | D9: =IFERROR(VLOOKUP(A9,[1]!TablaEquipos[#Data],2,FALSE),0) -> 500 | E9: =B9*C9*D9 -> 750
A10: Nivel torpedo | B10: 1 | C10: 1.5 | D10: =IFERROR(VLOOKUP(A10,[1]!TablaEquipos[#Data],2,FALSE),0) -> 1000 | E10: =B10*C10*D10 -> 1500
A11: Alicate universal | B11: 1 | C11: 1.5 | D11: =IFERROR(VLOOKUP(A11,[1]!TablaEquipos[#Data],2,FALSE),0) -> 500 | E11: =B11*C11*D11 -> 750
A12: tenaza/cizalla para alambre | B12: 1 | C12: 1.5 | D12: =IFERROR(VLOOKUP(A12,[1]!TablaEquipos[#Data],2,FALSE),0) -> 1000 | E12: =B12*D12 -> 1000
A13: Carretilla | B13: 2 | C13: 1.5 | D13: =IFERROR(VLOOKUP(A13,[1]!TablaEquipos[#Data],2,FALSE),0) -> 1500 | E13: =B13*C13*D13 -> 4500
D14: =IFERROR(VLOOKUP(A14,[1]!TablaEquipos[#Data],2,FALSE),0) -> 0 | E14: =B14*C14*D14 -> 0
D15: =IFERROR(VLOOKUP(A15,[1]!TablaEquipos[#Data],2,FALSE),0) -> 0 | E15: =B15*C15*D15 -> 0
D16: =IFERROR(VLOOKUP(A16,[1]!TablaEquipos[#Data],2,FALSE),0) -> 0
D17: =IFERROR(VLOOKUP(A17,[1]!TablaEquipos[#Data],2,FALSE),0) -> 0
D18: =IFERROR(VLOOKUP(A18,[1]!TablaEquipos[#Data],2,FALSE),0) -> 0
D19: =IFERROR(VLOOKUP(A19,[1]!TablaEquipos[#Data],2,FALSE),0) -> 0
D20: =IFERROR(VLOOKUP(A20,[1]!TablaEquipos[#Data],2,FALSE),0) -> 0
D21: =IFERROR(VLOOKUP(A21,[1]!TablaEquipos[#Data],2,FALSE),0) -> 0
F22: =SUM(E4:E21) -> 16450
A23: MATERIALES | B23: CANT | C23: REND/DIA | D23: TARIFA | E23: VR.PARCIAL
A24: Listón de madera 2 x 4 x 3 | B24: 3 | D24: =IFERROR(VLOOKUP(A24,[1]!TablaMateriales[#Data],2,FALSE),0) -> 35000 | E24: =B24*D24 -> 105000
A25: Tabla | B25: 7 | D25: =IFERROR(VLOOKUP(A25,[1]!TablaMateriales[#Data],2,FALSE),0) -> 30000 | E25: =B25*D25 -> 210000
A26: Alambre HG calibre 14 | B26: 2 | D26: =IFERROR(VLOOKUP(A26,[1]!TablaMateriales[#Data],2,FALSE),0) -> 14000 | E26: =B26*D26 -> 28000
A27: Varilla 1/8" | B27: 2 | D27: =IFERROR(VLOOKUP(A27,[1]!TablaMateriales[#Data],2,FALSE),0) -> 0 | E27: =B27*D27 -> 0
A28: Puntilla de 2,5" | B28: 1 | D28: =IFERROR(VLOOKUP(A28,[1]!TablaMateriales[#Data],2,FALSE),0) -> 9500 | E28: =B28*D28 -> 9500
A29: Malla eslabonada vena 7 | B29: 1.5 | D29: =IFERROR(VLOOKUP(A29,[1]!TablaMateriales[#Data],2,FALSE),0) -> 195000 | E29: =B29*D29 -> 292500
A30: Geotextil m2 | B30: 2 | D30: =IFERROR(VLOOKUP(A30,[1]!TablaMateriales[#Data],2,FALSE),0) -> 4300 | E30: =B30*D30 -> 8600
D31: =IFERROR(VLOOKUP(A31,[1]!TablaMateriales[#Data],2,FALSE),0) -> 0 | E31: =B31*D31 -> 0
D32: =IFERROR(VLOOKUP(A32,[1]!TablaMateriales[#Data],2,FALSE),0) -> 0 | E32: =B32*D32 -> 0
D33: =IFERROR(VLOOKUP(A33,[1]!TablaMateriales[#Data],2,FALSE),0) -> 0 | E33: =B33*D33 -> 0
D34: =IFERROR(VLOOKUP(A34,[1]!TablaMateriales[#Data],2,FALSE),0) -> 0 | E34: =B34*D34 -> 0
D35: =IFERROR(VLOOKUP(A35,[1]!TablaMateriales[#Data],2,FALSE),0) -> 0 | E35: =B35*D35 -> 0
D36: =IFERROR(VLOOKUP(A36,[1]!TablaMateriales[#Data],2,FALSE),0) -> 0
D37: =IFERROR(VLOOKUP(A37,[1]!TablaMateriales[#Data],2,FALSE),0) -> 0
D38: =IFERROR(VLOOKUP(A38,[1]!TablaMateriales[#Data],2,FALSE),0) -> 0
D39: =IFERROR(VLOOKUP(A39,[1]!TablaMateriales[#Data],2,FALSE),0) -> 0
D40: =IFERROR(VLOOKUP(A40,[1]!TablaMateriales[#Data],2,FALSE),0) -> 0
F41: =SUM(E24:E40) -> 653600
A42: MANO DE OBRA | B42: CANT | C42: REND/DIA | D42: SALARIO | E42: VR.PARCIAL
A43: Capataz | B43: 1 | C43: 0.75 | D43: ='tabla salarial'!AS4 -> 555393.74 | E43: =B43*C43*D43 -> 416545.31
A44: Hse | B44: 1 | C44: 0.75 | D44: ='tabla salarial'!AS4 -> 555393.74 | E44: =B44*C44*D44 -> 416545.31
A45: Topografo | B45: 1 | D45: ='tabla salarial'!AS4 -> 555393.74 | E45: =B45*C45*D45 -> 0
A46: Cadenero 1 | B46: 1.5 | D46: ='tabla salarial'!AS6 -> 407197.8 | E46: =B46*C46*D46 -> 0
A47: Andamiero | B47: 2 | D47: ='tabla salarial'!AS6 -> 407197.8 | E47: =B47*C47*D47 -> 0
A48: Oficial construccion | B48: 1 | C48: 1.8 | D48: ='tabla salarial'!AS7 -> 371571.33 | E48: =B48*C48*D48 -> 668828.39
A49: Auxiliar Administrativo | B49: 1 | C49: 0.75 | D49: ='tabla salarial'!AS8 -> 355821.88 | E49: =B49*C49*D49 -> 266866.41
A50: Auxiliar civil | B50: 2 | C50: 1.8 | D50: ='tabla salarial'!AS9 -> 382109.06 | E50: =B50*C50*D50 -> 1375592.6
A51: 3 | F51: =SUM(E43:E50) -> 3144378
A52: TRANSPORTE | B52: CANT | C52: REND/DIA | D52: TARIFA | E52: VR.PARCIAL
A53: Camión doble cabina | B53: 1 | C53: 0.1 | D53: =IFERROR(VLOOKUP(A53,[1]!TablaTransporte[#Data],2,FALSE),0) -> 550000 | E53: =B53*C53*D53 -> 55000
A54: Buseta Acpm | B54: 1 | C54: 0.75 | D54: =IFERROR(VLOOKUP(A54,[1]!TablaTransporte[#Data],2,FALSE),0) -> 600000 | E54: =B54*C54*D54 -> 450000
D55: =IFERROR(VLOOKUP(A55,[1]!TablaTransporte[#Data],2,FALSE),0) -> 0
D56: =IFERROR(VLOOKUP(A56,[1]!TablaTransporte[#Data],2,FALSE),0) -> 0
F57: =E54 -> 450000
F58: =F22+F41+F51+F57 -> 4264428
F59: =F58*A59 -> 0
F60: =F58+F59 -> 4264428
F61: =F60*A61 -> 0
F62: =F60+F61 -> 4264428
F63: =F62/F3 -> 1066107

Sheet drenajes e aguas 
A1: DRENAJES DE AGUAS CON MOTOBOMBA EN EXCAVACIONES
A2: EQUIPOS | B2: CANT | C2: REND/DIA | D2: TARIFA/DIA | E2: VR.PARCIAL | F2: Hora
F3: 438
A4: Motobomba diesel 4x4 | B4: 1 | C4: 62 | D4: =IFERROR(VLOOKUP(A4,[1]!TablaEquipos[#Data],2,FALSE),0) -> 40000 | E4: =B4*C4*D4 -> 2480000
A5: Dique para Metalico | B5: 1 | C5: 62 | D5: =IFERROR(VLOOKUP(A5,[1]!TablaEquipos[#Data],2,FALSE),0) -> 1000 | E5: =B5*C5*D5 -> 62000
D6: =IFERROR(VLOOKUP(A6,[1]!TablaEquipos[#Data],2,FALSE),0) -> 0 | E6: =B6*C6*D6 -> 0
D7: =IFERROR(VLOOKUP(A7,[1]!TablaEquipos[#Data],2,FALSE),0) -> 0 | E7: =B7*C7*D7 -> 0
D8: =IFERROR(VLOOKUP(A8,[1]!TablaEquipos[#Data],2,FALSE),0) -> 0 | E8: =B8*C8*D8 -> 0
D9: =IFERROR(VLOOKUP(A9,[1]!TablaEquipos[#Data],2,FALSE),0) -> 0 | E9: =B9*C9*D9 -> 0
D10: =IFERROR(VLOOKUP(A10,[1]!TablaEquipos[#Data],2,FALSE),0) -> 0 | E10: =B10*C10*D10 -> 0
D11: =IFERROR(VLOOKUP(A11,[1]!TablaEquipos[#Data],2,FALSE),0) -> 0 | E11: =B11*C11*D11 -> 0
D12: =IFERROR(VLOOKUP(A12,[1]!TablaEquipos[#Data],2,FALSE),0) -> 0 | E12: =B12*D12 -> 0
D13: =IFERROR(VLOOKUP(A13,[1]!TablaEquipos[#Data],2,FALSE),0) -> 0 | E13: =B13*C13*D13 -> 0
D14: =IFERROR(VLOOKUP(A14,[1]!TablaEquipos[#Data],2,FALSE),0) -> 0 | E14: =B14*C14*D14 -> 0
D15: =IFERROR(VLOOKUP(A15,[1]!TablaEquipos[#Data],2,FALSE),0) -> 0 | E15: =B15*C15*D15 -> 0
D16: =IFERROR(VLOOKUP(A16,[1]!TablaEquipos[#Data],2,FALSE),0) -> 0
D17: =IFERROR(VLOOKUP(A17,[1]!TablaEquipos[#Data],2,FALSE),0) -> 0
D18: =IFERROR(VLOOKUP(A18,[1]!TablaEquipos[#Data],2,FALSE),0) -> 0
D19: =IFERROR(VLOOKUP(A19,[1]!TablaEquipos[#Data],2,FALSE),0) -> 0
D20: =IFERROR(VLOOKUP(A20,[1]!TablaEquipos[#Data],2,FALSE),0) -> 0
D21: =IFERROR(VLOOKUP(A21,[1]!TablaEquipos[#Data],2,FALSE),0) -> 0
F22: =SUM(E4:E21) -> 2542000
A23: MATERIALES | B23: CANT | C23: REND/DIA | D23: TARIFA | E23: VR.PARCIAL
D24: =IFERROR(VLOOKUP(A24,[1]!TablaMateriales[#Data],2,FALSE),0) -> 0 | E24: =B24*D24 -> 0
A25: Aceite 15w40 | B25: 1.5 | D25: =IFERROR(VLOOKUP(A25,[1]!TablaMateriales[#Data],2,FALSE),0) -> 85000 | E25: =B25*D25 -> 127500
A26: Filtro para motor T85 | B26: 3 | D26: =IFERROR(VLOOKUP(A26,[1]!TablaMateriales[#Data],2,FALSE),0) -> 22000 | E26: =B26*D26 -> 66000
A27: Acpm Galon | B27: 150 | D27: =IFERROR(VLOOKUP(A27,[1]!TablaMateriales[#Data],2,FALSE),0) -> 11500 | E27: =B27*D27 -> 1725000
A28: Yoyo para motobomba | B28: 1 | D28: =IFERROR(VLOOKUP(A28,[1]!TablaMateriales[#Data],2,FALSE),0) -> 95000 | E28: =B28*D28 -> 95000
D29: =IFERROR(VLOOKUP(A29,[1]!TablaMateriales[#Data],2,FALSE),0) -> 0 | E29: =B29*D29 -> 0
D30: =IFERROR(VLOOKUP(A30,[1]!TablaMateriales[#Data],2,FALSE),0) -> 0 | E30: =B30*D30 -> 0
D31: =IFERROR(VLOOKUP(A31,[1]!TablaMateriales[#Data],2,FALSE),0) -> 0 | E31: =B31*D31 -> 0
D32: =IFERROR(VLOOKUP(A32,[1]!TablaMateriales[#Data],2,FALSE),0) -> 0 | E32: =B32*D32 -> 0
D33: =IFERROR(VLOOKUP(A33,[1]!TablaMateriales[#Data],2,FALSE),0) -> 0 | E33: =B33*D33 -> 0
D34: =IFERROR(VLOOKUP(A34,[1]!TablaMateriales[#Data],2,FALSE),0) -> 0 | E34: =B34*D34 -> 0
D35: =IFERROR(VLOOKUP(A35,[1]!TablaMateriales[#Data],2,FALSE),0) -> 0 | E35: =B35*D35 -> 0
D36: =IFERROR(VLOOKUP(A36,[1]!TablaMateriales[#Data],2,FALSE),0) -> 0
D37: =IFERROR(VLOOKUP(A37,[1]!TablaMateriales[#Data],2,FALSE),0) -> 0
D38: =IFERROR(VLOOKUP(A38,[1]!TablaMateriales[#Data],2,FALSE),0) -> 0
D39: =IFERROR(VLOOKUP(A39,[1]!TablaMateriales[#Data],2,FALSE),0) -> 0
D40: =IFERROR(VLOOKUP(A40,[1]!TablaMateriales[#Data],2,FALSE),0) -> 0
F41: =SUM(E24:E40) -> 2013500
A42: MANO DE OBRA | B42: CANT | C42: REND/DIA | D42: SALARIO | E42: VR.PARCIAL
A43: Capataz | B43: 1 | C43: 12 | D43: ='tabla salarial'!AS4 -> 555393.74 | E43: =B43*C43*D43 -> 6664724.9
A44: Hse | B44: 1 | C44: 12 | D44: ='tabla salarial'!AS4 -> 555393.74 | E44: =B44*C44*D44 -> 6664724.9
A45: Topografo | B45: 1 | D45: ='tabla salarial'!AS4 -> 555393.74 | E45: =B45*C45*D45 -> 0
A46: Cadenero 1 | B46: 1.5 | D46: ='tabla salarial'!AS6 -> 407197.8 | E46: =B46*C46*D46 -> 0
A47: Ayudante Tecnico | B47: 2 | C47: 8.46 | D47: ='tabla salarial'!AS7 -> 371571.33 | E47: =B47*C47*D47 -> 6286986.9
A48: Oficial construccion | B48: 1 | C48: 12 | D48: ='tabla salarial'!AS7 -> 371571.33 | E48: =B48*C48*D48 -> 4458856
A49: Auxiliar Administrativo | B49: 1 | C49: 12 | D49: ='tabla salarial'!AS8 -> 355821.88 | E49: =B49*C49*D49 -> 4269862.5
A50: Auxiliar civil | D50: ='tabla salarial'!AS9 -> 382109.06 | E50: =B50*C50*D50 -> 0
A51: 3 | F51: =SUM(E43:E50) -> 28345155
A52: TRANSPORTE | B52: CANT | C52: REND/DIA | D52: TARIFA | E52: VR.PARCIAL
A53: Camión doble cabina | B53: 1 | C53: 2 | D53: =IFERROR(VLOOKUP(A53,[1]!TablaTransporte[#Data],2,FALSE),0) -> 550000 | E53: =B53*C53*D53 -> 1100000
